Workbook
Name \0: [1]DIRIND!$U$1
Name \a: #N/A
Name RECADM: #N/A

Sheet byGOVDetalhado
A1: Arrecadação Direta por Esfera de Governo
A3: Esfera de Governo | B3: 2000 | F3: 2001 | J3: 2002 | N3: 2003 | R3: 2004 | V3: 2005 | Z3: 2006 | AD3: 2007 | AH3: 2008 | AL3: 2009 | AP3: 2010 | AT3: 2011 | AX3: 2012 | BB3: 2013 | BF3: 2014 | BJ3: 2015 | BN3: 2016 | BR3: 2017 | BV3: 2018 | BZ3: 2019 | CD3: 2020 | CH3: 2021 | CL3: 2022 | CP3: 2023 | CT3: 2024
B4: R$ Bilhões | C4: % PIB | D4: % Total | E4: Per capita (R$) | F4: R$ Bilhões | G4: % PIB | H4: % Total | I4: Per capita (R$) | J4: R$ Bilhões | K4: % PIB | L4: % Total | M4: Per capita (R$) | N4: R$ Bilhões | O4: % PIB | P4: % Total | Q4: Per capita (R$) | R4: R$ Bilhões | S4: % PIB | T4: % Total | U4: Per capita (R$) | V4: R$ Bilhões | W4: % PIB | X4: % Total | Y4: Per capita (R$) | Z4: R$ Bilhões | AA4: % PIB | AB4: % Total | AC4: Per capita (R$) | AD4: R$ Bilhões | AE4: % PIB | AF4: % Total | AG4: Per capita (R$) | AH4: R$ Bilhões | AI4: % PIB | AJ4: % Total | AK4: Per capita (R$) | AL4: R$ Bilhões | AM4: % PIB | AN4: % Total | AO4: Per capita (R$) | AP4: R$ Bilhões | AQ4: % PIB | AR4: % Total | AS4: Per capita (R$) | AT4: R$ Bilhões | AU4: % PIB | AV4: % Total | AW4: Per capita (R$) | AX4: R$ Bilhões | AY4: % PIB | AZ4: % Total | BA4: Per capita (R$) | BB4: R$ Bilhões | BC4: % PIB | BD4: % Total | BE4: Per capita (R$) | BF4: R$ Bilhões | BG4: % PIB | BH4: % Total | BI4: Per capita (R$) | BJ4: R$ Bilhões | BK4: % PIB | BL4: % Total | BM4: Per capita (R$) | BN4: R$ Bilhões | BO4: % PIB | BP4: % Total | BQ4: Per capita (R$) | BR4: R$ Bilhões | BS4: % PIB | BT4: % Total | BU4: Per capita (R$) | BV4: R$ Bilhões | BW4: % PIB | BX4: % Total | BY4: Per capita (R$) | BZ4: R$ Bilhões | CA4: % PIB | CB4: % Total | CC4: Per capita (R$) | CD4: R$ Bilhões | CE4: % PIB | CF4: % Total | CG4: Per capita (R$) | CH4: R$ Bilhões | CI4: % PIB | CJ4: % Total | CK4: Per capita (R$) | CL4: R$ Bilhões | CM4: % PIB | CN4: % Total | CO4: Per capita (R$) | CP4: R$ Bilhões | CQ4: % PIB | CR4: % Total | CS4: Per capita (R$) | CT4: R$ Bilhões | CU4: % PIB | CV4: % Total | CW4: Per capita (R$)
A5: PIB | B5: =[2]byGOVDetalhado!B5 -> 1202.3772 | C5: =[2]byGOVDetalhado!C5 -> 0 | D5: =[2]byGOVDetalhado!D5 -> 0 | E5: =[2]byGOVDetalhado!E5 -> 0 | F5: =[3]byGOVDetalhado!B5 -> 1315.755 | G5: =[3]byGOVDetalhado!C5 -> 0 | H5: =[3]byGOVDetalhado!D5 -> 0 | I5: =[3]byGOVDetalhado!E5 -> 0 | J5: =[4]byGOVDetalhado!B5 -> 1488.787 | K5: =[4]byGOVDetalhado!C5 -> 0 | L5: =[4]byGOVDetalhado!D5 -> 0 | M5: =[4]byGOVDetalhado!E5 -> 0 | N5: =[5]byGOVDetalhado!B5 -> 1717.95 | O5: =[5]byGOVDetalhado!C5 -> 0 | P5: =[5]byGOVDetalhado!D5 -> 0 | Q5: =[5]byGOVDetalhado!E5 -> 0 | R5: =[6]byGOVDetalhado!B5 -> 1957.751 | S5: =[6]byGOVDetalhado!C5 -> 0 | T5: =[6]byGOVDetalhado!D5 -> 0 | U5: =[6]byGOVDetalhado!E5 -> 0 | V5: =[7]byGOVDetalhado!B5 -> 2170.585 | W5: =[7]byGOVDetalhado!C5 -> 0 | X5: =[7]byGOVDetalhado!D5 -> 0 | Y5: =[7]byGOVDetalhado!E5 -> 0 | Z5: =[8]byGOVDetalhado!B5 -> 2409.45 | AA5: =[8]byGOVDetalhado!C5 -> 0 | AB5: =[8]byGOVDetalhado!D5 -> 0 | AC5: =[8]byGOVDetalhado!E5 -> 0 | AD5: =[9]byGOVDetalhado!B5 -> 2720.263 | AE5: =[9]byGOVDetalhado!C5 -> 0 | AF5: =[9]byGOVDetalhado!D5 -> 0 | AG5: =[9]byGOVDetalhado!E5 -> 0 | AH5: =[10]byGOVDetalhado!B5 -> 3109.803 | AI5: =[10]byGOVDetalhado!C5 -> 0 | AJ5: =[10]byGOVDetalhado!D5 -> 0 | AK5: =[10]byGOVDetalhado!E5 -> 0 | AL5: =[11]byGOVDetalhado!B5 -> 3333.039 | AM5: =[11]byGOVDetalhado!C5 -> 0 | AN5: =[11]byGOVDetalhado!D5 -> 0 | AO5: =[11]byGOVDetalhado!E5 -> 0 | AP5: =[12]byGOVDetalhado!B5 -> 3885.847 | AQ5: =[12]byGOVDetalhado!C5 -> 0 | AR5: =[12]byGOVDetalhado!D5 -> 0 | AS5: =[12]byGOVDetalhado!E5 -> 0 | AT5: =[13]byGOVDetalhado!B5 -> 4376.382 | AU5: =[13]byGOVDetalhado!C5 -> 0 | AV5: =[13]byGOVDetalhado!D5 -> 0 | AW5: =[13]byGOVDetalhado!E5 -> 0 | AX5: =[14]byGOVDetalhado!B5 -> 4814.76 | AY5: =[14]byGOVDetalhado!C5 -> 0 | AZ5: =[14]byGOVDetalhado!D5 -> 0 | BA5: =[14]byGOVDetalhado!E5 -> 0 | BB5: =[15]byGOVDetalhado!B5 -> 5331.619 | BC5: =[15]byGOVDetalhado!C5 -> 0 | BD5: =[15]byGOVDetalhado!D5 -> 0 | BE5: =[15]byGOVDetalhado!E5 -> 0 | BF5: =[16]byGOVDetalhado!B5 -> 5778.953 | BG5: =[16]byGOVDetalhado!C5 -> 0 | BH5: =[16]byGOVDetalhado!D5 -> 0 | BI5: =[16]byGOVDetalhado!E5 -> 0 | BJ5: =[17]byGOVDetalhado!B5 -> 5995.787 | BK5: =[17]byGOVDetalhado!C5 -> 0 | BL5: =[17]byGOVDetalhado!D5 -> 0 | BM5: =[17]byGOVDetalhado!E5 -> 0 | BN5: =[18]byGOVDetalhado!B5 -> 6267.205 | BO5: =[18]byGOVDetalhado!C5 -> 0 | BP5: =[18]byGOVDetalhado!D5 -> 0 | BQ5: =[18]byGOVDetalhado!E5 -> 0 | BR5: =[19]byGOVDetalhado!B5 -> 6553.8427 | BS5: =[19]byGOVDetalhado!C5 -> 0 | BT5: =[19]byGOVDetalhado!D5 -> 0 | BU5: =[19]byGOVDetalhado!E5 -> 0 | BV5: =[20]byGOVDetalhado!B5 -> 6889.1761 | BW5: =[20]byGOVDetalhado!C5 -> 0 | BX5: =[20]byGOVDetalhado!D5 -> 0 | BY5: =[20]byGOVDetalhado!E5 -> 0 | BZ5: =[21]byGOVDetalhado!B5 -> 7389.131 | CA5: =[21]byGOVDetalhado!C5 -> 0 | CB5: =[21]byGOVDetalhado!D5 -> 0 | CC5: =[21]byGOVDetalhado!E5 -> 0 | CD5: =[22]byGOVDetalhado!B5 -> 7609.597 | CE5: =[22]byGOVDetalhado!C5 -> 0 | CF5: =[22]byGOVDetalhado!D5 -> 0 | CG5: =[22]byGOVDetalhado!E5 -> 0 | CH5: =[23]byGOVDetalhado!B5 -> 8898.727 | CI5: =[23]byGOVDetalhado!C5 -> 0 | CJ5: =[23]byGOVDetalhado!D5 -> 0 | CK5: =[23]byGOVDetalhado!E5 -> 0 | CL5: =[24]byGOVDetalhado!B5 -> 10079.676 | CM5: =[24]byGOVDetalhado!C5 -> 0 | CN5: =[24]byGOVDetalhado!D5 -> 0 | CO5: =[24]byGOVDetalhado!E5 -> 0 | CP5: =[25]byGOVDetalhado!B5 -> 10943.344 | CQ5: =[25]byGOVDetalhado!C5 -> 0 | CR5: =[25]byGOVDetalhado!D5 -> 0 | CS5: =[25]byGOVDetalhado!E5 -> 0 | CT5: =[26]byGOVDetalhado!B5 -> 11744.709 | CU5: =[26]byGOVDetalhado!C5 -> 0 | CV5: =[26]byGOVDetalhado!D5 -> 0 | CW5: =[26]byGOVDetalhado!E5 -> 0
A6: População | B6: =[2]byGOVDetalhado!B6 -> 173448346 | C6: =[2]byGOVDetalhado!C6 -> 0 | D6: =[2]byGOVDetalhado!D6 -> 0 | E6: =[2]byGOVDetalhado!E6 -> 0 | F6: =[3]byGOVDetalhado!B6 -> 173448346 | G6: =[3]byGOVDetalhado!C6 -> 0 | H6: =[3]byGOVDetalhado!D6 -> 0 | I6: =[3]byGOVDetalhado!E6 -> 0 | J6: =[4]byGOVDetalhado!B6 -> 178276128 | K6: =[4]byGOVDetalhado!C6 -> 0 | L6: =[4]byGOVDetalhado!D6 -> 0 | M6: =[4]byGOVDetalhado!E6 -> 0 | N6: =[5]byGOVDetalhado!B6 -> 180619108 | O6: =[5]byGOVDetalhado!C6 -> 0 | P6: =[5]byGOVDetalhado!D6 -> 0 | Q6: =[5]byGOVDetalhado!E6 -> 0 | R6: =[6]byGOVDetalhado!B6 -> 182911487 | S6: =[6]byGOVDetalhado!C6 -> 0 | T6: =[6]byGOVDetalhado!D6 -> 0 | U6: =[6]byGOVDetalhado!E6 -> 0 | V6: =[7]byGOVDetalhado!B6 -> 185150806 | W6: =[7]byGOVDetalhado!C6 -> 0 | X6: =[7]byGOVDetalhado!D6 -> 0 | Y6: =[7]byGOVDetalhado!E6 -> 0 | Z6: =[8]byGOVDetalhado!B6 -> 187335137 | AA6: =[8]byGOVDetalhado!C6 -> 0 | AB6: =[8]byGOVDetalhado!D6 -> 0 | AC6: =[8]byGOVDetalhado!E6 -> 0 | AD6: =[9]byGOVDetalhado!B6 -> 189462755 | AE6: =[9]byGOVDetalhado!C6 -> 0 | AF6: =[9]byGOVDetalhado!D6 -> 0 | AG6: =[9]byGOVDetalhado!E6 -> 0 | AH6: =[10]byGOVDetalhado!B6 -> 191532439 | AI6: =[10]byGOVDetalhado!C6 -> 0 | AJ6: =[10]byGOVDetalhado!D6 -> 0 | AK6: =[10]byGOVDetalhado!E6 -> 0 | AL6: =[11]byGOVDetalhado!B6 -> 193543969 | AM6: =[11]byGOVDetalhado!C6 -> 0 | AN6: =[11]byGOVDetalhado!D6 -> 0 | AO6: =[11]byGOVDetalhado!E6 -> 0 | AP6: =[12]byGOVDetalhado!B6 -> 195497797 | AQ6: =[12]byGOVDetalhado!C6 -> 0 | AR6: =[12]byGOVDetalhado!D6 -> 0 | AS6: =[12]byGOVDetalhado!E6 -> 0 | AT6: =[13]byGOVDetalhado!B6 -> 197397018 | AU6: =[13]byGOVDetalhado!C6 -> 0 | AV6: =[13]byGOVDetalhado!D6 -> 0 | AW6: =[13]byGOVDetalhado!E6 -> 0 | AX6: =[14]byGOVDetalhado!B6 -> 199242462 | AY6: =[14]byGOVDetalhado!C6 -> 0 | AZ6: =[14]byGOVDetalhado!D6 -> 0 | BA6: =[14]byGOVDetalhado!E6 -> 0 | BB6: =[15]byGOVDetalhado!B6 -> 201032714 | BC6: =[15]byGOVDetalhado!C6 -> 0 | BD6: =[15]byGOVDetalhado!D6 -> 0 | BE6: =[15]byGOVDetalhado!E6 -> 0 | BF6: =[16]byGOVDetalhado!B6 -> 202768562 | BG6: =[16]byGOVDetalhado!C6 -> 0 | BH6: =[16]byGOVDetalhado!D6 -> 0 | BI6: =[16]byGOVDetalhado!E6 -> 0 | BJ6: =[17]byGOVDetalhado!B6 -> 204450649 | BK6: =[17]byGOVDetalhado!C6 -> 0 | BL6: =[17]byGOVDetalhado!D6 -> 0 | BM6: =[17]byGOVDetalhado!E6 -> 0 | BN6: =[18]byGOVDetalhado!B6 -> 206081432 | BO6: =[18]byGOVDetalhado!C6 -> 0 | BP6: =[18]byGOVDetalhado!D6 -> 0 | BQ6: =[18]byGOVDetalhado!E6 -> 0 | BR6: =[19]byGOVDetalhado!B6 -> 207660929 | BS6: =[19]byGOVDetalhado!C6 -> 0 | BT6: =[19]byGOVDetalhado!D6 -> 0 | BU6: =[19]byGOVDetalhado!E6 -> 0 | BV6: =[20]byGOVDetalhado!B6 -> 208494900 | BW6: =[20]byGOVDetalhado!C6 -> 0 | BX6: =[20]byGOVDetalhado!D6 -> 0 | BY6: =[20]byGOVDetalhado!E6 -> 0 | BZ6: =[21]byGOVDetalhado!B6 -> 210147125 | CA6: =[21]byGOVDetalhado!C6 -> 0 | CB6: =[21]byGOVDetalhado!D6 -> 0 | CC6: =[21]byGOVDetalhado!E6 -> 0 | CD6: =[22]byGOVDetalhado!B6 -> 211755692 | CE6: =[22]byGOVDetalhado!C6 -> 0 | CF6: =[22]byGOVDetalhado!D6 -> 0 | CG6: =[22]byGOVDetalhado!E6 -> 0 | CH6: =[23]byGOVDetalhado!B6 -> 213317639 | CI6: =[23]byGOVDetalhado!C6 -> 0 | CJ6: =[23]byGOVDetalhado!D6 -> 0 | CK6: =[23]byGOVDetalhado!E6 -> 0 | CL6: =[24]byGOVDetalhado!B6 -> 203080756 | CM6: =[24]byGOVDetalhado!C6 -> 0 | CN6: =[24]byGOVDetalhado!D6 -> 0 | CO6: =[24]byGOVDetalhado!E6 -> 0 | CP6: =[25]byGOVDetalhado!B6 -> 207832253 | CQ6: =[25]byGOVDetalhado!C6 -> 0 | CR6: =[25]byGOVDetalhado!D6 -> 0 | CS6: =[25]byGOVDetalhado!E6 -> 0 | CT6: =[26]byGOVDetalhado!B6 -> 212583750 | CU6: =[26]byGOVDetalhado!C6 -> 0 | CV6: =[26]byGOVDetalhado!D6 -> 0 | CW6: =[26]byGOVDetalhado!E6 -> 0
A7: TOTAL | B7: =[2]byGOVDetalhado!B7 -> 367.44515 | C7: =[2]byGOVDetalhado!C7 -> 30.559889 | D7: =[2]byGOVDetalhado!D7 -> 100 | E7: =[2]byGOVDetalhado!E7 -> 2118.4702 | F7: =[3]byGOVDetalhado!B7 -> 421.64663 | G7: =[3]byGOVDetalhado!C7 -> 32.045984 | H7: =[3]byGOVDetalhado!D7 -> 100 | I7: =[3]byGOVDetalhado!E7 -> 2430.9637 | J7: =[4]byGOVDetalhado!B7 -> 495.42481 | K7: =[4]byGOVDetalhado!C7 -> 33.277078 | L7: =[4]byGOVDetalhado!D7 -> 100 | M7: =[4]byGOVDetalhado!E7 -> 2778.9745 | N7: =[5]byGOVDetalhado!B7 -> 560.01487 | O7: =[5]byGOVDetalhado!C7 -> 32.597856 | P7: =[5]byGOVDetalhado!D7 -> 100 | Q7: =[5]byGOVDetalhado!E7 -> 3100.5295 | R7: =[6]byGOVDetalhado!B7 -> 658.25296 | S7: =[6]byGOVDetalhado!C7 -> 33.622915 | T7: =[6]byGOVDetalhado!D7 -> 100 | U7: =[6]byGOVDetalhado!E7 -> 3598.7513 | V7: =[7]byGOVDetalhado!B7 -> 754.18429 | W7: =[7]byGOVDetalhado!C7 -> 34.74567 | X7: =[7]byGOVDetalhado!D7 -> 100 | Y7: =[7]byGOVDetalhado!E7 -> 4073.3514 | Z7: =[8]byGOVDetalhado!B7 -> 829.53577 | AA7: =[8]byGOVDetalhado!C7 -> 34.428428 | AB7: =[8]byGOVDetalhado!D7 -> 100 | AC7: =[8]byGOVDetalhado!E7 -> 4428.0842 | AD7: =[9]byGOVDetalhado!B7 -> 940.81948 | AE7: =[9]byGOVDetalhado!C7 -> 34.585607 | AF7: =[9]byGOVDetalhado!D7 -> 100 | AG7: =[9]byGOVDetalhado!E7 -> 4965.7226 | AH7: =[10]byGOVDetalhado!B7 -> 1080.8859 | AI7: =[10]byGOVDetalhado!C7 -> 34.757375 | AJ7: =[10]byGOVDetalhado!D7 -> 100 | AK7: =[10]byGOVDetalhado!E7 -> 5643.3568 | AL7: =[11]byGOVDetalhado!B7 -> 1105.3741 | AM7: =[11]byGOVDetalhado!C7 -> 33.164151 | AN7: =[11]byGOVDetalhado!D7 -> 100 | AO7: =[11]byGOVDetalhado!E7 -> 5711.2298 | AP7: =[12]byGOVDetalhado!B7 -> 1291.3621 | AQ7: =[12]byGOVDetalhado!C7 -> 33.232448 | AR7: =[12]byGOVDetalhado!D7 -> 100 | AS7: =[12]byGOVDetalhado!E7 -> 6605.5071 | AT7: =[13]byGOVDetalhado!B7 -> 1491.6039 | AU7: =[13]byGOVDetalhado!C7 -> 34.083038 | AV7: =[13]byGOVDetalhado!D7 -> 100 | AW7: =[13]byGOVDetalhado!E7 -> 7556.3651 | AX7: =[14]byGOVDetalhado!B7 -> 1638.1111 | AY7: =[14]byGOVDetalhado!C7 -> 34.022696 | AZ7: =[14]byGOVDetalhado!D7 -> 100 | BA7: =[14]byGOVDetalhado!E7 -> 8221.6969 | BB7: =[15]byGOVDetalhado!B7 -> 1792.2461 | BC7: =[15]byGOVDetalhado!C7 -> 33.615419 | BD7: =[15]byGOVDetalhado!D7 -> 100 | BE7: =[15]byGOVDetalhado!E7 -> 8915.1961 | BF7: =[16]byGOVDetalhado!B7 -> 1899.7813 | BG7: =[16]byGOVDetalhado!C7 -> 32.874143 | BH7: =[16]byGOVDetalhado!D7 -> 100 | BI7: =[16]byGOVDetalhado!E7 -> 9369.2102 | BJ7: =[17]byGOVDetalhado!B7 -> 1969.031 | BK7: =[17]byGOVDetalhado!C7 -> 32.840243 | BL7: =[17]byGOVDetalhado!D7 -> 100 | BM7: =[17]byGOVDetalhado!E7 -> 9630.8376 | BN7: =[18]byGOVDetalhado!B7 -> 2086.1565 | BO7: =[18]byGOVDetalhado!C7 -> 33.286872 | BP7: =[18]byGOVDetalhado!D7 -> 100 | BQ7: =[18]byGOVDetalhado!E7 -> 10122.972 | BR7: =[19]byGOVDetalhado!B7 -> 2203.4045 | BS7: =[19]byGOVDetalhado!C7 -> 33.620039 | BT7: =[19]byGOVDetalhado!D7 -> 100 | BU7: =[19]byGOVDetalhado!E7 -> 10610.588 | BV7: =[20]byGOVDetalhado!B7 -> 2372.7995 | BW7: =[20]byGOVDetalhado!C7 -> 34.442428 | BX7: =[20]byGOVDetalhado!D7 -> 100 | BY7: =[20]byGOVDetalhado!E7 -> 11380.612 | BZ7: =[21]byGOVDetalhado!B7 -> 2496.9243 | CA7: =[21]byGOVDetalhado!C7 -> 33.791853 | CB7: =[21]byGOVDetalhado!D7 -> 100 | CC7: =[21]byGOVDetalhado!E7 -> 11881.791 | CD7: =[22]byGOVDetalhado!B7 -> 2451.5573 | CE7: =[22]byGOVDetalhado!C7 -> 32.216651 | CF7: =[22]byGOVDetalhado!D7 -> 100 | CG7: =[22]byGOVDetalhado!E7 -> 11577.291 | CH7: =[23]byGOVDetalhado!B7 -> 3060.9656 | CI7: =[23]byGOVDetalhado!C7 -> 34.397792 | CJ7: =[23]byGOVDetalhado!D7 -> 100 | CK7: =[23]byGOVDetalhado!E7 -> 14349.332 | CL7: =[24]byGOVDetalhado!B7 -> 3518.4966 | CM7: =[24]byGOVDetalhado!C7 -> 34.906843 | CN7: =[24]byGOVDetalhado!D7 -> 100 | CO7: =[24]byGOVDetalhado!E7 -> 17325.603 | CP7: =[25]byGOVDetalhado!B7 -> 3783.9875 | CQ7: =[25]byGOVDetalhado!C7 -> 34.577982 | CR7: =[25]byGOVDetalhado!D7 -> 100 | CS7: =[25]byGOVDetalhado!E7 -> 18206.931 | CT7: =[26]byGOVDetalhado!B7 -> 4222.222 | CU7: =[26]byGOVDetalhado!C7 -> 35.949992 | CV7: =[26]byGOVDetalhado!D7 -> 100 | CW7: =[26]byGOVDetalhado!E7 -> 19861.452
B8: =[2]byGOVDetalhado!B8 -> 0 | C8: =[2]byGOVDetalhado!C8 -> 0 | D8: =[2]byGOVDetalhado!D8 -> 0 | E8: =[2]byGOVDetalhado!E8 -> 0 | F8: =[3]byGOVDetalhado!B8 -> 0 | G8: =[3]byGOVDetalhado!C8 -> 0 | H8: =[3]byGOVDetalhado!D8 -> 0 | I8: =[3]byGOVDetalhado!E8 -> 0 | J8: =[4]byGOVDetalhado!B8 -> 0 | K8: =[4]byGOVDetalhado!C8 -> 0 | L8: =[4]byGOVDetalhado!D8 -> 0 | M8: =[4]byGOVDetalhado!E8 -> 0 | N8: =[5]byGOVDetalhado!B8 -> 0 | O8: =[5]byGOVDetalhado!C8 -> 0 | P8: =[5]byGOVDetalhado!D8 -> 0 | Q8: =[5]byGOVDetalhado!E8 -> 0 | R8: =[6]byGOVDetalhado!B8 -> 0 | S8: =[6]byGOVDetalhado!C8 -> 0 | T8: =[6]byGOVDetalhado!D8 -> 0 | U8: =[6]byGOVDetalhado!E8 -> 0 | V8: =[7]byGOVDetalhado!B8 -> 0 | W8: =[7]byGOVDetalhado!C8 -> 0 | X8: =[7]byGOVDetalhado!D8 -> 0 | Y8: =[7]byGOVDetalhado!E8 -> 0 | Z8: =[8]byGOVDetalhado!B8 -> 0 | AA8: =[8]byGOVDetalhado!C8 -> 0 | AB8: =[8]byGOVDetalhado!D8 -> 0 | AC8: =[8]byGOVDetalhado!E8 -> 0 | AD8: =[9]byGOVDetalhado!B8 -> 0 | AE8: =[9]byGOVDetalhado!C8 -> 0 | AF8: =[9]byGOVDetalhado!D8 -> 0 | AG8: =[9]byGOVDetalhado!E8 -> 0 | AH8: =[10]byGOVDetalhado!B8 -> 0 | AI8: =[10]byGOVDetalhado!C8 -> 0 | AJ8: =[10]byGOVDetalhado!D8 -> 0 | AK8: =[10]byGOVDetalhado!E8 -> 0 | AL8: =[11]byGOVDetalhado!B8 -> 0 | AM8: =[11]byGOVDetalhado!C8 -> 0 | AN8: =[11]byGOVDetalhado!D8 -> 0 | AO8: =[11]byGOVDetalhado!E8 -> 0 | AP8: =[12]byGOVDetalhado!B8 -> 0 | AQ8: =[12]byGOVDetalhado!C8 -> 0 | AR8: =[12]byGOVDetalhado!D8 -> 0 | AS8: =[12]byGOVDetalhado!E8 -> 0 | AT8: =[13]byGOVDetalhado!B8 -> 0 | AU8: =[13]byGOVDetalhado!C8 -> 0 | AV8: =[13]byGOVDetalhado!D8 -> 0 | AW8: =[13]byGOVDetalhado!E8 -> 0 | AX8: =[14]byGOVDetalhado!B8 -> 0 | AY8: =[14]byGOVDetalhado!C8 -> 0 | AZ8: =[14]byGOVDetalhado!D8 -> 0 | BA8: =[14]byGOVDetalhado!E8 -> 0 | BB8: =[15]byGOVDetalhado!B8 -> 0 | BC8: =[15]byGOVDetalhado!C8 -> 0 | BD8: =[15]byGOVDetalhado!D8 -> 0 | BE8: =[15]byGOVDetalhado!E8 -> 0 | BF8: =[16]byGOVDetalhado!B8 -> 0 | BG8: =[16]byGOVDetalhado!C8 -> 0 | BH8: =[16]byGOVDetalhado!D8 -> 0 | BI8: =[16]byGOVDetalhado!E8 -> 0 | BJ8: =[17]byGOVDetalhado!B8 -> 0 | BK8: =[17]byGOVDetalhado!C8 -> 0 | BL8: =[17]byGOVDetalhado!D8 -> 0 | BM8: =[17]byGOVDetalhado!E8 -> 0 | BN8: =[18]byGOVDetalhado!B8 -> 0 | BO8: =[18]byGOVDetalhado!C8 -> 0 | BP8: =[18]byGOVDetalhado!D8 -> 0 | BQ8: =[18]byGOVDetalhado!E8 -> 0 | BR8: =[19]byGOVDetalhado!B8 -> 0 | BS8: =[19]byGOVDetalhado!C8 -> 0 | BT8: =[19]byGOVDetalhado!D8 -> 0 | BU8: =[19]byGOVDetalhado!E8 -> 0 | BV8: =[20]byGOVDetalhado!B8 -> 0 | BW8: =[20]byGOVDetalhado!C8 -> 0 | BX8: =[20]byGOVDetalhado!D8 -> 0 | BY8: =[20]byGOVDetalhado!E8 -> 0 | BZ8: =[21]byGOVDetalhado!B8 -> 0 | CA8: =[21]byGOVDetalhado!C8 -> 0 | CB8: =[21]byGOVDetalhado!D8 -> 0 | CC8: =[21]byGOVDetalhado!E8 -> 0 | CD8: =[22]byGOVDetalhado!B8 -> 0 | CE8: =[22]byGOVDetalhado!C8 -> 0 | CF8: =[22]byGOVDetalhado!D8 -> 0 | CG8: =[22]byGOVDetalhado!E8 -> 0 | CH8: =[23]byGOVDetalhado!B8 -> 0 | CI8: =[23]byGOVDetalhado!C8 -> 0 | CJ8: =[23]byGOVDetalhado!D8 -> 0 | CK8: =[23]byGOVDetalhado!E8 -> 0 | CL8: =[24]byGOVDetalhado!B8 -> 0 | CM8: =[24]byGOVDetalhado!C8 -> 0 | CN8: =[24]byGOVDetalhado!D8 -> 0 | CO8: =[24]byGOVDetalhado!E8 -> 0 | CP8: =[25]byGOVDetalhado!B8 -> 0 | CQ8: =[25]byGOVDetalhado!C8 -> 0 | CR8: =[25]byGOVDetalhado!D8 -> 0 | CS8: =[25]byGOVDetalhado!E8 -> 0 | CT8: =[26]byGOVDetalhado!B8 -> 0 | CU8: =[26]byGOVDetalhado!C8 -> 0 | CV8: =[26]byGOVDetalhado!D8 -> 0 | CW8: =[26]byGOVDetalhado!E8 -> 0
A9: UNIÃO | B9: =[2]byGOVDetalhado!B9 -> 245.03204 | C9: =[2]byGOVDetalhado!C9 -> 20.378966 | D9: =[2]byGOVDetalhado!D9 -> 66.685339 | E9: =[2]byGOVDetalhado!E9 -> 1412.709 | F9: =[3]byGOVDetalhado!B9 -> 281.98373 | G9: =[3]byGOVDetalhado!C9 -> 21.431325 | H9: =[3]byGOVDetalhado!D9 -> 66.876788 | I9: =[3]byGOVDetalhado!E9 -> 1625.7505 | J9: =[4]byGOVDetalhado!B9 -> 337.12695 | K9: =[4]byGOVDetalhado!C9 -> 22.644404 | L9: =[4]byGOVDetalhado!D9 -> 68.048055 | M9: =[4]byGOVDetalhado!E9 -> 1891.0381 | N9: =[5]byGOVDetalhado!B9 -> 377.00184 | O9: =[5]byGOVDetalhado!C9 -> 21.944867 | P9: =[5]byGOVDetalhado!D9 -> 67.319971 | Q9: =[5]byGOVDetalhado!E9 -> 2087.2755 | R9: =[6]byGOVDetalhado!B9 -> 443.44386 | S9: =[6]byGOVDetalhado!C9 -> 22.650677 | T9: =[6]byGOVDetalhado!D9 -> 67.366786 | U9: =[6]byGOVDetalhado!E9 -> 2424.3631 | V9: =[7]byGOVDetalhado!B9 -> 515.78386 | W9: =[7]byGOVDetalhado!C9 -> 23.762435 | X9: =[7]byGOVDetalhado!D9 -> 68.389631 | Y9: =[7]byGOVDetalhado!E9 -> 2785.75 | Z9: =[8]byGOVDetalhado!B9 -> 564.59653 | AA9: =[8]byGOVDetalhado!C9 -> 23.43259 | AB9: =[8]byGOVDetalhado!D9 -> 68.061747 | AC9: =[8]byGOVDetalhado!E9 -> 3013.8315 | AD9: =[9]byGOVDetalhado!B9 -> 646.5957 | AE9: =[9]byGOVDetalhado!C9 -> 23.769602 | AF9: =[9]byGOVDetalhado!D9 -> 68.726862 | AG9: =[9]byGOVDetalhado!E9 -> 3412.7853 | AH9: =[10]byGOVDetalhado!B9 -> 738.74107 | AI9: =[10]byGOVDetalhado!C9 -> 23.755237 | AJ9: =[10]byGOVDetalhado!D9 -> 68.345889 | AK9: =[10]byGOVDetalhado!E9 -> 3857.0024 | AL9: =[11]byGOVDetalhado!B9 -> 745.83668 | AM9: =[11]byGOVDetalhado!C9 -> 22.377076 | AN9: =[11]byGOVDetalhado!D9 -> 67.47369 | AO9: =[11]byGOVDetalhado!E9 -> 3853.5775 | AP9: =[12]byGOVDetalhado!B9 -> 868.73679 | AQ9: =[12]byGOVDetalhado!C9 -> 22.356433 | AR9: =[12]byGOVDetalhado!D9 -> 67.272905 | AS9: =[12]byGOVDetalhado!E9 -> 4443.7165 | AT9: =[13]byGOVDetalhado!B9 -> 1017.0071 | AU9: =[13]byGOVDetalhado!C9 -> 23.238536 | AV9: =[13]byGOVDetalhado!D9 -> 68.182114 | AW9: =[13]byGOVDetalhado!E9 -> 5152.0895 | AX9: =[14]byGOVDetalhado!B9 -> 1111.1552 | AY9: =[14]byGOVDetalhado!C9 -> 23.078101 | AZ9: =[14]byGOVDetalhado!D9 -> 67.831488 | BA9: =[14]byGOVDetalhado!E9 -> 5576.8994 | BB9: =[15]byGOVDetalhado!B9 -> 1208.3874 | BC9: =[15]byGOVDetalhado!C9 -> 22.66455 | BD9: =[15]byGOVDetalhado!D9 -> 67.423076 | BE9: =[15]byGOVDetalhado!E9 -> 6010.8995 | BF9: =[16]byGOVDetalhado!B9 -> 1266.193 | BG9: =[16]byGOVDetalhado!C9 -> 21.910422 | BH9: =[16]byGOVDetalhado!D9 -> 66.649409 | BI9: =[16]byGOVDetalhado!E9 -> 6244.5232 | BJ9: =[17]byGOVDetalhado!B9 -> 1299.1238 | BK9: =[17]byGOVDetalhado!C9 -> 21.667278 | BL9: =[17]byGOVDetalhado!D9 -> 65.977824 | BM9: =[17]byGOVDetalhado!E9 -> 6354.2171 | BN9: =[18]byGOVDetalhado!B9 -> 1374.5454 | BO9: =[18]byGOVDetalhado!C9 -> 21.932351 | BP9: =[18]byGOVDetalhado!D9 -> 65.888892 | BQ9: =[18]byGOVDetalhado!E9 -> 6669.9138 | BR9: =[19]byGOVDetalhado!B9 -> 1439.7472 | BS9: =[19]byGOVDetalhado!C9 -> 21.967986 | BT9: =[19]byGOVDetalhado!D9 -> 65.341941 | BU9: =[19]byGOVDetalhado!E9 -> 6933.1638 | BV9: =[20]byGOVDetalhado!B9 -> 1550.492 | BW9: =[20]byGOVDetalhado!C9 -> 22.506204 | BX9: =[20]byGOVDetalhado!D9 -> 65.344418 | BY9: =[20]byGOVDetalhado!E9 -> 7436.5946 | BZ9: =[21]byGOVDetalhado!B9 -> 1610.6225 | CA9: =[21]byGOVDetalhado!C9 -> 21.797184 | CB9: =[21]byGOVDetalhado!D9 -> 64.504259 | CC9: =[21]byGOVDetalhado!E9 -> 7664.2615 | CD9: =[22]byGOVDetalhado!B9 -> 1541.6976 | CE9: =[22]byGOVDetalhado!C9 -> 20.259911 | CF9: =[22]byGOVDetalhado!D9 -> 62.886457 | CG9: =[22]byGOVDetalhado!E9 -> 7280.5484 | CH9: =[23]byGOVDetalhado!B9 -> 1962.2415 | CI9: =[23]byGOVDetalhado!C9 -> 22.050811 | CJ9: =[23]byGOVDetalhado!D9 -> 64.105309 | CK9: =[23]byGOVDetalhado!E9 -> 9198.6836 | CL9: =[24]byGOVDetalhado!B9 -> 2292.7229 | CM9: =[24]byGOVDetalhado!C9 -> 22.745998 | CN9: =[24]byGOVDetalhado!D9 -> 65.162002 | CO9: =[24]byGOVDetalhado!E9 -> 11289.71 | CP9: =[25]byGOVDetalhado!B9 -> 2470.2827 | CQ9: =[25]byGOVDetalhado!C9 -> 22.573381 | CR9: =[25]byGOVDetalhado!D9 -> 65.282528 | CS9: =[25]byGOVDetalhado!E9 -> 11885.945 | CT9: =[26]byGOVDetalhado!B9 -> 2735.2139 | CU9: =[26]byGOVDetalhado!C9 -> 23.288903 | CV9: =[26]byGOVDetalhado!D9 -> 64.781386 | CW9: =[26]byGOVDetalhado!E9 -> 12866.524
A10: IR | B10: =[2]byGOVDetalhado!B10 -> 48.05103 | C10: =[2]byGOVDetalhado!C10 -> 3.9963357 | D10: =[2]byGOVDetalhado!D10 -> 13.077062 | E10: =[2]byGOVDetalhado!E10 -> 277.03366 | F10: =[3]byGOVDetalhado!B10 -> 58.452662 | G10: =[3]byGOVDetalhado!C10 -> 4.4425187 | H10: =[3]byGOVDetalhado!D10 -> 13.86295 | I10: =[3]byGOVDetalhado!E10 -> 337.00328 | J10: =[4]byGOVDetalhado!B10 -> 75.551116 | K10: =[4]byGOVDetalhado!C10 -> 5.074676 | L10: =[4]byGOVDetalhado!D10 -> 15.249764 | M10: =[4]byGOVDetalhado!E10 -> 423.78706 | N10: =[5]byGOVDetalhado!B10 -> 82.42169 | O10: =[5]byGOVDetalhado!C10 -> 4.7976769 | P10: =[5]byGOVDetalhado!D10 -> 14.717768 | Q10: =[5]byGOVDetalhado!E10 -> 456.32874 | R10: =[6]byGOVDetalhado!B10 -> 90.362734 | S10: =[6]byGOVDetalhado!C10 -> 4.6156398 | T10: =[6]byGOVDetalhado!D10 -> 13.727661 | U10: =[6]byGOVDetalhado!E10 -> 494.02438 | V10: =[7]byGOVDetalhado!B10 -> 112.57153 | W10: =[7]byGOVDetalhado!C10 -> 5.18623 | X10: =[7]byGOVDetalhado!D10 -> 14.926263 | Y10: =[7]byGOVDetalhado!E10 -> 607.99914 | Z10: =[8]byGOVDetalhado!B10 -> 122.18487 | AA10: =[8]byGOVDetalhado!C10 -> 5.0710689 | AB10: =[8]byGOVDetalhado!D10 -> 14.729307 | AC10: =[8]byGOVDetalhado!E10 -> 652.22612 | AD10: =[9]byGOVDetalhado!B10 -> 143.96079 | AE10: =[9]byGOVDetalhado!C10 -> 5.2921644 | AF10: =[9]byGOVDetalhado!D10 -> 15.301638 | AG10: =[9]byGOVDetalhado!E10 -> 759.83689 | AH10: =[10]byGOVDetalhado!B10 -> 174.29937 | AI10: =[10]byGOVDetalhado!C10 -> 5.6048364 | AJ10: =[10]byGOVDetalhado!D10 -> 16.125603 | AK10: =[10]byGOVDetalhado!E10 -> 910.02532 | AL10: =[11]byGOVDetalhado!B10 -> 172.60142 | AM10: =[11]byGOVDetalhado!C10 -> 5.1784998 | AN10: =[11]byGOVDetalhado!D10 -> 15.614752 | AO10: =[11]byGOVDetalhado!E10 -> 891.79435 | AP10: =[12]byGOVDetalhado!B10 -> 190.54988 | AQ10: =[12]byGOVDetalhado!C10 -> 4.9036896 | AR10: =[12]byGOVDetalhado!D10 -> 14.755728 | AS10: =[12]byGOVDetalhado!E10 -> 974.69065 | AT10: =[13]byGOVDetalhado!B10 -> 231.29945 | AU10: =[13]byGOVDetalhado!C10 -> 5.2851751 | AV10: =[13]byGOVDetalhado!D10 -> 15.506761 | AW10: =[13]byGOVDetalhado!E10 -> 1171.7474 | AX10: =[14]byGOVDetalhado!B10 -> 235.64137 | AY10: =[14]byGOVDetalhado!C10 -> 4.8941457 | AZ10: =[14]byGOVDetalhado!D10 -> 14.384944 | BA10: =[14]byGOVDetalhado!E10 -> 1182.6865 | BB10: =[15]byGOVDetalhado!B10 -> 259.61411 | BC10: =[15]byGOVDetalhado!C10 -> 4.8693297 | BD10: =[15]byGOVDetalhado!D10 -> 14.485405 | BE10: =[15]byGOVDetalhado!E10 -> 1291.4023 | BF10: =[16]byGOVDetalhado!B10 -> 277.4003 | BG10: =[16]byGOVDetalhado!C10 -> 4.8001827 | BH10: =[16]byGOVDetalhado!D10 -> 14.601697 | BI10: =[16]byGOVDetalhado!E10 -> 1368.0637 | BJ10: =[17]byGOVDetalhado!B10 -> 294.59894 | BK10: =[17]byGOVDetalhado!C10 -> 4.9134324 | BL10: =[17]byGOVDetalhado!D10 -> 14.96162 | BM10: =[17]byGOVDetalhado!E10 -> 1440.9293 | BN10: =[18]byGOVDetalhado!B10 -> 333.76771 | BO10: =[18]byGOVDetalhado!C10 -> 5.325623 | BP10: =[18]byGOVDetalhado!D10 -> 15.999169 | BQ10: =[18]byGOVDetalhado!E10 -> 1619.5914 | BR10: =[19]byGOVDetalhado!B10 -> 352.07921 | BS10: =[19]byGOVDetalhado!C10 -> 5.3721035 | BT10: =[19]byGOVDetalhado!D10 -> 15.978874 | BU10: =[19]byGOVDetalhado!E10 -> 1695.4524 | BV10: =[20]byGOVDetalhado!B10 -> 350.80171 | BW10: =[20]byGOVDetalhado!C10 -> 5.0920705 | BX10: =[20]byGOVDetalhado!D10 -> 14.784296 | BY10: =[20]byGOVDetalhado!E10 -> 1682.5433 | BZ10: =[21]byGOVDetalhado!B10 -> 388.1289 | CA10: =[21]byGOVDetalhado!C10 -> 5.2527003 | CB10: =[21]byGOVDetalhado!D10 -> 15.54428 | CC10: =[21]byGOVDetalhado!E10 -> 1846.9389 | CD10: =[22]byGOVDetalhado!B10 -> 374.91586 | CE10: =[22]byGOVDetalhado!C10 -> 4.9268819 | CF10: =[22]byGOVDetalhado!D10 -> 15.292967 | CG10: =[22]byGOVDetalhado!E10 -> 1770.5114 | CH10: =[23]byGOVDetalhado!B10 -> 506.31434 | CI10: =[23]byGOVDetalhado!C10 -> 5.689739 | CJ10: =[23]byGOVDetalhado!D10 -> 16.541001 | CK10: =[23]byGOVDetalhado!E10 -> 2373.5231 | CL10: =[24]byGOVDetalhado!B10 -> 653.46837 | CM10: =[24]byGOVDetalhado!C10 -> 6.4830295 | CN10: =[24]byGOVDetalhado!D10 -> 18.572374 | CO10: =[24]byGOVDetalhado!E10 -> 3217.7759 | CP10: =[25]byGOVDetalhado!B10 -> 731.63772 | CQ10: =[25]byGOVDetalhado!C10 -> 6.6856869 | CR10: =[25]byGOVDetalhado!D10 -> 19.335099 | CS10: =[25]byGOVDetalhado!E10 -> 3520.3281 | CT10: =[26]byGOVDetalhado!B10 -> 764.55033 | CU10: =[26]byGOVDetalhado!C10 -> 6.5097427 | CV10: =[26]byGOVDetalhado!D10 -> 18.107772 | CW10: =[26]byGOVDetalhado!E10 -> 3596.4665
A11: IPI | B11: =[2]byGOVDetalhado!B11 -> 17.553938 | C11: =[2]byGOVDetalhado!C11 -> 1.459936 | D11: =[2]byGOVDetalhado!D11 -> 4.7772949 | E11: =[2]byGOVDetalhado!E11 -> 101.20557 | F11: =[3]byGOVDetalhado!B11 -> 18.83749 | G11: =[3]byGOVDetalhado!C11 -> 1.4316867 | H11: =[3]byGOVDetalhado!D11 -> 4.4676011 | I11: =[3]byGOVDetalhado!E11 -> 108.60576 | J11: =[4]byGOVDetalhado!B11 -> 18.471562 | K11: =[4]byGOVDetalhado!C11 -> 1.2407122 | L11: =[4]byGOVDetalhado!D11 -> 3.7284289 | M11: =[4]byGOVDetalhado!E11 -> 103.61209 | N11: =[5]byGOVDetalhado!B11 -> 17.923868 | O11: =[5]byGOVDetalhado!C11 -> 1.0433289 | P11: =[5]byGOVDetalhado!D11 -> 3.2006058 | Q11: =[5]byGOVDetalhado!E11 -> 99.235725 | R11: =[6]byGOVDetalhado!B11 -> 21.059034 | S11: =[6]byGOVDetalhado!C11 -> 1.0756748 | T11: =[6]byGOVDetalhado!D11 -> 3.1992312 | U11: =[6]byGOVDetalhado!E11 -> 115.13238 | V11: =[7]byGOVDetalhado!B11 -> 24.061421 | W11: =[7]byGOVDetalhado!C11 -> 1.1085224 | X11: =[7]byGOVDetalhado!D11 -> 3.1903901 | Y11: =[7]byGOVDetalhado!E11 -> 129.9558 | Z11: =[8]byGOVDetalhado!B11 -> 26.780064 | AA11: =[8]byGOVDetalhado!C11 -> 1.1114596 | AB11: =[8]byGOVDetalhado!D11 -> 3.2283194 | AC11: =[8]byGOVDetalhado!E11 -> 142.9527 | AD11: =[9]byGOVDetalhado!B11 -> 31.240028 | AE11: =[9]byGOVDetalhado!C11 -> 1.1484194 | AF11: =[9]byGOVDetalhado!D11 -> 3.3205125 | AG11: =[9]byGOVDetalhado!E11 -> 164.88744 | AH11: =[10]byGOVDetalhado!B11 -> 36.695285 | AI11: =[10]byGOVDetalhado!C11 -> 1.1799875 | AJ11: =[10]byGOVDetalhado!D11 -> 3.3949269 | AK11: =[10]byGOVDetalhado!E11 -> 191.58784 | AL11: =[11]byGOVDetalhado!B11 -> 27.598789 | AM11: =[11]byGOVDetalhado!C11 -> 0.82803679 | AN11: =[11]byGOVDetalhado!D11 -> 2.4967828 | AO11: =[11]byGOVDetalhado!E11 -> 142.597 | AP11: =[12]byGOVDetalhado!B11 -> 37.25502 | AQ11: =[12]byGOVDetalhado!C11 -> 0.95873615 | AR11: =[12]byGOVDetalhado!D11 -> 2.8849399 | AS11: =[12]byGOVDetalhado!E11 -> 190.56491 | AT11: =[13]byGOVDetalhado!B11 -> 41.140073 | AU11: =[13]byGOVDetalhado!C11 -> 0.94004758 | AV11: =[13]byGOVDetalhado!D11 -> 2.7581097 | AW11: =[13]byGOVDetalhado!E11 -> 208.41284 | AX11: =[14]byGOVDetalhado!B11 -> 42.566775 | AY11: =[14]byGOVDetalhado!C11 -> 0.88408924 | AZ11: =[14]byGOVDetalhado!D11 -> 2.5985279 | BA11: =[14]byGOVDetalhado!E11 -> 213.64309 | BB11: =[15]byGOVDetalhado!B11 -> 42.706265 | BC11: =[15]byGOVDetalhado!C11 -> 0.80099994 | BD11: =[15]byGOVDetalhado!D11 -> 2.3828349 | BE11: =[15]byGOVDetalhado!E11 -> 212.4344 | BF11: =[16]byGOVDetalhado!B11 -> 48.910482 | BG11: =[16]byGOVDetalhado!C11 -> 0.84635543 | BH11: =[16]byGOVDetalhado!D11 -> 2.5745323 | BI11: =[16]byGOVDetalhado!E11 -> 241.21334 | BJ11: =[17]byGOVDetalhado!B11 -> 47.96111 | BK11: =[17]byGOVDetalhado!C11 -> 0.7999135 | BL11: =[17]byGOVDetalhado!D11 -> 2.4357722 | BM11: =[17]byGOVDetalhado!E11 -> 234.58526 | BN11: =[18]byGOVDetalhado!B11 -> 41.757059 | BO11: =[18]byGOVDetalhado!C11 -> 0.66627881 | BP11: =[18]byGOVDetalhado!D11 -> 2.0016264 | BQ11: =[18]byGOVDetalhado!E11 -> 202.62407 | BR11: =[19]byGOVDetalhado!B11 -> 47.576969 | BS11: =[19]byGOVDetalhado!C11 -> 0.72594006 | BT11: =[19]byGOVDetalhado!D11 -> 2.1592481 | BU11: =[19]byGOVDetalhado!E11 -> 229.10891 | BV11: =[20]byGOVDetalhado!B11 -> 53.762111 | BW11: =[20]byGOVDetalhado!C11 -> 0.7803852 | BX11: =[20]byGOVDetalhado!D11 -> 2.2657671 | BY11: =[20]byGOVDetalhado!E11 -> 257.85816 | BZ11: =[21]byGOVDetalhado!B11 -> 52.258162 | CA11: =[21]byGOVDetalhado!C11 -> 0.70723015 | CB11: =[21]byGOVDetalhado!D11 -> 2.0929014 | CC11: =[21]byGOVDetalhado!E11 -> 248.67417 | CD11: =[22]byGOVDetalhado!B11 -> 55.67597 | CE11: =[22]byGOVDetalhado!C11 -> 0.73165465 | CF11: =[22]byGOVDetalhado!D11 -> 2.271045 | CG11: =[22]byGOVDetalhado!E11 -> 262.9255 | CH11: =[23]byGOVDetalhado!B11 -> 70.086019 | CI11: =[23]byGOVDetalhado!C11 -> 0.78759601 | CJ11: =[23]byGOVDetalhado!D11 -> 2.2896702 | CK11: =[23]byGOVDetalhado!E11 -> 328.55238 | CL11: =[24]byGOVDetalhado!B11 -> 58.255361 | CM11: =[24]byGOVDetalhado!C11 -> 0.57794874 | CN11: =[24]byGOVDetalhado!D11 -> 1.655689 | CO11: =[24]byGOVDetalhado!E11 -> 286.8581 | CP11: =[25]byGOVDetalhado!B11 -> 59.723119 | CQ11: =[25]byGOVDetalhado!C11 -> 0.54574835 | CR11: =[25]byGOVDetalhado!D11 -> 1.5783117 | CS11: =[25]byGOVDetalhado!E11 -> 287.36213 | CT11: =[26]byGOVDetalhado!B11 -> 82.173979 | CU11: =[26]byGOVDetalhado!C11 -> 0.69966807 | CV11: =[26]byGOVDetalhado!D11 -> 1.9462259 | CW11: =[26]byGOVDetalhado!E11 -> 386.54873
A12: IOF | B12: =[2]byGOVDetalhado!B12 -> 3.0909899 | C12: =[2]byGOVDetalhado!C12 -> 0.25707323 | D12: =[2]byGOVDetalhado!D12 -> 0.84121126 | E12: =[2]byGOVDetalhado!E12 -> 17.82081 | F12: =[3]byGOVDetalhado!B12 -> 3.5519022 | G12: =[3]byGOVDetalhado!C12 -> 0.26995164 | H12: =[3]byGOVDetalhado!D12 -> 0.84238837 | I12: =[3]byGOVDetalhado!E12 -> 20.478156 | J12: =[4]byGOVDetalhado!B12 -> 3.993263 | K12: =[4]byGOVDetalhado!C12 -> 0.26822259 | L12: =[4]byGOVDetalhado!D12 -> 0.80602806 | M12: =[4]byGOVDetalhado!E12 -> 22.399314 | N12: =[5]byGOVDetalhado!B12 -> 4.4184168 | O12: =[5]byGOVDetalhado!C12 -> 0.25719123 | P12: =[5]byGOVDetalhado!D12 -> 0.78898205 | Q12: =[5]byGOVDetalhado!E12 -> 24.462621 | R12: =[6]byGOVDetalhado!B12 -> 5.2309541 | S12: =[6]byGOVDetalhado!C12 -> 0.267192 | T12: =[6]byGOVDetalhado!D12 -> 0.79467234 | U12: =[6]byGOVDetalhado!E12 -> 28.598281 | V12: =[7]byGOVDetalhado!B12 -> 5.9653248 | W12: =[7]byGOVDetalhado!C12 -> 0.27482567 | X12: =[7]byGOVDetalhado!D12 -> 0.79096381 | Y12: =[7]byGOVDetalhado!E12 -> 32.218735 | Z12: =[8]byGOVDetalhado!B12 -> 6.7375805 | AA12: =[8]byGOVDetalhado!C12 -> 0.27963147 | AB12: =[8]byGOVDetalhado!D12 -> 0.81221097 | AC12: =[8]byGOVDetalhado!E12 -> 35.965386 | AD12: =[9]byGOVDetalhado!B12 -> 7.8165821 | AE12: =[9]byGOVDetalhado!C12 -> 0.28734656 | AF12: =[9]byGOVDetalhado!D12 -> 0.83082699 | AG12: =[9]byGOVDetalhado!E12 -> 41.256563 | AH12: =[10]byGOVDetalhado!B12 -> 20.167891 | AI12: =[10]byGOVDetalhado!C12 -> 0.64852634 | AJ12: =[10]byGOVDetalhado!D12 -> 1.8658669 | AK12: =[10]byGOVDetalhado!E12 -> 105.29752 | AL12: =[11]byGOVDetalhado!B12 -> 19.193098 | AM12: =[11]byGOVDetalhado!C12 -> 0.57584377 | AN12: =[11]byGOVDetalhado!D12 -> 1.7363441 | AO12: =[11]byGOVDetalhado!E12 -> 99.166601 | AP12: =[12]byGOVDetalhado!B12 -> 26.529575 | AQ12: =[12]byGOVDetalhado!C12 -> 0.68272309 | AR12: =[12]byGOVDetalhado!D12 -> 2.054387 | AS12: =[12]byGOVDetalhado!E12 -> 135.70268 | AT12: =[13]byGOVDetalhado!B12 -> 31.870478 | AU12: =[13]byGOVDetalhado!C12 -> 0.72823804 | AV12: =[13]byGOVDetalhado!D12 -> 2.1366582 | AW12: =[13]byGOVDetalhado!E12 -> 161.4537 | AX12: =[14]byGOVDetalhado!B12 -> 30.9984 | AY12: =[14]byGOVDetalhado!C12 -> 0.64382026 | AZ12: =[14]byGOVDetalhado!D12 -> 1.8923258 | BA12: =[14]byGOVDetalhado!E12 -> 155.58129 | BB12: =[15]byGOVDetalhado!B12 -> 29.41226 | BC12: =[15]byGOVDetalhado!C12 -> 0.55165719 | BD12: =[15]byGOVDetalhado!D12 -> 1.6410838 | BE12: =[15]byGOVDetalhado!E12 -> 146.30584 | BF12: =[16]byGOVDetalhado!B12 -> 29.739887 | BG12: =[16]byGOVDetalhado!C12 -> 0.51462413 | BH12: =[16]byGOVDetalhado!D12 -> 1.5654374 | BI12: =[16]byGOVDetalhado!E12 -> 146.66912 | BJ12: =[17]byGOVDetalhado!B12 -> 34.680211 | BK12: =[17]byGOVDetalhado!C12 -> 0.57840966 | BL12: =[17]byGOVDetalhado!D12 -> 1.7612832 | BM12: =[17]byGOVDetalhado!E12 -> 169.62632 | BN12: =[18]byGOVDetalhado!B12 -> 33.642583 | BO12: =[18]byGOVDetalhado!C12 -> 0.53680362 | BP12: =[18]byGOVDetalhado!D12 -> 1.6126587 | BQ12: =[18]byGOVDetalhado!E12 -> 163.24898 | BR12: =[19]byGOVDetalhado!B12 -> 34.408095 | BS12: =[19]byGOVDetalhado!C12 -> 0.52500642 | BT12: =[19]byGOVDetalhado!D12 -> 1.5615878 | BU12: =[19]byGOVDetalhado!E12 -> 165.69364 | BV12: =[20]byGOVDetalhado!B12 -> 36.612379 | BW12: =[20]byGOVDetalhado!C12 -> 0.53144786 | BX12: =[20]byGOVDetalhado!D12 -> 1.5430035 | BY12: =[20]byGOVDetalhado!E12 -> 175.60323 | BZ12: =[21]byGOVDetalhado!B12 -> 40.941984 | CA12: =[21]byGOVDetalhado!C12 -> 0.55408388 | CB12: =[21]byGOVDetalhado!D12 -> 1.6396967 | CC12: =[21]byGOVDetalhado!E12 -> 194.82534 | CD12: =[22]byGOVDetalhado!B12 -> 21.944817 | CE12: =[22]byGOVDetalhado!C12 -> 0.28838343 | CF12: =[22]byGOVDetalhado!D12 -> 0.89513783 | CG12: =[22]byGOVDetalhado!E12 -> 103.63271 | CH12: =[23]byGOVDetalhado!B12 -> 49.012228 | CI12: =[23]byGOVDetalhado!C12 -> 0.55077797 | CJ12: =[23]byGOVDetalhado!D12 -> 1.6012015 | CK12: =[23]byGOVDetalhado!E12 -> 229.76172 | CL12: =[24]byGOVDetalhado!B12 -> 58.960077 | CM12: =[24]byGOVDetalhado!C12 -> 0.58494021 | CN12: =[24]byGOVDetalhado!D12 -> 1.6757179 | CO12: =[24]byGOVDetalhado!E12 -> 290.32824 | CP12: =[25]byGOVDetalhado!B12 -> 61.012797 | CQ12: =[25]byGOVDetalhado!C12 -> 0.55753339 | CR12: =[25]byGOVDetalhado!D12 -> 1.6123942 | CS12: =[25]byGOVDetalhado!E12 -> 293.56751 | CT12: =[26]byGOVDetalhado!B12 -> 67.40223 | CU12: =[26]byGOVDetalhado!C12 -> 0.57389442 | CV12: =[26]byGOVDetalhado!D12 -> 1.5963687 | CW12: =[26]byGOVDetalhado!E12 -> 317.062
A13: Imp. Sobre Comércio Exterior | B13: =[2]byGOVDetalhado!B13 -> 8.4307442 | C13: =[2]byGOVDetalhado!C13 -> 0.70117298 | D13: =[2]byGOVDetalhado!D13 -> 2.2944225 | E13: =[2]byGOVDetalhado!E13 -> 48.606657 | F13: =[3]byGOVDetalhado!B13 -> 9.0965329 | G13: =[3]byGOVDetalhado!C13 -> 0.69135461 | H13: =[3]byGOVDetalhado!D13 -> 2.157383 | I13: =[3]byGOVDetalhado!E13 -> 52.445198 | J13: =[4]byGOVDetalhado!B13 -> 7.9535269 | K13: =[4]byGOVDetalhado!C13 -> 0.53422867 | L13: =[4]byGOVDetalhado!D13 -> 1.6053954 | M13: =[4]byGOVDetalhado!E13 -> 44.613527 | N13: =[5]byGOVDetalhado!B13 -> 8.1282986 | O13: =[5]byGOVDetalhado!C13 -> 0.47313941 | P13: =[5]byGOVDetalhado!D13 -> 1.4514434 | Q13: =[5]byGOVDetalhado!E13 -> 45.002429 | R13: =[6]byGOVDetalhado!B13 -> 9.2158879 | S13: =[6]byGOVDetalhado!C13 -> 0.47073851 | T13: =[6]byGOVDetalhado!D13 -> 1.4000526 | U13: =[6]byGOVDetalhado!E13 -> 50.384413 | V13: =[7]byGOVDetalhado!B13 -> 8.9411287 | W13: =[7]byGOVDetalhado!C13 -> 0.41192253 | X13: =[7]byGOVDetalhado!D13 -> 1.1855363 | Y13: =[7]byGOVDetalhado!E13 -> 48.29106 | Z13: =[8]byGOVDetalhado!B13 -> 9.8571358 | AA13: =[8]byGOVDetalhado!C13 -> 0.40910315 | AB13: =[8]byGOVDetalhado!D13 -> 1.1882713 | AC13: =[8]byGOVDetalhado!E13 -> 52.617656 | AD13: =[9]byGOVDetalhado!B13 -> 12.21607 | AE13: =[9]byGOVDetalhado!C13 -> 0.44907679 | AF13: =[9]byGOVDetalhado!D13 -> 1.2984499 | AG13: =[9]byGOVDetalhado!E13 -> 64.477421 | AH13: =[10]byGOVDetalhado!B13 -> 17.10149 | AI13: =[10]byGOVDetalhado!C13 -> 0.54992198 | AJ13: =[10]byGOVDetalhado!D13 -> 1.5821735 | AK13: =[10]byGOVDetalhado!E13 -> 89.287697 | AL13: =[11]byGOVDetalhado!B13 -> 15.806918 | AM13: =[11]byGOVDetalhado!C13 -> 0.47424943 | AN13: =[11]byGOVDetalhado!D13 -> 1.4300063 | AO13: =[11]byGOVDetalhado!E13 -> 81.670943 | AP13: =[12]byGOVDetalhado!B13 -> 21.080739 | AQ13: =[12]byGOVDetalhado!C13 -> 0.54250049 | AR13: =[12]byGOVDetalhado!D13 -> 1.6324422 | AS13: =[12]byGOVDetalhado!E13 -> 107.83108 | AT13: =[13]byGOVDetalhado!B13 -> 26.644493 | AU13: =[13]byGOVDetalhado!C13 -> 0.60882467 | AV13: =[13]byGOVDetalhado!D13 -> 1.7862981 | AW13: =[13]byGOVDetalhado!E13 -> 134.97921 | AX13: =[14]byGOVDetalhado!B13 -> 31.085492 | AY13: =[14]byGOVDetalhado!C13 -> 0.64562912 | AZ13: =[14]byGOVDetalhado!D13 -> 1.8976425 | BA13: =[14]byGOVDetalhado!E13 -> 156.01841 | BB13: =[15]byGOVDetalhado!B13 -> 36.709334 | BC13: =[15]byGOVDetalhado!C13 -> 0.68852134 | BD13: =[15]byGOVDetalhado!D13 -> 2.0482307 | BE13: =[15]byGOVDetalhado!E13 -> 182.60378 | BF13: =[16]byGOVDetalhado!B13 -> 36.764846 | BG13: =[16]byGOVDetalhado!C13 -> 0.63618524 | BH13: =[16]byGOVDetalhado!D13 -> 1.9352147 | BI13: =[16]byGOVDetalhado!E13 -> 181.31433 | BJ13: =[17]byGOVDetalhado!B13 -> 38.963128 | BK13: =[17]byGOVDetalhado!C13 -> 0.64984177 | BL13: =[17]byGOVDetalhado!D13 -> 1.9787971 | BM13: =[17]byGOVDetalhado!E13 -> 190.57474 | BN13: =[18]byGOVDetalhado!B13 -> 31.443843 | BO13: =[18]byGOVDetalhado!C13 -> 0.50172035 | BP13: =[18]byGOVDetalhado!D13 -> 1.507262 | BQ13: =[18]byGOVDetalhado!E13 -> 152.5797 | BR13: =[19]byGOVDetalhado!B13 -> 32.430856 | BS13: =[19]byGOVDetalhado!C13 -> 0.49483726 | BT13: =[19]byGOVDetalhado!D13 -> 1.4718521 | BU13: =[19]byGOVDetalhado!E13 -> 156.17216 | BV13: =[20]byGOVDetalhado!B13 -> 40.694891 | BW13: =[20]byGOVDetalhado!C13 -> 0.59070766 | BX13: =[20]byGOVDetalhado!D13 -> 1.7150581 | BY13: =[20]byGOVDetalhado!E13 -> 195.18411 | BZ13: =[21]byGOVDetalhado!B13 -> 42.92663 | CA13: =[21]byGOVDetalhado!C13 -> 0.58094287 | CB13: =[21]byGOVDetalhado!D13 -> 1.7191803 | CC13: =[21]byGOVDetalhado!E13 -> 204.26941 | CD13: =[22]byGOVDetalhado!B13 -> 45.713058 | CE13: =[22]byGOVDetalhado!C13 -> 0.60072902 | CF13: =[22]byGOVDetalhado!D13 -> 1.8646538 | CG13: =[22]byGOVDetalhado!E13 -> 215.87641 | CH13: =[23]byGOVDetalhado!B13 -> 62.028225 | CI13: =[23]byGOVDetalhado!C13 -> 0.69704605 | CJ13: =[23]byGOVDetalhado!D13 -> 2.0264267 | CK13: =[23]byGOVDetalhado!E13 -> 290.7787 | CL13: =[24]byGOVDetalhado!B13 -> 59.015768 | CM13: =[24]byGOVDetalhado!C13 -> 0.5854927 | CN13: =[24]byGOVDetalhado!D13 -> 1.6773007 | CO13: =[24]byGOVDetalhado!E13 -> 290.60246 | CP13: =[25]byGOVDetalhado!B13 -> 58.575786 | CQ13: =[25]byGOVDetalhado!C13 -> 0.53526405 | CR13: =[25]byGOVDetalhado!D13 -> 1.547991 | CS13: =[25]byGOVDetalhado!E13 -> 281.84165 | CT13: =[26]byGOVDetalhado!B13 -> 77.507333 | CU13: =[26]byGOVDetalhado!C13 -> 0.65993405 | CV13: =[26]byGOVDetalhado!D13 -> 1.8357001 | CW13: =[26]byGOVDetalhado!E13 -> 364.5967
A14: ITR | B14: =[2]byGOVDetalhado!B14 -> 0.23082787 | C14: =[2]byGOVDetalhado!C14 -> 0.019197625 | D14: =[2]byGOVDetalhado!D14 -> 0.062819682 | E14: =[2]byGOVDetalhado!E14 -> 1.3308162 | F14: =[3]byGOVDetalhado!B14 -> 0.18998403 | G14: =[3]byGOVDetalhado!C14 -> 0.014439164 | H14: =[3]byGOVDetalhado!D14 -> 0.045057641 | I14: =[3]byGOVDetalhado!E14 -> 1.0953349 | J14: =[4]byGOVDetalhado!B14 -> 0.18918939 | K14: =[4]byGOVDetalhado!C14 -> 0.01270762 | L14: =[4]byGOVDetalhado!D14 -> 0.038187307 | M14: =[4]byGOVDetalhado!E14 -> 1.0612155 | N14: =[5]byGOVDetalhado!B14 -> 0.22792358 | O14: =[5]byGOVDetalhado!C14 -> 0.013267183 | P14: =[5]byGOVDetalhado!D14 -> 0.040699558 | Q14: =[5]byGOVDetalhado!E14 -> 1.2619018 | R14: =[6]byGOVDetalhado!B14 -> 0.23977249 | S14: =[6]byGOVDetalhado!C14 -> 0.012247343 | T14: =[6]byGOVDetalhado!D14 -> 0.036425584 | U14: =[6]byGOVDetalhado!E14 -> 1.3108662 | V14: =[7]byGOVDetalhado!B14 -> 0.27007668 | W14: =[7]byGOVDetalhado!C14 -> 0.012442575 | X14: =[7]byGOVDetalhado!D14 -> 0.035810435 | Y14: =[7]byGOVDetalhado!E14 -> 1.4586848 | Z14: =[8]byGOVDetalhado!B14 -> 0.28402332 | AA14: =[8]byGOVDetalhado!C14 -> 0.01178789 | AB14: =[8]byGOVDetalhado!D14 -> 0.034238827 | AC14: =[8]byGOVDetalhado!E14 -> 1.5161241 | AD14: =[9]byGOVDetalhado!B14 -> 0.31279981 | AE14: =[9]byGOVDetalhado!C14 -> 0.011498881 | AF14: =[9]byGOVDetalhado!D14 -> 0.033247591 | AG14: =[9]byGOVDetalhado!E14 -> 1.6509831 | AH14: =[10]byGOVDetalhado!B14 -> 0.39541172 | AI14: =[10]byGOVDetalhado!C14 -> 0.012715009 | AJ14: =[10]byGOVDetalhado!D14 -> 0.036582189 | AK14: =[10]byGOVDetalhado!E14 -> 2.0644634 | AL14: =[11]byGOVDetalhado!B14 -> 0.4088979 | AM14: =[11]byGOVDetalhado!C14 -> 0.01226802 | AN14: =[11]byGOVDetalhado!D14 -> 0.036991812 | AO14: =[11]byGOVDetalhado!E14 -> 2.1126874 | AP14: =[12]byGOVDetalhado!B14 -> 0.47598755 | AQ14: =[12]byGOVDetalhado!C14 -> 0.012249261 | AR14: =[12]byGOVDetalhado!D14 -> 0.03685934 | AS14: =[12]byGOVDetalhado!E14 -> 2.4347463 | AT14: =[13]byGOVDetalhado!B14 -> 0.54624142 | AU14: =[13]byGOVDetalhado!C14 -> 0.012481575 | AV14: =[13]byGOVDetalhado!D14 -> 0.036621077 | AW14: =[13]byGOVDetalhado!E14 -> 2.7672223 | AX14: =[14]byGOVDetalhado!B14 -> 0.60943849 | AY14: =[14]byGOVDetalhado!C14 -> 0.012657713 | AZ14: =[14]byGOVDetalhado!D14 -> 0.037203733 | BA14: =[14]byGOVDetalhado!E14 -> 3.0587782 | BB14: =[15]byGOVDetalhado!B14 -> 0.75283784 | BC14: =[15]byGOVDetalhado!C14 -> 0.014120248 | BD14: =[15]byGOVDetalhado!D14 -> 0.042005272 | BE14: =[15]byGOVDetalhado!E14 -> 3.7448524 | BF14: =[16]byGOVDetalhado!B14 -> 0.89117742 | BG14: =[16]byGOVDetalhado!C14 -> 0.015421088 | BH14: =[16]byGOVDetalhado!D14 -> 0.046909475 | BI14: =[16]byGOVDetalhado!E14 -> 4.3950473 | BJ14: =[17]byGOVDetalhado!B14 -> 1.1012954 | BK14: =[17]byGOVDetalhado!C14 -> 0.018367821 | BL14: =[17]byGOVDetalhado!D14 -> 0.055930832 | BM14: =[17]byGOVDetalhado!E14 -> 5.3866076 | BN14: =[18]byGOVDetalhado!B14 -> 1.1189416 | BO14: =[18]byGOVDetalhado!C14 -> 0.017853917 | BP14: =[18]byGOVDetalhado!D14 -> 0.053636511 | BQ14: =[18]byGOVDetalhado!E14 -> 5.4296088 | BR14: =[19]byGOVDetalhado!B14 -> 1.2712081 | BS14: =[19]byGOVDetalhado!C14 -> 0.019396378 | BT14: =[19]byGOVDetalhado!D14 -> 0.057692909 | BU14: =[19]byGOVDetalhado!E14 -> 6.1215566 | BV14: =[20]byGOVDetalhado!B14 -> 1.413985 | BW14: =[20]byGOVDetalhado!C14 -> 0.020524733 | BX14: =[20]byGOVDetalhado!D14 -> 0.059591421 | BY14: =[20]byGOVDetalhado!E14 -> 6.7818684 | BZ14: =[21]byGOVDetalhado!B14 -> 1.6252833 | CA14: =[21]byGOVDetalhado!C14 -> 0.021995595 | CB14: =[21]byGOVDetalhado!D14 -> 0.065091413 | CC14: =[21]byGOVDetalhado!E14 -> 7.7340259 | CD14: =[22]byGOVDetalhado!B14 -> 1.757006 | CE14: =[22]byGOVDetalhado!C14 -> 0.023089344 | CF14: =[22]byGOVDetalhado!D14 -> 0.071668976 | CG14: =[22]byGOVDetalhado!E14 -> 8.2973261 | CH14: =[23]byGOVDetalhado!B14 -> 2.1600571 | CI14: =[23]byGOVDetalhado!C14 -> 0.024273776 | CJ14: =[23]byGOVDetalhado!D14 -> 0.070567833 | CK14: =[23]byGOVDetalhado!E14 -> 10.126013 | CL14: =[24]byGOVDetalhado!B14 -> 2.5880176 | CM14: =[24]byGOVDetalhado!C14 -> 0.025675604 | CN14: =[24]byGOVDetalhado!D14 -> 0.073554643 | CO14: =[24]byGOVDetalhado!E14 -> 12.743786 | CP14: =[25]byGOVDetalhado!B14 -> 3.0321212 | CQ14: =[25]byGOVDetalhado!C14 -> 0.027707447 | CR14: =[25]byGOVDetalhado!D14 -> 0.080130318 | CS14: =[25]byGOVDetalhado!E14 -> 14.589272 | CT14: =[26]byGOVDetalhado!B14 -> 3.2455194 | CU14: =[26]byGOVDetalhado!C14 -> 0.027633885 | CV14: =[26]byGOVDetalhado!D14 -> 0.076867569 | CW14: =[26]byGOVDetalhado!E14 -> 15.267016
A15: Taxas | B15: =[2]byGOVDetalhado!B15 -> 1.3282668 | C15: =[2]byGOVDetalhado!C15 -> 0.11047006 | D15: =[2]byGOVDetalhado!D15 -> 0.36148711 | E15: =[2]byGOVDetalhado!E15 -> 7.6579966 | F15: =[3]byGOVDetalhado!B15 -> 1.4958849 | G15: =[3]byGOVDetalhado!C15 -> 0.11369023 | H15: =[3]byGOVDetalhado!D15 -> 0.35477217 | I15: =[3]byGOVDetalhado!E15 -> 8.6243827 | J15: =[4]byGOVDetalhado!B15 -> 1.7383784 | K15: =[4]byGOVDetalhado!C15 -> 0.11676475 | L15: =[4]byGOVDetalhado!D15 -> 0.35088642 | M15: =[4]byGOVDetalhado!E15 -> 9.7510442 | N15: =[5]byGOVDetalhado!B15 -> 2.0708408 | O15: =[5]byGOVDetalhado!C15 -> 0.12054139 | P15: =[5]byGOVDetalhado!D15 -> 0.36978317 | Q15: =[5]byGOVDetalhado!E15 -> 11.465236 | R15: =[6]byGOVDetalhado!B15 -> 2.565985 | S15: =[6]byGOVDetalhado!C15 -> 0.131068 | T15: =[6]byGOVDetalhado!D15 -> 0.38981747 | U15: =[6]byGOVDetalhado!E15 -> 14.028561 | V15: =[7]byGOVDetalhado!B15 -> 3.2479439 | W15: =[7]byGOVDetalhado!C15 -> 0.1496345 | X15: =[7]byGOVDetalhado!D15 -> 0.43065653 | Y15: =[7]byGOVDetalhado!E15 -> 17.542154 | Z15: =[8]byGOVDetalhado!B15 -> 3.6589161 | AA15: =[8]byGOVDetalhado!C15 -> 0.1518569 | AB15: =[8]byGOVDetalhado!D15 -> 0.44107997 | AC15: =[8]byGOVDetalhado!E15 -> 19.531393 | AD15: =[9]byGOVDetalhado!B15 -> 4.0543466 | AE15: =[9]byGOVDetalhado!C15 -> 0.14904245 | AF15: =[9]byGOVDetalhado!D15 -> 0.43093778 | AG15: =[9]byGOVDetalhado!E15 -> 21.399175 | AH15: =[10]byGOVDetalhado!B15 -> 4.9633387 | AI15: =[10]byGOVDetalhado!C15 -> 0.15960299 | AJ15: =[10]byGOVDetalhado!D15 -> 0.45919174 | AK15: =[10]byGOVDetalhado!E15 -> 25.913828 | AL15: =[11]byGOVDetalhado!B15 -> 4.9891651 | AM15: =[11]byGOVDetalhado!C15 -> 0.14968817 | AN15: =[11]byGOVDetalhado!D15 -> 0.45135536 | AO15: =[11]byGOVDetalhado!E15 -> 25.777941 | AP15: =[12]byGOVDetalhado!B15 -> 5.9237249 | AQ15: =[12]byGOVDetalhado!C15 -> 0.1524436 | AR15: =[12]byGOVDetalhado!D15 -> 0.45871913 | AS15: =[12]byGOVDetalhado!E15 -> 30.300725 | AT15: =[13]byGOVDetalhado!B15 -> 7.1480912 | AU15: =[13]byGOVDetalhado!C15 -> 0.16333335 | AV15: =[13]byGOVDetalhado!D15 -> 0.4792218 | AW15: =[13]byGOVDetalhado!E15 -> 36.211749 | AX15: =[14]byGOVDetalhado!B15 -> 6.8505461 | AY15: =[14]byGOVDetalhado!C15 -> 0.14228219 | AZ15: =[14]byGOVDetalhado!D15 -> 0.41819788 | BA15: =[14]byGOVDetalhado!E15 -> 34.382963 | BB15: =[15]byGOVDetalhado!B15 -> 7.1480912 | BC15: =[15]byGOVDetalhado!C15 -> 0.13406981 | BD15: =[15]byGOVDetalhado!D15 -> 0.39883425 | BE15: =[15]byGOVDetalhado!E15 -> 35.556856 | BF15: =[16]byGOVDetalhado!B15 -> 6.8399028 | BG15: =[16]byGOVDetalhado!C15 -> 0.11835886 | BH15: =[16]byGOVDetalhado!D15 -> 0.36003633 | BI15: =[16]byGOVDetalhado!E15 -> 33.732561 | BJ15: =[17]byGOVDetalhado!B15 -> 7.369943 | BK15: =[17]byGOVDetalhado!C15 -> 0.12291869 | BL15: =[17]byGOVDetalhado!D15 -> 0.37429289 | BM15: =[17]byGOVDetalhado!E15 -> 36.04754 | BN15: =[18]byGOVDetalhado!B15 -> 8.5112539 | BO15: =[18]byGOVDetalhado!C15 -> 0.13580622 | BP15: =[18]byGOVDetalhado!D15 -> 0.40798732 | BQ15: =[18]byGOVDetalhado!E15 -> 41.30044 | BR15: =[19]byGOVDetalhado!B15 -> 8.3067015 | BS15: =[19]byGOVDetalhado!C15 -> 0.12674551 | BT15: =[19]byGOVDetalhado!D15 -> 0.37699395 | BU15: =[19]byGOVDetalhado!E15 -> 40.001273 | BV15: =[20]byGOVDetalhado!B15 -> 9.6090797 | BW15: =[20]byGOVDetalhado!C15 -> 0.13948082 | BX15: =[20]byGOVDetalhado!D15 -> 0.40496804 | BY15: =[20]byGOVDetalhado!E15 -> 46.08784 | BZ15: =[21]byGOVDetalhado!B15 -> 8.5844524 | CA15: =[21]byGOVDetalhado!C15 -> 0.11617675 | CB15: =[21]byGOVDetalhado!D15 -> 0.34380107 | CC15: =[21]byGOVDetalhado!E15 -> 40.849726 | CD15: =[22]byGOVDetalhado!B15 -> 6.1198764 | CE15: =[22]byGOVDetalhado!C15 -> 0.080423134 | CF15: =[22]byGOVDetalhado!D15 -> 0.2496322 | CG15: =[22]byGOVDetalhado!E15 -> 28.900647 | CH15: =[23]byGOVDetalhado!B15 -> 7.1798169 | CI15: =[23]byGOVDetalhado!C15 -> 0.08068364 | CJ15: =[23]byGOVDetalhado!D15 -> 0.23456052 | CK15: =[23]byGOVDetalhado!E15 -> 33.657868 | CL15: =[24]byGOVDetalhado!B15 -> 7.8124658 | CM15: =[24]byGOVDetalhado!C15 -> 0.077507113 | CN15: =[24]byGOVDetalhado!D15 -> 0.22203988 | CO15: =[24]byGOVDetalhado!E15 -> 38.46975 | CP15: =[25]byGOVDetalhado!B15 -> 8.9104359 | CQ15: =[25]byGOVDetalhado!C15 -> 0.081423337 | CR15: =[25]byGOVDetalhado!D15 -> 0.23547741 | CS15: =[25]byGOVDetalhado!E15 -> 42.87321 | CT15: =[26]byGOVDetalhado!B15 -> 9.4437154 | CU15: =[26]byGOVDetalhado!C15 -> 0.080408254 | CV15: =[26]byGOVDetalhado!D15 -> 0.22366696 | CW15: =[26]byGOVDetalhado!E15 -> 44.423506
A16: Previdência (1) | B16: =[2]byGOVDetalhado!B16 -> 55.712837 | C16: =[2]byGOVDetalhado!C16 -> 4.6335573 | D16: =[2]byGOVDetalhado!D16 -> 15.162219 | E16: =[2]byGOVDetalhado!E16 -> 321.20708 | F16: =[3]byGOVDetalhado!B16 -> 62.433582 | G16: =[3]byGOVDetalhado!C16 -> 4.7450765 | H16: =[3]byGOVDetalhado!D16 -> 14.807087 | I16: =[3]byGOVDetalhado!E16 -> 359.9549 | J16: =[4]byGOVDetalhado!B16 -> 69.251554 | K16: =[4]byGOVDetalhado!C16 -> 4.6515421 | L16: =[4]byGOVDetalhado!D16 -> 13.978217 | M16: =[4]byGOVDetalhado!E16 -> 388.45108 | N16: =[5]byGOVDetalhado!B16 -> 79.375176 | O16: =[5]byGOVDetalhado!C16 -> 4.6203426 | P16: =[5]byGOVDetalhado!D16 -> 14.173762 | Q16: =[5]byGOVDetalhado!E16 -> 439.46168 | R16: =[6]byGOVDetalhado!B16 -> 93.327546 | S16: =[6]byGOVDetalhado!C16 -> 4.7670795 | T16: =[6]byGOVDetalhado!D16 -> 14.178067 | U16: =[6]byGOVDetalhado!E16 -> 510.23338 | V16: =[7]byGOVDetalhado!B16 -> 106.6517 | W16: =[7]byGOVDetalhado!C16 -> 4.9135005 | X16: =[7]byGOVDetalhado!D16 -> 14.141332 | Y16: =[7]byGOVDetalhado!E16 -> 576.02614 | Z16: =[8]byGOVDetalhado!B16 -> 121.05943 | AA16: =[8]byGOVDetalhado!C16 -> 5.0243597 | AB16: =[8]byGOVDetalhado!D16 -> 14.593637 | AC16: =[8]byGOVDetalhado!E16 -> 646.21852 | AD16: =[9]byGOVDetalhado!B16 -> 138.11807 | AE16: =[9]byGOVDetalhado!C16 -> 5.0773794 | AF16: =[9]byGOVDetalhado!D16 -> 14.680614 | AG16: =[9]byGOVDetalhado!E16 -> 728.99855 | AH16: =[10]byGOVDetalhado!B16 -> 158.09568 | AI16: =[10]byGOVDetalhado!C16 -> 5.0837844 | AJ16: =[10]byGOVDetalhado!D16 -> 14.626491 | AK16: =[10]byGOVDetalhado!E16 -> 825.42509 | AL16: =[11]byGOVDetalhado!B16 -> 178.24284 | AM16: =[11]byGOVDetalhado!C16 -> 5.3477574 | AN16: =[11]byGOVDetalhado!D16 -> 16.125115 | AO16: =[11]byGOVDetalhado!E16 -> 920.94237 | AP16: =[12]byGOVDetalhado!B16 -> 210.4037 | AQ16: =[12]byGOVDetalhado!C16 -> 5.4146161 | AR16: =[12]byGOVDetalhado!D16 -> 16.293161 | AS16: =[12]byGOVDetalhado!E16 -> 1076.2459 | AT16: =[13]byGOVDetalhado!B16 -> 242.23414 | AU16: =[13]byGOVDetalhado!C16 -> 5.5350319 | AV16: =[13]byGOVDetalhado!D16 -> 16.239843 | AW16: =[13]byGOVDetalhado!E16 -> 1227.1418 | AX16: =[14]byGOVDetalhado!B16 -> 269.00561 | AY16: =[14]byGOVDetalhado!C16 -> 5.5871033 | AZ16: =[14]byGOVDetalhado!D16 -> 16.421695 | BA16: =[14]byGOVDetalhado!E16 -> 1350.142 | BB16: =[15]byGOVDetalhado!B16 -> 292.7361 | BC16: =[15]byGOVDetalhado!C16 -> 5.4905668 | BD16: =[15]byGOVDetalhado!D16 -> 16.333477 | BE16: =[15]byGOVDetalhado!E16 -> 1456.1615 | BF16: =[16]byGOVDetalhado!B16 -> 312.81126 | BG16: =[16]byGOVDetalhado!C16 -> 5.4129401 | BH16: =[16]byGOVDetalhado!D16 -> 16.465646 | BI16: =[16]byGOVDetalhado!E16 -> 1542.701 | BJ16: =[17]byGOVDetalhado!B16 -> 315.94696 | BK16: =[17]byGOVDetalhado!C16 -> 5.2694828 | BL16: =[17]byGOVDetalhado!D16 -> 16.04581 | BM16: =[17]byGOVDetalhado!E16 -> 1545.3459 | BN16: =[18]byGOVDetalhado!B16 -> 333.76555 | BO16: =[18]byGOVDetalhado!C16 -> 5.3255886 | BP16: =[18]byGOVDetalhado!D16 -> 15.999066 | BQ16: =[18]byGOVDetalhado!E16 -> 1619.5809 | BR16: =[19]byGOVDetalhado!B16 -> 351.88658 | BS16: =[19]byGOVDetalhado!C16 -> 5.3691643 | BT16: =[19]byGOVDetalhado!D16 -> 15.970131 | BU16: =[19]byGOVDetalhado!E16 -> 1694.5247 | BV16: =[20]byGOVDetalhado!B16 -> 371.2967 | BW16: =[20]byGOVDetalhado!C16 -> 5.3895661 | BX16: =[20]byGOVDetalhado!D16 -> 15.648043 | BY16: =[20]byGOVDetalhado!E16 -> 1780.8431 | BZ16: =[21]byGOVDetalhado!B16 -> 394.94103 | CA16: =[21]byGOVDetalhado!C16 -> 5.3448914 | CB16: =[21]byGOVDetalhado!D16 -> 15.817101 | CC16: =[21]byGOVDetalhado!E16 -> 1879.3549 | CD16: =[22]byGOVDetalhado!B16 -> 386.78782 | CE16: =[22]byGOVDetalhado!C16 -> 5.0828949 | CF16: =[22]byGOVDetalhado!D16 -> 15.777229 | CG16: =[22]byGOVDetalhado!E16 -> 1826.5758 | CH16: =[23]byGOVDetalhado!B16 -> 443.13288 | CI16: =[23]byGOVDetalhado!C16 -> 4.9797333 | CJ16: =[23]byGOVDetalhado!D16 -> 14.476898 | CK16: =[23]byGOVDetalhado!E16 -> 2077.3382 | CL16: =[24]byGOVDetalhado!B16 -> 514.64479 | CM16: =[24]byGOVDetalhado!C16 -> 5.1057672 | CN16: =[24]byGOVDetalhado!D16 -> 14.626838 | CO16: =[24]byGOVDetalhado!E16 -> 2534.1879 | CP16: =[25]byGOVDetalhado!B16 -> 534.84268 | CQ16: =[25]byGOVDetalhado!C16 -> 4.8873788 | CR16: =[25]byGOVDetalhado!D16 -> 14.134367 | CS16: =[25]byGOVDetalhado!E16 -> 2573.4344 | CT16: =[26]byGOVDetalhado!B16 -> 611.64221 | CU16: =[26]byGOVDetalhado!C16 -> 5.2078107 | CV16: =[26]byGOVDetalhado!D16 -> 14.486264 | CW16: =[26]byGOVDetalhado!E16 -> 2877.1823
A17: Cofins | B17: =[2]byGOVDetalhado!B17 -> 38.634039 | C17: =[2]byGOVDetalhado!C17 -> 3.213138 | D17: =[2]byGOVDetalhado!D17 -> 10.514233 | E17: =[2]byGOVDetalhado!E17 -> 222.74089 | F17: =[3]byGOVDetalhado!B17 -> 45.678823 | G17: =[3]byGOVDetalhado!C17 -> 3.4716815 | H17: =[3]byGOVDetalhado!D17 -> 10.833437 | I17: =[3]byGOVDetalhado!E17 -> 263.35693 | J17: =[4]byGOVDetalhado!B17 -> 50.855606 | K17: =[4]byGOVDetalhado!C17 -> 3.4159088 | L17: =[4]byGOVDetalhado!D17 -> 10.26505 | M17: =[4]byGOVDetalhado!E17 -> 285.26313 | N17: =[5]byGOVDetalhado!B17 -> 57.522166 | O17: =[5]byGOVDetalhado!C17 -> 3.3483027 | P17: =[5]byGOVDetalhado!D17 -> 10.271543 | Q17: =[5]byGOVDetalhado!E17 -> 318.47221 | R17: =[6]byGOVDetalhado!B17 -> 77.290069 | S17: =[6]byGOVDetalhado!C17 -> 3.9479009 | T17: =[6]byGOVDetalhado!D17 -> 11.741697 | U17: =[6]byGOVDetalhado!E17 -> 422.55448 | V17: =[7]byGOVDetalhado!B17 -> 86.532235 | W17: =[7]byGOVDetalhado!C17 -> 3.9865859 | X17: =[7]byGOVDetalhado!D17 -> 11.473619 | Y17: =[7]byGOVDetalhado!E17 -> 467.36083 | Z17: =[8]byGOVDetalhado!B17 -> 89.096351 | AA17: =[8]byGOVDetalhado!C17 -> 3.6977879 | AB17: =[8]byGOVDetalhado!D17 -> 10.740507 | AC17: =[8]byGOVDetalhado!E17 -> 475.59872 | AD17: =[9]byGOVDetalhado!B17 -> 100.55555 | AE17: =[9]byGOVDetalhado!C17 -> 3.6965379 | AF17: =[9]byGOVDetalhado!D17 -> 10.688081 | AG17: =[9]byGOVDetalhado!E17 -> 530.74047 | AH17: =[10]byGOVDetalhado!B17 -> 118.43105 | AI17: =[10]byGOVDetalhado!C17 -> 3.8083136 | AJ17: =[10]byGOVDetalhado!D17 -> 10.95685 | AK17: =[10]byGOVDetalhado!E17 -> 618.33416 | AL17: =[11]byGOVDetalhado!B17 -> 114.72393 | AM17: =[11]byGOVDetalhado!C17 -> 3.4420219 | AN17: =[11]byGOVDetalhado!D17 -> 10.378743 | AO17: =[11]byGOVDetalhado!E17 -> 592.75385 | AP17: =[12]byGOVDetalhado!B17 -> 138.636 | AQ17: =[12]byGOVDetalhado!C17 -> 3.5677165 | AR17: =[12]byGOVDetalhado!D17 -> 10.735641 | AS17: =[12]byGOVDetalhado!E17 -> 709.14356 | AT17: =[13]byGOVDetalhado!B17 -> 158.16676 | AU17: =[13]byGOVDetalhado!C17 -> 3.6140987 | AV17: =[13]byGOVDetalhado!D17 -> 10.603804 | AW17: =[13]byGOVDetalhado!E17 -> 801.26218 | AX17: =[14]byGOVDetalhado!B17 -> 174.626 | AY17: =[14]byGOVDetalhado!C17 -> 3.6268889 | AZ17: =[14]byGOVDetalhado!D17 -> 10.660204 | BA17: =[14]byGOVDetalhado!E17 -> 876.44971 | BB17: =[15]byGOVDetalhado!B17 -> 193.12483 | BC17: =[15]byGOVDetalhado!C17 -> 3.6222548 | BD17: =[15]byGOVDetalhado!D17 -> 10.775575 | BE17: =[15]byGOVDetalhado!E17 -> 960.66368 | BF17: =[16]byGOVDetalhado!B17 -> 193.55241 | BG17: =[16]byGOVDetalhado!C17 -> 3.3492643 | BH17: =[16]byGOVDetalhado!D17 -> 10.188142 | BI17: =[16]byGOVDetalhado!E17 -> 954.54841 | BJ17: =[17]byGOVDetalhado!B17 -> 199.3447 | BK17: =[17]byGOVDetalhado!C17 -> 3.3247462 | BL17: =[17]byGOVDetalhado!D17 -> 10.124 | BM17: =[17]byGOVDetalhado!E17 -> 975.02602 | BN17: =[18]byGOVDetalhado!B17 -> 200.94415 | BO17: =[18]byGOVDetalhado!C17 -> 3.2062801 | BP17: =[18]byGOVDetalhado!D17 -> 9.6322663 | BQ17: =[18]byGOVDetalhado!E17 -> 975.07158 | BR17: =[19]byGOVDetalhado!B17 -> 214.80578 | BS17: =[19]byGOVDetalhado!C17 -> 3.2775547 | BT17: =[19]byGOVDetalhado!D17 -> 9.7488129 | BU17: =[19]byGOVDetalhado!E17 -> 1034.4063 | BV17: =[20]byGOVDetalhado!B17 -> 243.26353 | BW17: =[20]byGOVDetalhado!C17 -> 3.5310976 | BX17: =[20]byGOVDetalhado!D17 -> 10.252174 | BY17: =[20]byGOVDetalhado!E17 -> 1166.7601 | BZ17: =[21]byGOVDetalhado!B17 -> 236.27309 | CA17: =[21]byGOVDetalhado!C17 -> 3.1975761 | CB17: =[21]byGOVDetalhado!D17 -> 9.4625652 | CC17: =[21]byGOVDetalhado!E17 -> 1124.3223 | CD17: =[22]byGOVDetalhado!B17 -> 217.3663 | CE17: =[22]byGOVDetalhado!C17 -> 2.8564759 | CF17: =[22]byGOVDetalhado!D17 -> 8.8664581 | CG17: =[22]byGOVDetalhado!E17 -> 1026.4957 | CH17: =[23]byGOVDetalhado!B17 -> 267.76451 | CI17: =[23]byGOVDetalhado!C17 -> 3.0090204 | CJ17: =[23]byGOVDetalhado!D17 -> 8.7477138 | CK17: =[23]byGOVDetalhado!E17 -> 1255.2385 | CL17: =[24]byGOVDetalhado!B17 -> 269.29528 | CM17: =[24]byGOVDetalhado!C17 -> 2.671666 | CN17: =[24]byGOVDetalhado!D17 -> 7.653703 | CO17: =[24]byGOVDetalhado!E17 -> 1326.0502 | CP17: =[25]byGOVDetalhado!B17 -> 326.94474 | CQ17: =[25]byGOVDetalhado!C17 -> 2.9876127 | CR17: =[25]byGOVDetalhado!D17 -> 8.6402171 | CS17: =[25]byGOVDetalhado!E17 -> 1573.1184 | CT17: =[26]byGOVDetalhado!B17 -> 353.79252 | CU17: =[26]byGOVDetalhado!C17 -> 3.0123567 | CV17: =[26]byGOVDetalhado!D17 -> 8.3792971 | CW17: =[26]byGOVDetalhado!E17 -> 1664.2501
A18: CPMF | B18: =[2]byGOVDetalhado!B18 -> 14.396561 | C18: =[2]byGOVDetalhado!C18 -> 1.1973415 | D18: =[2]byGOVDetalhado!D18 -> 3.9180165 | E18: =[2]byGOVDetalhado!E18 -> 83.00201 | F18: =[3]byGOVDetalhado!B18 -> 17.157002 | G18: =[3]byGOVDetalhado!C18 -> 1.3039663 | H18: =[3]byGOVDetalhado!D18 -> 4.0690474 | I18: =[3]byGOVDetalhado!E18 -> 98.917066 | J18: =[4]byGOVDetalhado!B18 -> 20.266822 | K18: =[4]byGOVDetalhado!C18 -> 1.3612976 | L18: =[4]byGOVDetalhado!D18 -> 4.0907967 | M18: =[4]byGOVDetalhado!E18 -> 113.6822 | N18: =[5]byGOVDetalhado!B18 -> 22.984138 | O18: =[5]byGOVDetalhado!C18 -> 1.3378817 | P18: =[5]byGOVDetalhado!D18 -> 4.1042014 | Q18: =[5]byGOVDetalhado!E18 -> 127.25197 | R18: =[6]byGOVDetalhado!B18 -> 26.393531 | S18: =[6]byGOVDetalhado!C18 -> 1.3481557 | T18: =[6]byGOVDetalhado!D18 -> 4.0096335 | U18: =[6]byGOVDetalhado!E18 -> 144.29674 | V18: =[7]byGOVDetalhado!B18 -> 28.99577 | W18: =[7]byGOVDetalhado!C18 -> 1.3358505 | X18: =[7]byGOVDetalhado!D18 -> 3.8446531 | Y18: =[7]byGOVDetalhado!E18 -> 156.60623 | Z18: =[8]byGOVDetalhado!B18 -> 31.935233 | AA18: =[8]byGOVDetalhado!C18 -> 1.3254159 | AB18: =[8]byGOVDetalhado!D18 -> 3.8497717 | AC18: =[8]byGOVDetalhado!E18 -> 170.47113 | AD18: =[9]byGOVDetalhado!B18 -> 36.319613 | AE18: =[9]byGOVDetalhado!C18 -> 1.3351508 | AF18: =[9]byGOVDetalhado!D18 -> 3.8604231 | AG18: =[9]byGOVDetalhado!E18 -> 191.6979 | AH18: =[10]byGOVDetalhado!B18 -> 0.97129909 | AI18: =[10]byGOVDetalhado!C18 -> 0.031233461 | AJ18: =[10]byGOVDetalhado!D18 -> 0.089861391 | AK18: =[10]byGOVDetalhado!E18 -> 5.0711989 | AL18: =[11]byGOVDetalhado!B18 -> -0.055668721 | AM18: =[11]byGOVDetalhado!C18 -> -0.0016702091 | AN18: =[11]byGOVDetalhado!D18 -> -0.0050361884 | AO18: =[11]byGOVDetalhado!E18 -> -0.28762829 | AP18: =[12]byGOVDetalhado!B18 -> -0.045253027 | AQ18: =[12]byGOVDetalhado!C18 -> -0.0011645602 | AR18: =[12]byGOVDetalhado!D18 -> -0.0035042865 | AS18: =[12]byGOVDetalhado!E18 -> -0.23147589 | AT18: =[13]byGOVDetalhado!B18 -> -0.0035526914 | AU18: =[13]byGOVDetalhado!C18 -> -8.1178733e-05 | AV18: =[13]byGOVDetalhado!D18 -> -0.00023817927 | AW18: =[13]byGOVDetalhado!E18 -> -0.017997696 | AX18: =[14]byGOVDetalhado!B18 -> -0.26159925 | AY18: =[14]byGOVDetalhado!C18 -> -0.0054332771 | AZ18: =[14]byGOVDetalhado!D18 -> -0.015969567 | BA18: =[14]byGOVDetalhado!E18 -> -1.3129694 | BB18: =[15]byGOVDetalhado!B18 -> -0.26783297 | BC18: =[15]byGOVDetalhado!C18 -> -0.0050234829 | BD18: =[15]byGOVDetalhado!D18 -> -0.014943984 | BE18: =[15]byGOVDetalhado!E18 -> -1.3322855 | BF18: =[16]byGOVDetalhado!B18 -> 0 | BG18: =[16]byGOVDetalhado!C18 -> 0 | BH18: =[16]byGOVDetalhado!D18 -> 0 | BI18: =[16]byGOVDetalhado!E18 -> 0 | BJ18: =[17]byGOVDetalhado!B18 -> 0.00013952736 | BK18: =[17]byGOVDetalhado!C18 -> 2.32709e-06 | BL18: =[17]byGOVDetalhado!D18 -> 7.0860926e-06 | BM18: =[17]byGOVDetalhado!E18 -> 0.00068245007 | BN18: =[18]byGOVDetalhado!B18 -> -0.0002882768 | BO18: =[18]byGOVDetalhado!C18 -> -4.5997666e-06 | BP18: =[18]byGOVDetalhado!D18 -> -1.3818561e-05 | BQ18: =[18]byGOVDetalhado!E18 -> -0.001398849 | BR18: =[19]byGOVDetalhado!B18 -> 9.895308e-05 | BS18: =[19]byGOVDetalhado!C18 -> 1.5098483e-06 | BT18: =[19]byGOVDetalhado!D18 -> 4.4909177e-06 | BU18: =[19]byGOVDetalhado!E18 -> 0.00047651275 | BV18: =[20]byGOVDetalhado!B18 -> 8.216e-08 | BW18: =[20]byGOVDetalhado!C18 -> 1.1925954e-09 | BX18: =[20]byGOVDetalhado!D18 -> 3.4625765e-09 | BY18: =[20]byGOVDetalhado!E18 -> 3.940624e-07 | BZ18: =[21]byGOVDetalhado!B18 -> -0.036175415 | CA18: =[21]byGOVDetalhado!C18 -> -0.00048957605 | CB18: =[21]byGOVDetalhado!D18 -> -0.0014487991 | CC18: =[21]byGOVDetalhado!E18 -> -0.17214328 | CD18: =[22]byGOVDetalhado!B18 -> -0.0029404074 | CE18: =[22]byGOVDetalhado!C18 -> -3.8640776e-05 | CF18: =[22]byGOVDetalhado!D18 -> -0.00011994039 | CG18: =[22]byGOVDetalhado!E18 -> -0.013885848 | CH18: =[23]byGOVDetalhado!B18 -> -0.024904616 | CI18: =[23]byGOVDetalhado!C18 -> -0.00027986717 | CJ18: =[23]byGOVDetalhado!D18 -> -0.00081361959 | CK18: =[23]byGOVDetalhado!E18 -> -0.11674898 | CL18: =[24]byGOVDetalhado!B18 -> 0.003714376 | CM18: =[24]byGOVDetalhado!C18 -> 3.6850152e-05 | CN18: =[24]byGOVDetalhado!D18 -> 0.00010556713 | CO18: =[24]byGOVDetalhado!E18 -> 0.018290142 | CP18: =[25]byGOVDetalhado!B18 -> 3.99997e-06 | CQ18: =[25]byGOVDetalhado!C18 -> 3.6551624e-08 | CR18: =[25]byGOVDetalhado!D18 -> 1.057078e-07 | CS18: =[25]byGOVDetalhado!E18 -> 1.9246147e-05 | CT18: =[26]byGOVDetalhado!B18 -> -0.022443285 | CU18: =[26]byGOVDetalhado!C18 -> -0.00019109273 | CV18: =[26]byGOVDetalhado!D18 -> -0.00053155152 | CW18: =[26]byGOVDetalhado!E18 -> -0.10557385
A19: CSLL | B19: =[2]byGOVDetalhado!B19 -> 8.6657559 | C19: =[2]byGOVDetalhado!C19 -> 0.72071857 | D19: =[2]byGOVDetalhado!D19 -> 2.3583808 | E19: =[2]byGOVDetalhado!E19 -> 49.961594 | F19: =[3]byGOVDetalhado!B19 -> 8.9678194 | G19: =[3]byGOVDetalhado!C19 -> 0.68157213 | H19: =[3]byGOVDetalhado!D19 -> 2.1268566 | I19: =[3]byGOVDetalhado!E19 -> 51.703113 | J19: =[4]byGOVDetalhado!B19 -> 12.374589 | K19: =[4]byGOVDetalhado!C19 -> 0.83118597 | L19: =[4]byGOVDetalhado!D19 -> 2.4977733 | M19: =[4]byGOVDetalhado!E19 -> 69.412483 | N19: =[5]byGOVDetalhado!B19 -> 15.661353 | O19: =[5]byGOVDetalhado!C19 -> 0.91163032 | P19: =[5]byGOVDetalhado!D19 -> 2.7965959 | Q19: =[5]byGOVDetalhado!E19 -> 86.709281 | R19: =[6]byGOVDetalhado!B19 -> 19.309499 | S19: =[6]byGOVDetalhado!C19 -> 0.98631024 | T19: =[6]byGOVDetalhado!D19 -> 2.9334465 | U19: =[6]byGOVDetalhado!E19 -> 105.56745 | V19: =[7]byGOVDetalhado!B19 -> 24.948634 | W19: =[7]byGOVDetalhado!C19 -> 1.1493968 | X19: =[7]byGOVDetalhado!D19 -> 3.3080289 | Y19: =[7]byGOVDetalhado!E19 -> 134.74764 | Z19: =[8]byGOVDetalhado!B19 -> 26.547247 | AA19: =[8]byGOVDetalhado!C19 -> 1.101797 | AB19: =[8]byGOVDetalhado!D19 -> 3.2002535 | AC19: =[8]byGOVDetalhado!E19 -> 141.70992 | AD19: =[9]byGOVDetalhado!B19 -> 33.183201 | AE19: =[9]byGOVDetalhado!C19 -> 1.2198527 | AF19: =[9]byGOVDetalhado!D19 -> 3.5270529 | AG19: =[9]byGOVDetalhado!E19 -> 175.14366 | AH19: =[10]byGOVDetalhado!B19 -> 41.663704 | AI19: =[10]byGOVDetalhado!C19 -> 1.3397538 | AJ19: =[10]byGOVDetalhado!D19 -> 3.8545886 | AK19: =[10]byGOVDetalhado!E19 -> 217.52819 | AL19: =[11]byGOVDetalhado!B19 -> 42.808449 | AM19: =[11]byGOVDetalhado!C19 -> 1.2843669 | AN19: =[11]byGOVDetalhado!D19 -> 3.8727568 | AO19: =[11]byGOVDetalhado!E19 -> 221.18204 | AP19: =[12]byGOVDetalhado!B19 -> 45.199616 | AQ19: =[12]byGOVDetalhado!C19 -> 1.1631857 | AR19: =[12]byGOVDetalhado!D19 -> 3.5001504 | AS19: =[12]byGOVDetalhado!E19 -> 231.20268 | AT19: =[13]byGOVDetalhado!B19 -> 56.964314 | AU19: =[13]byGOVDetalhado!C19 -> 1.3016303 | AV19: =[13]byGOVDetalhado!D19 -> 3.8189973 | AW19: =[13]byGOVDetalhado!E19 -> 288.57738 | AX19: =[14]byGOVDetalhado!B19 -> 55.608133 | AY19: =[14]byGOVDetalhado!C19 -> 1.1549513 | AZ19: =[14]byGOVDetalhado!D19 -> 3.3946496 | BA19: =[14]byGOVDetalhado!E19 -> 279.0978 | BB19: =[15]byGOVDetalhado!B19 -> 59.775636 | BC19: =[15]byGOVDetalhado!C19 -> 1.1211536 | BD19: =[15]byGOVDetalhado!D19 -> 3.335236 | BE19: =[15]byGOVDetalhado!E19 -> 297.34283 | BF19: =[16]byGOVDetalhado!B19 -> 61.590539 | BG19: =[16]byGOVDetalhado!C19 -> 1.0657733 | BH19: =[16]byGOVDetalhado!D19 -> 3.2419805 | BI19: =[16]byGOVDetalhado!E19 -> 303.74797 | BJ19: =[17]byGOVDetalhado!B19 -> 58.696026 | BK19: =[17]byGOVDetalhado!C19 -> 0.97895449 | BL19: =[17]byGOVDetalhado!D19 -> 2.98096 | BM19: =[17]byGOVDetalhado!E19 -> 287.09142 | BN19: =[18]byGOVDetalhado!B19 -> 66.329487 | BO19: =[18]byGOVDetalhado!C19 -> 1.0583584 | BP19: =[18]byGOVDetalhado!D19 -> 3.1795068 | BQ19: =[18]byGOVDetalhado!E19 -> 321.86057 | BR19: =[19]byGOVDetalhado!B19 -> 67.348213 | BS19: =[19]byGOVDetalhado!C19 -> 1.0276141 | BT19: =[19]byGOVDetalhado!D19 -> 3.0565525 | BU19: =[19]byGOVDetalhado!E19 -> 324.31817 | BV19: =[20]byGOVDetalhado!B19 -> 74.914336 | BW19: =[20]byGOVDetalhado!C19 -> 1.0874208 | BX19: =[20]byGOVDetalhado!D19 -> 3.157213 | BY19: =[20]byGOVDetalhado!E19 -> 359.31016 | BZ19: =[21]byGOVDetalhado!B19 -> 79.552491 | CA19: =[21]byGOVDetalhado!C19 -> 1.076615 | CB19: =[21]byGOVDetalhado!D19 -> 3.1860194 | CC19: =[21]byGOVDetalhado!E19 -> 378.55617 | CD19: =[22]byGOVDetalhado!B19 -> 76.663607 | CE19: =[22]byGOVDetalhado!C19 -> 1.0074595 | CF19: =[22]byGOVDetalhado!D19 -> 3.1271391 | CG19: =[22]byGOVDetalhado!E19 -> 362.038 | CH19: =[23]byGOVDetalhado!B19 -> 111.00247 | CI19: =[23]byGOVDetalhado!C19 -> 1.2473972 | CJ19: =[23]byGOVDetalhado!D19 -> 3.6263874 | CK19: =[23]byGOVDetalhado!E19 -> 520.36237 | CL19: =[24]byGOVDetalhado!B19 -> 154.59303 | CM19: =[24]byGOVDetalhado!C19 -> 1.5337103 | CN19: =[24]byGOVDetalhado!D19 -> 4.393724 | CO19: =[24]byGOVDetalhado!E19 -> 761.23919 | CP19: =[25]byGOVDetalhado!B19 -> 152.44528 | CQ19: =[25]byGOVDetalhado!C19 -> 1.3930411 | CR19: =[25]byGOVDetalhado!D19 -> 4.0286939 | CS19: =[25]byGOVDetalhado!E19 -> 733.50153 | CT19: =[26]byGOVDetalhado!B19 -> 160.6067 | CU19: =[26]byGOVDetalhado!C19 -> 1.3674813 | CV19: =[26]byGOVDetalhado!D19 -> 3.8038431 | CW19: =[26]byGOVDetalhado!E19 -> 755.49848
A20: PIS-PASEP | B20: =[2]byGOVDetalhado!B20 -> 9.4840235 | C20: =[2]byGOVDetalhado!C20 -> 0.78877272 | D20: =[2]byGOVDetalhado!D20 -> 2.5810719 | E20: =[2]byGOVDetalhado!E20 -> 54.679239 | F20: =[3]byGOVDetalhado!B20 -> 11.186001 | G20: =[3]byGOVDetalhado!C20 -> 0.85015833 | H20: =[3]byGOVDetalhado!D20 -> 2.6529325 | I20: =[3]byGOVDetalhado!E20 -> 64.491827 | J20: =[4]byGOVDetalhado!B20 -> 12.472114 | K20: =[4]byGOVDetalhado!C20 -> 0.83773665 | L20: =[4]byGOVDetalhado!D20 -> 2.5174586 | M20: =[4]byGOVDetalhado!E20 -> 69.959531 | N20: =[5]byGOVDetalhado!B20 -> 16.506662 | O20: =[5]byGOVDetalhado!C20 -> 0.96083482 | P20: =[5]byGOVDetalhado!D20 -> 2.9475399 | Q20: =[5]byGOVDetalhado!E20 -> 91.389344 | R20: =[6]byGOVDetalhado!B20 -> 19.278062 | S20: =[6]byGOVDetalhado!C20 -> 0.98470447 | T20: =[6]byGOVDetalhado!D20 -> 2.9286707 | U20: =[6]byGOVDetalhado!E20 -> 105.39558 | V20: =[7]byGOVDetalhado!B20 -> 21.296733 | W20: =[7]byGOVDetalhado!C20 -> 0.98115177 | X20: =[7]byGOVDetalhado!D20 -> 2.8238102 | Y20: =[7]byGOVDetalhado!E20 -> 115.02371 | Z20: =[8]byGOVDetalhado!B20 -> 23.38789 | AA20: =[8]byGOVDetalhado!C20 -> 0.97067337 | AB20: =[8]byGOVDetalhado!D20 -> 2.819395 | AC20: =[8]byGOVDetalhado!E20 -> 124.84518 | AD20: =[9]byGOVDetalhado!B20 -> 25.779152 | AE20: =[9]byGOVDetalhado!C20 -> 0.94767132 | AF20: =[9]byGOVDetalhado!D20 -> 2.7400742 | AG20: =[9]byGOVDetalhado!E20 -> 136.06449 | AH20: =[10]byGOVDetalhado!B20 -> 30.326771 | AI20: =[10]byGOVDetalhado!C20 -> 0.9751991 | AJ20: =[10]byGOVDetalhado!D20 -> 2.8057329 | AK20: =[10]byGOVDetalhado!E20 -> 158.33752 | AL20: =[11]byGOVDetalhado!B20 -> 30.439081 | AM20: =[11]byGOVDetalhado!C20 -> 0.91325308 | AN20: =[11]byGOVDetalhado!D20 -> 2.7537358 | AO20: =[11]byGOVDetalhado!E20 -> 157.27218 | AP20: =[12]byGOVDetalhado!B20 -> 40.007507 | AQ20: =[12]byGOVDetalhado!C20 -> 1.0295698 | AR20: =[12]byGOVDetalhado!D20 -> 3.098086 | AS20: =[12]byGOVDetalhado!E20 -> 204.64429 | AT20: =[13]byGOVDetalhado!B20 -> 41.153666 | AU20: =[13]byGOVDetalhado!C20 -> 0.94035817 | AV20: =[13]byGOVDetalhado!D20 -> 2.759021 | AW20: =[13]byGOVDetalhado!E20 -> 208.4817 | AX20: =[14]byGOVDetalhado!B20 -> 46.352209 | AY20: =[14]byGOVDetalhado!C20 -> 0.96271068 | AZ20: =[14]byGOVDetalhado!D20 -> 2.8296132 | BA20: =[14]byGOVDetalhado!E20 -> 232.64222 | BB20: =[15]byGOVDetalhado!B20 -> 49.724602 | BC20: =[15]byGOVDetalhado!C20 -> 0.93263606 | BD20: =[15]byGOVDetalhado!D20 -> 2.7744294 | BE20: =[15]byGOVDetalhado!E20 -> 247.34582 | BF20: =[16]byGOVDetalhado!B20 -> 50.830252 | BG20: =[16]byGOVDetalhado!C20 -> 0.87957546 | BH20: =[16]byGOVDetalhado!D20 -> 2.6755844 | BI20: =[16]byGOVDetalhado!E20 -> 250.68113 | BJ20: =[17]byGOVDetalhado!B20 -> 52.442132 | BK20: =[17]byGOVDetalhado!C20 -> 0.87464969 | BL20: =[17]byGOVDetalhado!D20 -> 2.6633472 | BM20: =[17]byGOVDetalhado!E20 -> 256.50264 | BN20: =[18]byGOVDetalhado!B20 -> 52.680545 | BO20: =[18]byGOVDetalhado!C20 -> 0.84057478 | BP20: =[18]byGOVDetalhado!D20 -> 2.5252442 | BQ20: =[18]byGOVDetalhado!E20 -> 255.62975 | BR20: =[19]byGOVDetalhado!B20 -> 57.142051 | BS20: =[19]byGOVDetalhado!C20 -> 0.87188622 | BT20: =[19]byGOVDetalhado!D20 -> 2.5933528 | BU20: =[19]byGOVDetalhado!E20 -> 275.16997 | BV20: =[20]byGOVDetalhado!B20 -> 63.690799 | BW20: =[20]byGOVDetalhado!C20 -> 0.92450531 | BX20: =[20]byGOVDetalhado!D20 -> 2.6842048 | BY20: =[20]byGOVDetalhado!E20 -> 305.47893 | BZ20: =[21]byGOVDetalhado!B20 -> 63.740821 | CA20: =[21]byGOVDetalhado!C20 -> 0.86262946 | CB20: =[21]byGOVDetalhado!D20 -> 2.5527735 | CC20: =[21]byGOVDetalhado!E20 -> 303.31522 | CD20: =[22]byGOVDetalhado!B20 -> 61.010339 | CE20: =[22]byGOVDetalhado!C20 -> 0.80175519 | CF20: =[22]byGOVDetalhado!D20 -> 2.488636 | CG20: =[22]byGOVDetalhado!E20 -> 288.11664 | CH20: =[23]byGOVDetalhado!B20 -> 74.069403 | CI20: =[23]byGOVDetalhado!C20 -> 0.83235954 | CJ20: =[23]byGOVDetalhado!D20 -> 2.4198051 | CK20: =[23]byGOVDetalhado!E20 -> 347.22587 | CL20: =[24]byGOVDetalhado!B20 -> 77.836053 | CM20: =[24]byGOVDetalhado!C20 -> 0.77220789 | CN20: =[24]byGOVDetalhado!D20 -> 2.2121963 | CO20: =[24]byGOVDetalhado!E20 -> 383.27636 | CP20: =[25]byGOVDetalhado!B20 -> 90.271789 | CQ20: =[25]byGOVDetalhado!C20 -> 0.82490132 | CR20: =[25]byGOVDetalhado!D20 -> 2.385626 | CS20: =[25]byGOVDetalhado!E20 -> 434.34928 | CT20: =[26]byGOVDetalhado!B20 -> 99.843386 | CU20: =[26]byGOVDetalhado!C20 -> 0.85011375 | CV20: =[26]byGOVDetalhado!D20 -> 2.3647119 | CW20: =[26]byGOVDetalhado!E20 -> 469.66613
... A27: Multas e Dívida Ativa | B27: =[2]byGOVDetalhado!B27 -> 4.8908671 | C27: =[2]byGOVDetalhado!C27 -> 0.40676645 | D27: =[2]byGOVDetalhado!D27 -> 1.3310469 | E27: =[2]byGOVDetalhado!E27 -> 28.197831 | F27: =[3]byGOVDetalhado!B27 -> 4.5093598 | G27: =[3]byGOVDetalhado!C27 -> 0.34272032 | H27: =[3]byGOVDetalhado!D27 -> 1.0694642 | I27: =[3]byGOVDetalhado!E27 -> 25.998286 | J27: =[4]byGOVDetalhado!B27 -> 8.5753653 | K27: =[4]byGOVDetalhado!C27 -> 0.57599679 | L27: =[4]byGOVDetalhado!D27 -> 1.7309116 | M27: =[4]byGOVDetalhado!E27 -> 48.101591 | N27: =[5]byGOVDetalhado!B27 -> 5.421533 | O27: =[5]byGOVDetalhado!C27 -> 0.31558154 | P27: =[5]byGOVDetalhado!D27 -> 0.96810519 | Q27: =[5]byGOVDetalhado!E27 -> 30.016387 | R27: =[6]byGOVDetalhado!B27 -> 5.7666842 | S27: =[6]byGOVDetalhado!C27 -> 0.29455657 | T27: =[6]byGOVDetalhado!D27 -> 0.87605898 | U27: =[6]byGOVDetalhado!E27 -> 31.527184 | V27: =[7]byGOVDetalhado!B27 -> 11.75963 | W27: =[7]byGOVDetalhado!C27 -> 0.54177237 | X27: =[7]byGOVDetalhado!D27 -> 1.5592515 | Y27: =[7]byGOVDetalhado!E27 -> 63.513792 | Z27: =[8]byGOVDetalhado!B27 -> 11.635175 | AA27: =[8]byGOVDetalhado!C27 -> 0.48289756 | AB27: =[8]byGOVDetalhado!D27 -> 1.4026129 | AC27: =[8]byGOVDetalhado!E27 -> 62.108879 | AD27: =[9]byGOVDetalhado!B27 -> 14.467598 | AE27: =[9]byGOVDetalhado!C27 -> 0.53184556 | AF27: =[9]byGOVDetalhado!D27 -> 1.5377656 | AG27: =[9]byGOVDetalhado!E27 -> 76.361172 | AH27: =[10]byGOVDetalhado!B27 -> 18.682404 | AI27: =[10]byGOVDetalhado!C27 -> 0.60075843 | AJ27: =[10]byGOVDetalhado!D27 -> 1.7284344 | AK27: =[10]byGOVDetalhado!E27 -> 97.541721 | AL27: =[11]byGOVDetalhado!B27 -> 18.672511 | AM27: =[11]byGOVDetalhado!C27 -> 0.56022478 | AN27: =[11]byGOVDetalhado!D27 -> 1.6892481 | AO27: =[11]byGOVDetalhado!E27 -> 96.47684 | AP27: =[12]byGOVDetalhado!B27 -> 11.687716 | AQ27: =[12]byGOVDetalhado!C27 -> 0.30077653 | AR27: =[12]byGOVDetalhado!D27 -> 0.90506884 | AS27: =[12]byGOVDetalhado!E27 -> 59.784387 | AT27: =[13]byGOVDetalhado!B27 -> 15.1986 | AU27: =[13]byGOVDetalhado!C27 -> 0.34728686 | AV27: =[13]byGOVDetalhado!D27 -> 1.0189434 | AW27: =[13]byGOVDetalhado!E27 -> 76.995082 | AX27: =[14]byGOVDetalhado!B27 -> 38.958865 | AY27: =[14]byGOVDetalhado!C27 -> 0.80915488 | AZ27: =[14]byGOVDetalhado!D27 -> 2.3782797 | BA27: =[14]byGOVDetalhado!E27 -> 195.53495 | BB27: =[15]byGOVDetalhado!B27 -> 38.188029 | BC27: =[15]byGOVDetalhado!C27 -> 0.71625577 | BD27: =[15]byGOVDetalhado!D27 -> 2.1307358 | BE27: =[15]byGOVDetalhado!E27 -> 189.95928 | BF27: =[16]byGOVDetalhado!B27 -> 26.764985 | BG27: =[16]byGOVDetalhado!C27 -> 0.46314592 | BH27: =[16]byGOVDetalhado!D27 -> 1.4088456 | BI27: =[16]byGOVDetalhado!E27 -> 131.99771 | BJ27: =[17]byGOVDetalhado!B27 -> 22.530261 | BK27: =[17]byGOVDetalhado!C27 -> 0.3757682 | BL27: =[17]byGOVDetalhado!D27 -> 1.1442309 | BM27: =[17]byGOVDetalhado!E27 -> 110.19902 | BN27: =[18]byGOVDetalhado!B27 -> 46.357378 | BO27: =[18]byGOVDetalhado!C27 -> 0.73968185 | BP27: =[18]byGOVDetalhado!D27 -> 2.2221429 | BQ27: =[18]byGOVDetalhado!E27 -> 224.94689 | BR27: =[19]byGOVDetalhado!B27 -> 29.200653 | BS27: =[19]byGOVDetalhado!C27 -> 0.44555011 | BT27: =[19]byGOVDetalhado!D27 -> 1.3252516 | BU27: =[19]byGOVDetalhado!E27 -> 140.61698 | BV27: =[20]byGOVDetalhado!B27 -> 38.256325 | BW27: =[20]byGOVDetalhado!C27 -> 0.55531061 | BX27: =[20]byGOVDetalhado!D27 -> 1.6122865 | BY27: =[20]byGOVDetalhado!E27 -> 183.48806 | BZ27: =[21]byGOVDetalhado!B27 -> 26.903796 | CA27: =[21]byGOVDetalhado!C27 -> 0.3640996 | CB27: =[21]byGOVDetalhado!D27 -> 1.0774774 | CC27: =[21]byGOVDetalhado!E27 -> 128.02362 | CD27: =[22]byGOVDetalhado!B27 -> 28.824853 | CE27: =[22]byGOVDetalhado!C27 -> 0.37879605 | CF27: =[22]byGOVDetalhado!D27 -> 1.1757772 | CG27: =[22]byGOVDetalhado!E27 -> 136.12315 | CH27: =[23]byGOVDetalhado!B27 -> 38.326583 | CI27: =[23]byGOVDetalhado!C27 -> 0.43069736 | CJ27: =[23]byGOVDetalhado!D27 -> 1.2521076 | CK27: =[23]byGOVDetalhado!E27 -> 179.66907 | CL27: =[24]byGOVDetalhado!B27 -> 46.504542 | CM27: =[24]byGOVDetalhado!C27 -> 0.46136941 | CN27: =[24]byGOVDetalhado!D27 -> 1.3217162 | CO27: =[24]byGOVDetalhado!E27 -> 228.99531 | CP27: =[25]byGOVDetalhado!B27 -> 53.584088 | CQ27: =[25]byGOVDetalhado!C27 -> 0.48965003 | CR27: =[25]byGOVDetalhado!D27 -> 1.4160746 | CS27: =[25]byGOVDetalhado!E27 -> 257.82373 | CT27: =[26]byGOVDetalhado!B27 -> 77.423706 | CU27: =[26]byGOVDetalhado!C27 -> 0.659222 | CV27: =[26]byGOVDetalhado!D27 -> 1.8337194 | CW27: =[26]byGOVDetalhado!E27 -> 364.20331
B28: =[2]byGOVDetalhado!B28 -> 0 | C28: =[2]byGOVDetalhado!C28 -> 0 | D28: =[2]byGOVDetalhado!D28 -> 0 | E28: =[2]byGOVDetalhado!E28 -> 0 | F28: =[3]byGOVDetalhado!B28 -> 0 | G28: =[3]byGOVDetalhado!C28 -> 0 | H28: =[3]byGOVDetalhado!D28 -> 0 | I28: =[3]byGOVDetalhado!E28 -> 0 | J28: =[4]byGOVDetalhado!B28 -> 0 | K28: =[4]byGOVDetalhado!C28 -> 0 | L28: =[4]byGOVDetalhado!D28 -> 0 | M28: =[4]byGOVDetalhado!E28 -> 0 | N28: =[5]byGOVDetalhado!B28 -> 0 | O28: =[5]byGOVDetalhado!C28 -> 0 | P28: =[5]byGOVDetalhado!D28 -> 0 | Q28: =[5]byGOVDetalhado!E28 -> 0 | R28: =[6]byGOVDetalhado!B28 -> 0 | S28: =[6]byGOVDetalhado!C28 -> 0 | T28: =[6]byGOVDetalhado!D28 -> 0 | U28: =[6]byGOVDetalhado!E28 -> 0 | V28: =[7]byGOVDetalhado!B28 -> 0 | W28: =[7]byGOVDetalhado!C28 -> 0 | X28: =[7]byGOVDetalhado!D28 -> 0 | Y28: =[7]byGOVDetalhado!E28 -> 0 | Z28: =[8]byGOVDetalhado!B28 -> 0 | AA28: =[8]byGOVDetalhado!C28 -> 0 | AB28: =[8]byGOVDetalhado!D28 -> 0 | AC28: =[8]byGOVDetalhado!E28 -> 0 | AD28: =[9]byGOVDetalhado!B28 -> 0 | AE28: =[9]byGOVDetalhado!C28 -> 0 | AF28: =[9]byGOVDetalhado!D28 -> 0 | AG28: =[9]byGOVDetalhado!E28 -> 0 | AH28: =[10]byGOVDetalhado!B28 -> 0 | AI28: =[10]byGOVDetalhado!C28 -> 0 | AJ28: =[10]byGOVDetalhado!D28 -> 0 | AK28: =[10]byGOVDetalhado!E28 -> 0 | AL28: =[11]byGOVDetalhado!B28 -> 0 | AM28: =[11]byGOVDetalhado!C28 -> 0 | AN28: =[11]byGOVDetalhado!D28 -> 0 | AO28: =[11]byGOVDetalhado!E28 -> 0 | AP28: =[12]byGOVDetalhado!B28 -> 0 | AQ28: =[12]byGOVDetalhado!C28 -> 0 | AR28: =[12]byGOVDetalhado!D28 -> 0 | AS28: =[12]byGOVDetalhado!E28 -> 0 | AT28: =[13]byGOVDetalhado!B28 -> 0 | AU28: =[13]byGOVDetalhado!C28 -> 0 | AV28: =[13]byGOVDetalhado!D28 -> 0 | AW28: =[13]byGOVDetalhado!E28 -> 0 | AX28: =[14]byGOVDetalhado!B28 -> 0 | AY28: =[14]byGOVDetalhado!C28 -> 0 | AZ28: =[14]byGOVDetalhado!D28 -> 0 | BA28: =[14]byGOVDetalhado!E28 -> 0 | BB28: =[15]byGOVDetalhado!B28 -> 0 | BC28: =[15]byGOVDetalhado!C28 -> 0 | BD28: =[15]byGOVDetalhado!D28 -> 0 | BE28: =[15]byGOVDetalhado!E28 -> 0 | BF28: =[16]byGOVDetalhado!B28 -> 0 | BG28: =[16]byGOVDetalhado!C28 -> 0 | BH28: =[16]byGOVDetalhado!D28 -> 0 | BI28: =[16]byGOVDetalhado!E28 -> 0 | BJ28: =[17]byGOVDetalhado!B28 -> 0 | BK28: =[17]byGOVDetalhado!C28 -> 0 | BL28: =[17]byGOVDetalhado!D28 -> 0 | BM28: =[17]byGOVDetalhado!E28 -> 0 | BN28: =[18]byGOVDetalhado!B28 -> 0 | BO28: =[18]byGOVDetalhado!C28 -> 0 | BP28: =[18]byGOVDetalhado!D28 -> 0 | BQ28: =[18]byGOVDetalhado!E28 -> 0 | BR28: =[19]byGOVDetalhado!B28 -> 0 | BS28: =[19]byGOVDetalhado!C28 -> 0 | BT28: =[19]byGOVDetalhado!D28 -> 0 | BU28: =[19]byGOVDetalhado!E28 -> 0 | BV28: =[20]byGOVDetalhado!B28 -> 0 | BW28: =[20]byGOVDetalhado!C28 -> 0 | BX28: =[20]byGOVDetalhado!D28 -> 0 | BY28: =[20]byGOVDetalhado!E28 -> 0 | BZ28: =[21]byGOVDetalhado!B28 -> 0 | CA28: =[21]byGOVDetalhado!C28 -> 0 | CB28: =[21]byGOVDetalhado!D28 -> 0 | CC28: =[21]byGOVDetalhado!E28 -> 0 | CD28: =[22]byGOVDetalhado!B28 -> 0 | CE28: =[22]byGOVDetalhado!C28 -> 0 | CF28: =[22]byGOVDetalhado!D28 -> 0 | CG28: =[22]byGOVDetalhado!E28 -> 0 | CH28: =[23]byGOVDetalhado!B28 -> 0 | CI28: =[23]byGOVDetalhado!C28 -> 0 | CJ28: =[23]byGOVDetalhado!D28 -> 0 | CK28: =[23]byGOVDetalhado!E28 -> 0 | CL28: =[24]byGOVDetalhado!B28 -> 0 | CM28: =[24]byGOVDetalhado!C28 -> 0 | CN28: =[24]byGOVDetalhado!D28 -> 0 | CO28: =[24]byGOVDetalhado!E28 -> 0 | CP28: =[25]byGOVDetalhado!B28 -> 0 | CQ28: =[25]byGOVDetalhado!C28 -> 0 | CR28: =[25]byGOVDetalhado!D28 -> 0 | CS28: =[25]byGOVDetalhado!E28 -> 0 | CT28: =[26]byGOVDetalhado!B28 -> 0 | CU28: =[26]byGOVDetalhado!C28 -> 0 | CV28: =[26]byGOVDetalhado!D28 -> 0 | CW28: =[26]byGOVDetalhado!E28 -> 0
A29: ESTADOS | B29: =[2]byGOVDetalhado!B29 -> 101.55271 | C29: =[2]byGOVDetalhado!C29 -> 8.4459945 | D29: =[2]byGOVDetalhado!D29 -> 27.637517 | E29: =[2]byGOVDetalhado!E29 -> 585.49255 | F29: =[3]byGOVDetalhado!B29 -> 116.59916 | G29: =[3]byGOVDetalhado!C29 -> 8.8617682 | H29: =[3]byGOVDetalhado!D29 -> 27.653288 | I29: =[3]byGOVDetalhado!E29 -> 672.2414 | J29: =[4]byGOVDetalhado!B29 -> 131.20896 | K29: =[4]byGOVDetalhado!C29 -> 8.8131451 | L29: =[4]byGOVDetalhado!D29 -> 26.484132 | M29: =[4]byGOVDetalhado!E29 -> 735.98726 | N29: =[5]byGOVDetalhado!B29 -> 150.58469 | O29: =[5]byGOVDetalhado!C29 -> 8.7653712 | P29: =[5]byGOVDetalhado!D29 -> 26.88941 | Q29: =[5]byGOVDetalhado!E29 -> 833.71409 | R29: =[6]byGOVDetalhado!B29 -> 176.27545 | S29: =[6]byGOVDetalhado!C29 -> 9.0039772 | T29: =[6]byGOVDetalhado!D29 -> 26.779288 | U29: =[6]byGOVDetalhado!E29 -> 963.71998 | V29: =[7]byGOVDetalhado!B29 -> 196.79826 | W29: =[7]byGOVDetalhado!C29 -> 9.0665999 | X29: =[7]byGOVDetalhado!D29 -> 26.094187 | Y29: =[7]byGOVDetalhado!E29 -> 1062.9079 | Z29: =[8]byGOVDetalhado!B29 -> 217.05425 | AA29: =[8]byGOVDetalhado!C29 -> 9.0084564 | AB29: =[8]byGOVDetalhado!D29 -> 26.16575 | AC29: =[8]byGOVDetalhado!E29 -> 1158.6414 | AD29: =[9]byGOVDetalhado!B29 -> 238.87844 | AE29: =[9]byGOVDetalhado!C29 -> 8.7814464 | AF29: =[9]byGOVDetalhado!D29 -> 25.390465 | AG29: =[9]byGOVDetalhado!E29 -> 1260.82 | AH29: =[10]byGOVDetalhado!B29 -> 278.97677 | AI29: =[10]byGOVDetalhado!C29 -> 8.9708825 | AJ29: =[10]byGOVDetalhado!D29 -> 25.810012 | AK29: =[10]byGOVDetalhado!E29 -> 1456.551 | AL29: =[11]byGOVDetalhado!B29 -> 291.3799 | AM29: =[11]byGOVDetalhado!C29 -> 8.7421688 | AN29: =[11]byGOVDetalhado!D29 -> 26.360298 | AO29: =[11]byGOVDetalhado!E29 -> 1505.4972 | AP29: =[12]byGOVDetalhado!B29 -> 342.29349 | AQ29: =[12]byGOVDetalhado!C29 -> 8.8087227 | AR29: =[12]byGOVDetalhado!D29 -> 26.506391 | AS29: =[12]byGOVDetalhado!E29 -> 1750.8816 | AT29: =[13]byGOVDetalhado!B29 -> 381.20877 | AU29: =[13]byGOVDetalhado!C29 -> 8.7105918 | AV29: =[13]byGOVDetalhado!D29 -> 25.55697 | AW29: =[13]byGOVDetalhado!E29 -> 1931.178 | AX29: =[14]byGOVDetalhado!B29 -> 421.75593 | AY29: =[14]byGOVDetalhado!C29 -> 8.759646 | AZ29: =[14]byGOVDetalhado!D29 -> 25.746478 | BA29: =[14]byGOVDetalhado!E29 -> 2116.7974 | BB29: =[15]byGOVDetalhado!B29 -> 467.13276 | BC29: =[15]byGOVDetalhado!C29 -> 8.7615555 | BD29: =[15]byGOVDetalhado!D29 -> 26.064097 | BE29: =[15]byGOVDetalhado!E29 -> 2323.6654 | BF29: =[16]byGOVDetalhado!B29 -> 503.87862 | BG29: =[16]byGOVDetalhado!C29 -> 8.7192025 | BH29: =[16]byGOVDetalhado!D29 -> 26.52298 | BI29: =[16]byGOVDetalhado!E29 -> 2484.9938 | BJ29: =[17]byGOVDetalhado!B29 -> 527.86464 | BK29: =[17]byGOVDetalhado!C29 -> 8.8039259 | BL29: =[17]byGOVDetalhado!D29 -> 26.808346 | BM29: =[17]byGOVDetalhado!E29 -> 2581.8683 | BN29: =[18]byGOVDetalhado!B29 -> 560.81875 | BO29: =[18]byGOVDetalhado!C29 -> 8.9484667 | BP29: =[18]byGOVDetalhado!D29 -> 26.882871 | BQ29: =[18]byGOVDetalhado!E29 -> 2721.3454 | BR29: =[19]byGOVDetalhado!B29 -> 599.89915 | BS29: =[19]byGOVDetalhado!C29 -> 9.1533956 | BT29: =[19]byGOVDetalhado!D29 -> 27.226011 | BU29: =[19]byGOVDetalhado!E29 -> 2888.8397 | BV29: =[20]byGOVDetalhado!B29 -> 650.27292 | BW29: =[20]byGOVDetalhado!C29 -> 9.439052 | BX29: =[20]byGOVDetalhado!D29 -> 27.405304 | BY29: =[20]byGOVDetalhado!E29 -> 3118.8912 | BZ29: =[21]byGOVDetalhado!B29 -> 694.7788 | CA29: =[21]byGOVDetalhado!C29 -> 9.4027132 | CB29: =[21]byGOVDetalhado!D29 -> 27.825385 | CC29: =[21]byGOVDetalhado!E29 -> 3306.1542 | CD29: =[22]byGOVDetalhado!B29 -> 712.17638 | CE29: =[22]byGOVDetalhado!C29 -> 9.3589238 | CF29: =[22]byGOVDetalhado!D29 -> 29.049958 | CG29: =[22]byGOVDetalhado!E29 -> 3363.1983 | CH29: =[23]byGOVDetalhado!B29 -> 858.14661 | CI29: =[23]byGOVDetalhado!C29 -> 9.6434761 | CJ29: =[23]byGOVDetalhado!D29 -> 28.03516 | CK29: =[23]byGOVDetalhado!E29 -> 4022.8582 | CL29: =[24]byGOVDetalhado!B29 -> 950.1873 | CM29: =[24]byGOVDetalhado!C29 -> 9.4267643 | CN29: =[24]byGOVDetalhado!D29 -> 27.005491 | CO29: =[24]byGOVDetalhado!E29 -> 4678.8643 | CP29: =[25]byGOVDetalhado!B29 -> 995.58127 | CQ29: =[25]byGOVDetalhado!C29 -> 9.0975964 | CR29: =[25]byGOVDetalhado!D29 -> 26.310374 | CS29: =[25]byGOVDetalhado!E29 -> 4790.3117 | CT29: =[26]byGOVDetalhado!B29 -> 1127.2114 | CU29: =[26]byGOVDetalhado!C29 -> 9.5976102 | CV29: =[26]byGOVDetalhado!D29 -> 26.697113 | CW29: =[26]byGOVDetalhado!E29 -> 5302.4344
A30: ICMS | B30: =[2]byGOVDetalhado!B30 -> 82.274924 | C30: =[2]byGOVDetalhado!C30 -> 6.8426882 | D30: =[2]byGOVDetalhado!D30 -> 22.391077 | E30: =[2]byGOVDetalhado!E30 -> 474.34828 | F30: =[3]byGOVDetalhado!B30 -> 92.126566 | G30: =[3]byGOVDetalhado!C30 -> 7.0018024 | H30: =[3]byGOVDetalhado!D30 -> 21.849235 | I30: =[3]byGOVDetalhado!E30 -> 531.14698 | J30: =[4]byGOVDetalhado!B30 -> 102.95168 | K30: =[4]byGOVDetalhado!C30 -> 6.9151381 | L30: =[4]byGOVDetalhado!D30 -> 20.780485 | M30: =[4]byGOVDetalhado!E30 -> 577.48437 | N30: =[5]byGOVDetalhado!B30 -> 117.13526 | O30: =[5]byGOVDetalhado!C30 -> 6.8183163 | P30: =[5]byGOVDetalhado!D30 -> 20.916456 | Q30: =[5]byGOVDetalhado!E30 -> 648.52089 | R30: =[6]byGOVDetalhado!B30 -> 136.58039 | S30: =[6]byGOVDetalhado!C30 -> 6.976392 | T30: =[6]byGOVDetalhado!D30 -> 20.748921 | U30: =[6]byGOVDetalhado!E30 -> 746.70206 | V30: =[7]byGOVDetalhado!B30 -> 152.36755 | W30: =[7]byGOVDetalhado!C30 -> 7.0196535 | X30: =[7]byGOVDetalhado!D30 -> 20.202959 | Y30: =[7]byGOVDetalhado!E30 -> 822.93753 | Z30: =[8]byGOVDetalhado!B30 -> 165.66636 | AA30: =[8]byGOVDetalhado!C30 -> 6.8756919 | AB30: =[8]byGOVDetalhado!D30 -> 19.970972 | AC30: =[8]byGOVDetalhado!E30 -> 884.33147 | AD30: =[9]byGOVDetalhado!B30 -> 183.53723 | AE30: =[9]byGOVDetalhado!C30 -> 6.74704 | AF30: =[9]byGOVDetalhado!D30 -> 19.508231 | AG30: =[9]byGOVDetalhado!E30 -> 968.72461 | AH30: =[10]byGOVDetalhado!B30 -> 217.29792 | AI30: =[10]byGOVDetalhado!C30 -> 6.9875141 | AJ30: =[10]byGOVDetalhado!D30 -> 20.103688 | AK30: =[10]byGOVDetalhado!E30 -> 1134.5228 | AL30: =[11]byGOVDetalhado!B30 -> 225.33715 | AM30: =[11]byGOVDetalhado!C30 -> 6.7607115 | AN30: =[11]byGOVDetalhado!D30 -> 20.385601 | AO30: =[11]byGOVDetalhado!E30 -> 1164.2685 | AP30: =[12]byGOVDetalhado!B30 -> 264.74599 | AQ30: =[12]byGOVDetalhado!C30 -> 6.8130833 | AR30: =[12]byGOVDetalhado!D30 -> 20.501298 | AS30: =[12]byGOVDetalhado!E30 -> 1354.2147 | AT30: =[13]byGOVDetalhado!B30 -> 294.37887 | AU30: =[13]byGOVDetalhado!C30 -> 6.7265351 | AV30: =[13]byGOVDetalhado!D30 -> 19.735726 | AW30: =[13]byGOVDetalhado!E30 -> 1491.3035 | AX30: =[14]byGOVDetalhado!B30 -> 323.41528 | AY30: =[14]byGOVDetalhado!C30 -> 6.7171631 | AZ30: =[14]byGOVDetalhado!D30 -> 19.743183 | BA30: =[14]byGOVDetalhado!E30 -> 1623.2247 | BB30: =[15]byGOVDetalhado!B30 -> 357.38316 | BC30: =[15]byGOVDetalhado!C30 -> 6.7030889 | BD30: =[15]byGOVDetalhado!D30 -> 19.940518 | BE30: =[15]byGOVDetalhado!E30 -> 1777.7363 | BF30: =[16]byGOVDetalhado!B30 -> 381.24976 | BG30: =[16]byGOVDetalhado!C30 -> 6.5972117 | BH30: =[16]byGOVDetalhado!D30 -> 20.068087 | BI30: =[16]byGOVDetalhado!E30 -> 1880.2213 | BJ30: =[17]byGOVDetalhado!B30 -> 391.98354 | BK30: =[17]byGOVDetalhado!C30 -> 6.5376495 | BL30: =[17]byGOVDetalhado!D30 -> 19.907433 | BM30: =[17]byGOVDetalhado!E30 -> 1917.2526 | BN30: =[18]byGOVDetalhado!B30 -> 411.9384 | BO30: =[18]byGOVDetalhado!C30 -> 6.5729205 | BP30: =[18]byGOVDetalhado!D30 -> 19.746285 | BQ30: =[18]byGOVDetalhado!E30 -> 1998.9108 | BR30: =[19]byGOVDetalhado!B30 -> 445.13304 | BS30: =[19]byGOVDetalhado!C30 -> 6.7919396 | BT30: =[19]byGOVDetalhado!D30 -> 20.202058 | BU30: =[19]byGOVDetalhado!E30 -> 2143.557 | BV30: =[20]byGOVDetalhado!B30 -> 491.64152 | BW30: =[20]byGOVDetalhado!C30 -> 7.1364342 | BX30: =[20]byGOVDetalhado!D30 -> 20.719893 | BY30: =[20]byGOVDetalhado!E30 -> 2358.0506 | BZ30: =[21]byGOVDetalhado!B30 -> 524.20017 | CA30: =[21]byGOVDetalhado!C30 -> 7.0942059 | CB30: =[21]byGOVDetalhado!D30 -> 20.993835 | CC30: =[21]byGOVDetalhado!E30 -> 2494.4437 | CD30: =[22]byGOVDetalhado!B30 -> 538.05601 | CE30: =[22]byGOVDetalhado!C30 -> 7.0707556 | CF30: =[22]byGOVDetalhado!D30 -> 21.947519 | CG30: =[22]byGOVDetalhado!E30 -> 2540.9282 | CH30: =[23]byGOVDetalhado!B30 -> 655.21342 | CI30: =[23]byGOVDetalhado!C30 -> 7.3630017 | CJ30: =[23]byGOVDetalhado!D30 -> 21.405449 | CK30: =[23]byGOVDetalhado!E30 -> 3071.5389 | CL30: =[24]byGOVDetalhado!B30 -> 709.15701 | CM30: =[24]byGOVDetalhado!C30 -> 7.0355139 | CN30: =[24]byGOVDetalhado!D30 -> 20.155114 | CO30: =[24]byGOVDetalhado!E30 -> 3491.9951 | CP30: =[25]byGOVDetalhado!B30 -> 720.5693 | CQ30: =[25]byGOVDetalhado!C30 -> 6.584544 | CR30: =[25]byGOVDetalhado!D30 -> 19.042592 | CS30: =[25]byGOVDetalhado!E30 -> 3467.0716 | CT30: =[26]byGOVDetalhado!B30 -> 828.14597 | CU30: =[26]byGOVDetalhado!C30 -> 7.0512259 | CV30: =[26]byGOVDetalhado!D30 -> 19.613985 | CW30: =[26]byGOVDetalhado!E30 -> 3895.6222
A31: IPVA | B31: =[2]byGOVDetalhado!B31 -> 5.296891 | C31: =[2]byGOVDetalhado!C31 -> 0.44053488 | D31: =[2]byGOVDetalhado!D31 -> 1.4415461 | E31: =[2]byGOVDetalhado!E31 -> 30.538723 | F31: =[3]byGOVDetalhado!B31 -> 6.2183107 | G31: =[3]byGOVDetalhado!C31 -> 0.472604 | H31: =[3]byGOVDetalhado!D31 -> 1.4747683 | I31: =[3]byGOVDetalhado!E31 -> 35.851081 | J31: =[4]byGOVDetalhado!B31 -> 6.9447605 | K31: =[4]byGOVDetalhado!C31 -> 0.46647106 | L31: =[4]byGOVDetalhado!D31 -> 1.4017789 | M31: =[4]byGOVDetalhado!E31 -> 38.955078 | N31: =[5]byGOVDetalhado!B31 -> 7.6435455 | O31: =[5]byGOVDetalhado!C31 -> 0.44492247 | P31: =[5]byGOVDetalhado!D31 -> 1.3648826 | Q31: =[5]byGOVDetalhado!E31 -> 42.318587 | R31: =[6]byGOVDetalhado!B31 -> 8.8129406 | S31: =[6]byGOVDetalhado!C31 -> 0.45015636 | T31: =[6]byGOVDetalhado!D31 -> 1.338838 | U31: =[6]byGOVDetalhado!E31 -> 48.18145 | V31: =[7]byGOVDetalhado!B31 -> 10.387591 | W31: =[7]byGOVDetalhado!C31 -> 0.47856182 | X31: =[7]byGOVDetalhado!D31 -> 1.377328 | Y31: =[7]byGOVDetalhado!E31 -> 56.103407 | Z31: =[8]byGOVDetalhado!B31 -> 12.064105 | AA31: =[8]byGOVDetalhado!C31 -> 0.50069954 | AB31: =[8]byGOVDetalhado!D31 -> 1.4543201 | AC31: =[8]byGOVDetalhado!E31 -> 64.398518 | AD31: =[9]byGOVDetalhado!B31 -> 14.286212 | AE31: =[9]byGOVDetalhado!C31 -> 0.52517762 | AF31: =[9]byGOVDetalhado!D31 -> 1.518486 | AG31: =[9]byGOVDetalhado!E31 -> 75.403804 | AH31: =[10]byGOVDetalhado!B31 -> 16.629265 | AI31: =[10]byGOVDetalhado!C31 -> 0.53473694 | AJ31: =[10]byGOVDetalhado!D31 -> 1.5384848 | AK31: =[10]byGOVDetalhado!E31 -> 86.822187 | AL31: =[11]byGOVDetalhado!B31 -> 20.071088 | AM31: =[11]byGOVDetalhado!C31 -> 0.60218581 | AN31: =[11]byGOVDetalhado!D31 -> 1.8157733 | AO31: =[11]byGOVDetalhado!E31 -> 103.70299 | AP31: =[12]byGOVDetalhado!B31 -> 21.277523 | AQ31: =[12]byGOVDetalhado!C31 -> 0.54756461 | AR31: =[12]byGOVDetalhado!D31 -> 1.6476806 | AS31: =[12]byGOVDetalhado!E31 -> 108.83766 | AT31: =[13]byGOVDetalhado!B31 -> 23.939387 | AU31: =[13]byGOVDetalhado!C31 -> 0.54701318 | AV31: =[13]byGOVDetalhado!D31 -> 1.6049426 | AW31: =[13]byGOVDetalhado!E31 -> 121.27532 | AX31: =[14]byGOVDetalhado!B31 -> 26.68516 | AY31: =[14]byGOVDetalhado!C31 -> 0.55423656 | AZ31: =[14]byGOVDetalhado!D31 -> 1.6290201 | BA31: =[14]byGOVDetalhado!E31 -> 133.9331 | BB31: =[15]byGOVDetalhado!B31 -> 28.809677 | BC31: =[15]byGOVDetalhado!C31 -> 0.54035513 | BD31: =[15]byGOVDetalhado!D31 -> 1.6074621 | BE31: =[15]byGOVDetalhado!E31 -> 143.3084 | BF31: =[16]byGOVDetalhado!B31 -> 31.271539 | BG31: =[16]byGOVDetalhado!C31 -> 0.5411281 | BH31: =[16]byGOVDetalhado!D31 -> 1.64606 | BI31: =[16]byGOVDetalhado!E31 -> 154.22282 | BJ31: =[17]byGOVDetalhado!B31 -> 34.912679 | BK31: =[17]byGOVDetalhado!C31 -> 0.58228684 | BL31: =[17]byGOVDetalhado!D31 -> 1.7730894 | BM31: =[17]byGOVDetalhado!E31 -> 170.76336 | BN31: =[18]byGOVDetalhado!B31 -> 37.7041 | BO31: =[18]byGOVDetalhado!C31 -> 0.60160949 | BP31: =[18]byGOVDetalhado!D31 -> 1.8073476 | BQ31: =[18]byGOVDetalhado!E31 -> 182.95729 | BR31: =[19]byGOVDetalhado!B31 -> 39.125596 | BS31: =[19]byGOVDetalhado!C31 -> 0.59698711 | BT31: =[19]byGOVDetalhado!D31 -> 1.7756883 | BU31: =[19]byGOVDetalhado!E31 -> 188.41096 | BV31: =[20]byGOVDetalhado!B31 -> 44.770656 | BW31: =[20]byGOVDetalhado!C31 -> 0.64986953 | BX31: =[20]byGOVDetalhado!D31 -> 1.8868284 | BY31: =[20]byGOVDetalhado!E31 -> 214.73262 | BZ31: =[21]byGOVDetalhado!B31 -> 47.941198 | CA31: =[21]byGOVDetalhado!C31 -> 0.64880698 | CB31: =[21]byGOVDetalhado!D31 -> 1.9200101 | CC31: =[21]byGOVDetalhado!E31 -> 228.13159 | CD31: =[22]byGOVDetalhado!B31 -> 49.426633 | CE31: =[22]byGOVDetalhado!C31 -> 0.64953023 | CF31: =[22]byGOVDetalhado!D31 -> 2.016132 | CG31: =[22]byGOVDetalhado!E31 -> 233.41348 | CH31: =[23]byGOVDetalhado!B31 -> 53.679325 | CI31: =[23]byGOVDetalhado!C31 -> 0.60322477 | CJ31: =[23]byGOVDetalhado!D31 -> 1.7536729 | CK31: =[23]byGOVDetalhado!E31 -> 251.64035 | CL31: =[24]byGOVDetalhado!B31 -> 66.218662 | CM31: =[24]byGOVDetalhado!C31 -> 0.65695229 | CN31: =[24]byGOVDetalhado!D31 -> 1.8820158 | CO31: =[24]byGOVDetalhado!E31 -> 326.07059 | CP31: =[25]byGOVDetalhado!B31 -> 82.462627 | CQ31: =[25]byGOVDetalhado!C31 -> 0.75354139 | CR31: =[25]byGOVDetalhado!D31 -> 2.1792521 | CS31: =[25]byGOVDetalhado!E31 -> 396.77493 | CT31: =[26]byGOVDetalhado!B31 -> 87.533122 | CU31: =[26]byGOVDetalhado!C31 -> 0.74529834 | CV31: =[26]byGOVDetalhado!D31 -> 2.073153 | CW31: =[26]byGOVDetalhado!E31 -> 411.75829
A32: ITCD | B32: =[2]byGOVDetalhado!B32 -> 0.328869 | C32: =[2]byGOVDetalhado!C32 -> 0.027351566 | D32: =[2]byGOVDetalhado!D32 -> 0.089501523 | E32: =[2]byGOVDetalhado!E32 -> 1.8960631 | F32: =[3]byGOVDetalhado!B32 -> 0.33517398 | G32: =[3]byGOVDetalhado!C32 -> 0.02547389 | H32: =[3]byGOVDetalhado!D32 -> 0.079491678 | I32: =[3]byGOVDetalhado!E32 -> 1.9324138 | J32: =[4]byGOVDetalhado!B32 -> 0.52009774 | K32: =[4]byGOVDetalhado!C32 -> 0.034934329 | L32: =[4]byGOVDetalhado!D32 -> 0.10498016 | M32: =[4]byGOVDetalhado!E32 -> 2.9173718 | N32: =[5]byGOVDetalhado!B32 -> 0.87184423 | O32: =[5]byGOVDetalhado!C32 -> 0.050749104 | P32: =[5]byGOVDetalhado!D32 -> 0.15568234 | Q32: =[5]byGOVDetalhado!E32 -> 4.8269767 | R32: =[6]byGOVDetalhado!B32 -> 0.7360696 | S32: =[6]byGOVDetalhado!C32 -> 0.037597713 | T32: =[6]byGOVDetalhado!D32 -> 0.11182169 | U32: =[6]byGOVDetalhado!E32 -> 4.0241846 | V32: =[7]byGOVDetalhado!B32 -> 0.81550389 | W32: =[7]byGOVDetalhado!C32 -> 0.037570696 | X32: =[7]byGOVDetalhado!D32 -> 0.10813059 | Y32: =[7]byGOVDetalhado!E32 -> 4.4045387 | Z32: =[8]byGOVDetalhado!B32 -> 0.96697826 | AA32: =[8]byGOVDetalhado!C32 -> 0.040132738 | AB32: =[8]byGOVDetalhado!D32 -> 0.1165686 | AC32: =[8]byGOVDetalhado!E32 -> 5.1617559 | AD32: =[9]byGOVDetalhado!B32 -> 1.2044485 | AE32: =[9]byGOVDetalhado!C32 -> 0.044276914 | AF32: =[9]byGOVDetalhado!D32 -> 0.12802121 | AG32: =[9]byGOVDetalhado!E32 -> 6.3571783 | AH32: =[10]byGOVDetalhado!B32 -> 1.4858492 | AI32: =[10]byGOVDetalhado!C32 -> 0.047779529 | AJ32: =[10]byGOVDetalhado!D32 -> 0.13746587 | AK32: =[10]byGOVDetalhado!E32 -> 7.7576896 | AL32: =[11]byGOVDetalhado!B32 -> 1.6730877 | AM32: =[11]byGOVDetalhado!C32 -> 0.050197064 | AN32: =[11]byGOVDetalhado!D32 -> 0.15135941 | AO32: =[11]byGOVDetalhado!E32 -> 8.6444838 | AP32: =[12]byGOVDetalhado!B32 -> 2.508177 | AQ32: =[12]byGOVDetalhado!C32 -> 0.064546469 | AR32: =[12]byGOVDetalhado!D32 -> 0.19422725 | AS32: =[12]byGOVDetalhado!E32 -> 12.829695 | AT32: =[13]byGOVDetalhado!B32 -> 2.7547689 | AU32: =[13]byGOVDetalhado!C32 -> 0.062946263 | AV32: =[13]byGOVDetalhado!D32 -> 0.18468501 | AW32: =[13]byGOVDetalhado!E32 -> 13.955474 | AX32: =[14]byGOVDetalhado!B32 -> 3.3911116 | AY32: =[14]byGOVDetalhado!C32 -> 0.070431581 | AZ32: =[14]byGOVDetalhado!D32 -> 0.20701352 | BA32: =[14]byGOVDetalhado!E32 -> 17.020025 | BB32: =[15]byGOVDetalhado!B32 -> 4.113285 | BC32: =[15]byGOVDetalhado!C32 -> 0.077148892 | BD32: =[15]byGOVDetalhado!D32 -> 0.22950448 | BE32: =[15]byGOVDetalhado!E32 -> 20.460774 | BF32: =[16]byGOVDetalhado!B32 -> 4.6600297 | BG32: =[16]byGOVDetalhado!C32 -> 0.080637958 | BH32: =[16]byGOVDetalhado!D32 -> 0.24529296 | BI32: =[16]byGOVDetalhado!E32 -> 22.982013 | BJ32: =[17]byGOVDetalhado!B32 -> 6.4155264 | BK32: =[17]byGOVDetalhado!C32 -> 0.10700057 | BL32: =[17]byGOVDetalhado!D32 -> 0.3258215 | BM32: =[17]byGOVDetalhado!E32 -> 31.37934 | BN32: =[18]byGOVDetalhado!B32 -> 7.3011862 | BO32: =[18]byGOVDetalhado!C32 -> 0.11649828 | BP32: =[18]byGOVDetalhado!D32 -> 0.34998267 | BQ32: =[18]byGOVDetalhado!E32 -> 35.428647 | BR32: =[19]byGOVDetalhado!B32 -> 7.0893822 | BS32: =[19]byGOVDetalhado!C32 -> 0.10817138 | BT32: =[19]byGOVDetalhado!D32 -> 0.32174675 | BU32: =[19]byGOVDetalhado!E32 -> 34.13922 | BV32: =[20]byGOVDetalhado!B32 -> 7.7539016 | BW32: =[20]byGOVDetalhado!C32 -> 0.11255194 | BX32: =[20]byGOVDetalhado!D32 -> 0.32678284 | BY32: =[20]byGOVDetalhado!E32 -> 37.189886 | BZ32: =[21]byGOVDetalhado!B32 -> 8.9722657 | CA32: =[21]byGOVDetalhado!C32 -> 0.12142518 | CB32: =[21]byGOVDetalhado!D32 -> 0.35933271 | CC32: =[21]byGOVDetalhado!E32 -> 42.695163 | CD32: =[22]byGOVDetalhado!B32 -> 9.5149503 | CE32: =[22]byGOVDetalhado!C32 -> 0.12503882 | CF32: =[22]byGOVDetalhado!D32 -> 0.38811861 | CG32: =[22]byGOVDetalhado!E32 -> 44.933622 | CH32: =[23]byGOVDetalhado!B32 -> 12.905018 | CI32: =[23]byGOVDetalhado!C32 -> 0.14502094 | CJ32: =[23]byGOVDetalhado!D32 -> 0.42159956 | CK32: =[23]byGOVDetalhado!E32 -> 60.496721 | CL32: =[24]byGOVDetalhado!B32 -> 13.671435 | CM32: =[24]byGOVDetalhado!C32 -> 0.13563367 | CN32: =[24]byGOVDetalhado!D32 -> 0.38855898 | CO32: =[24]byGOVDetalhado!E32 -> 67.320187 | CP32: =[25]byGOVDetalhado!B32 -> 15.699626 | CQ32: =[25]byGOVDetalhado!C32 -> 0.14346278 | CR32: =[25]byGOVDetalhado!D32 -> 0.41489635 | CS32: =[25]byGOVDetalhado!E32 -> 75.539892 | CT32: =[26]byGOVDetalhado!B32 -> 18.575221 | CU32: =[26]byGOVDetalhado!C32 -> 0.1581582 | CV32: =[26]byGOVDetalhado!D32 -> 0.43993946 | CW32: =[26]byGOVDetalhado!E32 -> 87.378365
A33: IRRF | B33: =[2]byGOVDetalhado!B33 -> 4.131 | C33: =[2]byGOVDetalhado!C33 -> 0.34356938 | D33: =[2]byGOVDetalhado!D33 -> 1.1242494 | E33: =[2]byGOVDetalhado!E33 -> 23.816889 | F33: =[3]byGOVDetalhado!B33 -> 4.7881215 | G33: =[3]byGOVDetalhado!C33 -> 0.36390677 | H33: =[3]byGOVDetalhado!D33 -> 1.1355768 | I33: =[3]byGOVDetalhado!E33 -> 27.605461 | J33: =[4]byGOVDetalhado!B33 -> 5.6425586 | K33: =[4]byGOVDetalhado!C33 -> 0.37900375 | L33: =[4]byGOVDetalhado!D33 -> 1.1389334 | M33: =[4]byGOVDetalhado!E33 -> 31.650668 | N33: =[5]byGOVDetalhado!B33 -> 6.6916211 | O33: =[5]byGOVDetalhado!C33 -> 0.38951198 | P33: =[5]byGOVDetalhado!D33 -> 1.1949006 | Q33: =[5]byGOVDetalhado!E33 -> 37.048246 | R33: =[6]byGOVDetalhado!B33 -> 8.1076954 | S33: =[6]byGOVDetalhado!C33 -> 0.41413312 | T33: =[6]byGOVDetalhado!D33 -> 1.231699 | U33: =[6]byGOVDetalhado!E33 -> 44.325786 | V33: =[7]byGOVDetalhado!B33 -> 8.2672771 | W33: =[7]byGOVDetalhado!C33 -> 0.38087783 | X33: =[7]byGOVDetalhado!D33 -> 1.0961879 | Y33: =[7]byGOVDetalhado!E33 -> 44.651586 | Z33: =[8]byGOVDetalhado!B33 -> 10.28424 | AA33: =[8]byGOVDetalhado!C33 -> 0.42682937 | AB33: =[8]byGOVDetalhado!D33 -> 1.2397585 | AC33: =[8]byGOVDetalhado!E33 -> 54.897551 | AD33: =[9]byGOVDetalhado!B33 -> 11.301139 | AE33: =[9]byGOVDetalhado!C33 -> 0.41544287 | AF33: =[9]byGOVDetalhado!D33 -> 1.2012016 | AG33: =[9]byGOVDetalhado!E33 -> 59.648339 | AH33: =[10]byGOVDetalhado!B33 -> 12.936655 | AI33: =[10]byGOVDetalhado!C33 -> 0.41599598 | AJ33: =[10]byGOVDetalhado!D33 -> 1.1968567 | AK33: =[10]byGOVDetalhado!E33 -> 67.542894 | AL33: =[11]byGOVDetalhado!B33 -> 12.208578 | AM33: =[11]byGOVDetalhado!C33 -> 0.36628969 | AN33: =[11]byGOVDetalhado!D33 -> 1.1044748 | AO33: =[11]byGOVDetalhado!E33 -> 63.079094 | AP33: =[12]byGOVDetalhado!B33 -> 16.538762 | AQ33: =[12]byGOVDetalhado!C33 -> 0.42561537 | AR33: =[12]byGOVDetalhado!D33 -> 1.2807223 | AS33: =[12]byGOVDetalhado!E33 -> 84.598201 | AT33: =[13]byGOVDetalhado!B33 -> 19.382035 | AU33: =[13]byGOVDetalhado!C33 -> 0.44287804 | AV33: =[13]byGOVDetalhado!D33 -> 1.2994089 | AW33: =[13]byGOVDetalhado!E33 -> 98.188084 | AX33: =[14]byGOVDetalhado!B33 -> 20.641858 | AY33: =[14]byGOVDetalhado!C33 -> 0.42872039 | AZ33: =[14]byGOVDetalhado!D33 -> 1.2601012 | BA33: =[14]byGOVDetalhado!E33 -> 103.6017 | BB33: =[15]byGOVDetalhado!B33 -> 22.502789 | BC33: =[15]byGOVDetalhado!C33 -> 0.42206297 | BD33: =[15]byGOVDetalhado!D33 -> 1.2555636 | BE33: =[15]byGOVDetalhado!E33 -> 111.93596 | BF33: =[16]byGOVDetalhado!B33 -> 29.074395 | BG33: =[16]byGOVDetalhado!C33 -> 0.50310834 | BH33: =[16]byGOVDetalhado!D33 -> 1.5304075 | BI33: =[16]byGOVDetalhado!E33 -> 143.38709 | BJ33: =[17]byGOVDetalhado!B33 -> 33.196819 | BK33: =[17]byGOVDetalhado!C33 -> 0.55366908 | BL33: =[17]byGOVDetalhado!D33 -> 1.685947 | BM33: =[17]byGOVDetalhado!E33 -> 162.37082 | BN33: =[18]byGOVDetalhado!B33 -> 36.470125 | BO33: =[18]byGOVDetalhado!C33 -> 0.5819201 | BP33: =[18]byGOVDetalhado!D33 -> 1.748197 | BQ33: =[18]byGOVDetalhado!E33 -> 176.96949 | BR33: =[19]byGOVDetalhado!B33 -> 39.39875 | BS33: =[19]byGOVDetalhado!C33 -> 0.60115496 | BT33: =[19]byGOVDetalhado!D33 -> 1.7880852 | BU33: =[19]byGOVDetalhado!E33 -> 189.72635 | BV33: =[20]byGOVDetalhado!B33 -> 43.068644 | BW33: =[20]byGOVDetalhado!C33 -> 0.62516394 | BX33: =[20]byGOVDetalhado!D33 -> 1.8150983 | BY33: =[20]byGOVDetalhado!E33 -> 206.56929 | BZ33: =[21]byGOVDetalhado!B33 -> 45.282099 | CA33: =[21]byGOVDetalhado!C33 -> 0.61282036 | CB33: =[21]byGOVDetalhado!D33 -> 1.8135151 | CC33: =[21]byGOVDetalhado!E33 -> 215.47808 | CD33: =[22]byGOVDetalhado!B33 -> 49.013715 | CE33: =[22]byGOVDetalhado!C33 -> 0.64410396 | CF33: =[22]byGOVDetalhado!D33 -> 1.999289 | CG33: =[22]byGOVDetalhado!E33 -> 231.46351 | CH33: =[23]byGOVDetalhado!B33 -> 51.034365 | CI33: =[23]byGOVDetalhado!C33 -> 0.57350187 | CJ33: =[23]byGOVDetalhado!D33 -> 1.6672636 | CK33: =[23]byGOVDetalhado!E33 -> 239.24119 | CL33: =[24]byGOVDetalhado!B33 -> 63.027856 | CM33: =[24]byGOVDetalhado!C33 -> 0.62529645 | CN33: =[24]byGOVDetalhado!D33 -> 1.7913292 | CO33: =[24]byGOVDetalhado!E33 -> 310.35859 | CP33: =[25]byGOVDetalhado!B33 -> 73.355354 | CQ33: =[25]byGOVDetalhado!C33 -> 0.67031936 | CR33: =[25]byGOVDetalhado!D33 -> 1.9385728 | CS33: =[25]byGOVDetalhado!E33 -> 352.95462 | CT33: =[26]byGOVDetalhado!B33 -> 81.090062 | CU33: =[26]byGOVDetalhado!C33 -> 0.69043909 | CV33: =[26]byGOVDetalhado!D33 -> 1.9205542 | CW33: =[26]byGOVDetalhado!E33 -> 381.44995
A34: TAXAS | B34: =[2]byGOVDetalhado!B34 -> 2.876632 | C34: =[2]byGOVDetalhado!C34 -> 0.23924539 | D34: =[2]byGOVDetalhado!D34 -> 0.78287386 | E34: =[2]byGOVDetalhado!E34 -> 16.584949 | F34: =[3]byGOVDetalhado!B34 -> 2.6327502 | G34: =[3]byGOVDetalhado!C34 -> 0.20009426 | H34: =[3]byGOVDetalhado!D34 -> 0.6243973 | I34: =[3]byGOVDetalhado!E34 -> 15.178872 | J34: =[4]byGOVDetalhado!B34 -> 3.0509827 | K34: =[4]byGOVDetalhado!C34 -> 0.20493077 | L34: =[4]byGOVDetalhado!D34 -> 0.61583164 | M34: =[4]byGOVDetalhado!E34 -> 17.113804 | N34: =[5]byGOVDetalhado!B34 -> 3.5475135 | O34: =[5]byGOVDetalhado!C34 -> 0.2064969 | P34: =[5]byGOVDetalhado!D34 -> 0.63346774 | Q34: =[5]byGOVDetalhado!E34 -> 19.640854 | R34: =[6]byGOVDetalhado!B34 -> 4.3686962 | S34: =[6]byGOVDetalhado!C34 -> 0.22314871 | T34: =[6]byGOVDetalhado!D34 -> 0.66368045 | U34: =[6]byGOVDetalhado!E34 -> 23.884209 | V34: =[7]byGOVDetalhado!B34 -> 5.334906 | W34: =[7]byGOVDetalhado!C34 -> 0.24578194 | X34: =[7]byGOVDetalhado!D34 -> 0.70737431 | Y34: =[7]byGOVDetalhado!E34 -> 28.813841 | Z34: =[8]byGOVDetalhado!B34 -> 6.1494131 | AA34: =[8]byGOVDetalhado!C34 -> 0.25522061 | AB34: =[8]byGOVDetalhado!D34 -> 0.74130777 | AC34: =[8]byGOVDetalhado!E34 -> 32.825732 | AD34: =[9]byGOVDetalhado!B34 -> 7.0186839 | AE34: =[9]byGOVDetalhado!C34 -> 0.2580149 | AF34: =[9]byGOVDetalhado!D34 -> 0.74601814 | AG34: =[9]byGOVDetalhado!E34 -> 37.045191 | AH34: =[10]byGOVDetalhado!B34 -> 8.1450978 | AI34: =[10]byGOVDetalhado!C34 -> 0.26191684 | AJ34: =[10]byGOVDetalhado!D34 -> 0.75355761 | AK34: =[10]byGOVDetalhado!E34 -> 42.525944 | AL34: =[11]byGOVDetalhado!B34 -> 9.5642828 | AM34: =[11]byGOVDetalhado!C34 -> 0.28695382 | AN34: =[11]byGOVDetalhado!D34 -> 0.86525304 | AO34: =[11]byGOVDetalhado!E34 -> 49.416589 | AP34: =[12]byGOVDetalhado!B34 -> 10.430009 | AQ34: =[12]byGOVDetalhado!C34 -> 0.26841019 | AR34: =[12]byGOVDetalhado!D34 -> 0.80767504 | AS34: =[12]byGOVDetalhado!E34 -> 53.351032 | AT34: =[13]byGOVDetalhado!B34 -> 11.845725 | AU34: =[13]byGOVDetalhado!C34 -> 0.27067392 | AV34: =[13]byGOVDetalhado!D34 -> 0.79416019 | AW34: =[13]byGOVDetalhado!E34 -> 60.009644 | AX34: =[14]byGOVDetalhado!B34 -> 13.60096 | AY34: =[14]byGOVDetalhado!C34 -> 0.28248468 | AZ34: =[14]byGOVDetalhado!D34 -> 0.83028308 | BA34: =[14]byGOVDetalhado!E34 -> 68.263358 | BB34: =[15]byGOVDetalhado!B34 -> 16.623532 | BC34: =[15]byGOVDetalhado!C34 -> 0.31179144 | BD34: =[15]byGOVDetalhado!D34 -> 0.92752508 | BE34: =[15]byGOVDetalhado!E34 -> 82.69068 | BF34: =[16]byGOVDetalhado!B34 -> 17.891343 | BG34: =[16]byGOVDetalhado!C34 -> 0.30959488 | BH34: =[16]byGOVDetalhado!D34 -> 0.94175803 | BI34: =[16]byGOVDetalhado!E34 -> 88.235289 | BJ34: =[17]byGOVDetalhado!B34 -> 18.606898 | BK34: =[17]byGOVDetalhado!C34 -> 0.31033287 | BL34: =[17]byGOVDetalhado!D34 -> 0.9449774 | BM34: =[17]byGOVDetalhado!E34 -> 91.009239 | BN34: =[18]byGOVDetalhado!B34 -> 20.887901 | BO34: =[18]byGOVDetalhado!C34 -> 0.33328895 | BP34: =[18]byGOVDetalhado!D34 -> 1.0012624 | BQ34: =[18]byGOVDetalhado!E34 -> 101.35751 | BR34: =[19]byGOVDetalhado!B34 -> 23.096097 | BS34: =[19]byGOVDetalhado!C34 -> 0.35240542 | BT34: =[19]byGOVDetalhado!D34 -> 1.0482005 | BU34: =[19]byGOVDetalhado!E34 -> 111.22023 | BV34: =[20]byGOVDetalhado!B34 -> 24.812432 | BW34: =[20]byGOVDetalhado!C34 -> 0.36016545 | BX34: =[20]byGOVDetalhado!D34 -> 1.0457028 | BY34: =[20]byGOVDetalhado!E34 -> 119.00738 | BZ34: =[21]byGOVDetalhado!B34 -> 28.594001 | CA34: =[21]byGOVDetalhado!C34 -> 0.3869738 | CB34: =[21]byGOVDetalhado!D34 -> 1.1451689 | CC34: =[21]byGOVDetalhado!E34 -> 136.06658 | CD34: =[22]byGOVDetalhado!B34 -> 27.077935 | CE34: =[22]byGOVDetalhado!C34 -> 0.35583928 | CF34: =[22]byGOVDetalhado!D34 -> 1.1045198 | CG34: =[22]byGOVDetalhado!E34 -> 127.87347 | CH34: =[23]byGOVDetalhado!B34 -> 33.855731 | CI34: =[23]byGOVDetalhado!C34 -> 0.38045589 | CJ34: =[23]byGOVDetalhado!D34 -> 1.1060474 | CK34: =[23]byGOVDetalhado!E34 -> 158.71041 | CL34: =[24]byGOVDetalhado!B34 -> 40.419467 | CM34: =[24]byGOVDetalhado!C34 -> 0.40099966 | CN34: =[24]byGOVDetalhado!D34 -> 1.1487709 | CO34: =[24]byGOVDetalhado!E34 -> 199.0315 | CP34: =[25]byGOVDetalhado!B34 -> 44.646974 | CQ34: =[25]byGOVDetalhado!C34 -> 0.40798291 | CR34: =[25]byGOVDetalhado!D34 -> 1.1798922 | CS34: =[25]byGOVDetalhado!E34 -> 214.82216 | CT34: =[26]byGOVDetalhado!B34 -> 48.769144 | CU34: =[26]byGOVDetalhado!C34 -> 0.41524353 | CV34: =[26]byGOVDetalhado!D34 -> 1.1550587 | CW34: =[26]byGOVDetalhado!E34 -> 229.41144
A35: Previ. Estadual | B35: =[2]byGOVDetalhado!B35 -> 1.278323 | C35: =[2]byGOVDetalhado!C35 -> 0.1063163 | D35: =[2]byGOVDetalhado!D35 -> 0.34789492 | E35: =[2]byGOVDetalhado!E35 -> 7.3700501 | F35: =[3]byGOVDetalhado!B35 -> 6.0712159 | G35: =[3]byGOVDetalhado!C35 -> 0.4614245 | H35: =[3]byGOVDetalhado!D35 -> 1.4398825 | I35: =[3]byGOVDetalhado!E35 -> 35.00302 | J35: =[4]byGOVDetalhado!B35 -> 8.501475 | K35: =[4]byGOVDetalhado!C35 -> 0.57103367 | L35: =[4]byGOVDetalhado!D35 -> 1.715997 | M35: =[4]byGOVDetalhado!E35 -> 47.68712 | N35: =[5]byGOVDetalhado!B35 -> 10.660094 | O35: =[5]byGOVDetalhado!C35 -> 0.62051244 | P35: =[5]byGOVDetalhado!D35 -> 1.9035376 | Q35: =[5]byGOVDetalhado!E35 -> 59.019744 | R35: =[6]byGOVDetalhado!B35 -> 13.294473 | S35: =[6]byGOVDetalhado!C35 -> 0.67906865 | T35: =[6]byGOVDetalhado!D35 -> 2.0196602 | U35: =[6]byGOVDetalhado!E35 -> 72.68255 | V35: =[7]byGOVDetalhado!B35 -> 14.579522 | W35: =[7]byGOVDetalhado!C35 -> 0.67168627 | X35: =[7]byGOVDetalhado!D35 -> 1.933151 | Y35: =[7]byGOVDetalhado!E35 -> 78.744035 | Z35: =[8]byGOVDetalhado!B35 -> 15.420326 | AA35: =[8]byGOVDetalhado!C35 -> 0.63999361 | AB35: =[8]byGOVDetalhado!D35 -> 1.8589103 | AC35: =[8]byGOVDetalhado!E35 -> 82.314115 | AD35: =[9]byGOVDetalhado!B35 -> 16.572447 | AE35: =[9]byGOVDetalhado!C35 -> 0.60922224 | AF35: =[9]byGOVDetalhado!D35 -> 1.7614906 | AG35: =[9]byGOVDetalhado!E35 -> 87.470739 | AH35: =[10]byGOVDetalhado!B35 -> 16.286006 | AI35: =[10]byGOVDetalhado!C35 -> 0.52369897 | AJ35: =[10]byGOVDetalhado!D35 -> 1.5067276 | AK35: =[10]byGOVDetalhado!E35 -> 85.030016 | AL35: =[11]byGOVDetalhado!B35 -> 15.751857 | AM35: =[11]byGOVDetalhado!C35 -> 0.47259743 | AN35: =[11]byGOVDetalhado!D35 -> 1.425025 | AO35: =[11]byGOVDetalhado!E35 -> 81.38645 | AP35: =[12]byGOVDetalhado!B35 -> 17.531526 | AQ35: =[12]byGOVDetalhado!C35 -> 0.45116358 | AR35: =[12]byGOVDetalhado!D35 -> 1.3575996 | AS35: =[12]byGOVDetalhado!E35 -> 89.676338 | AT35: =[13]byGOVDetalhado!B35 -> 19.363598 | AU35: =[13]byGOVDetalhado!C35 -> 0.44245676 | AV35: =[13]byGOVDetalhado!D35 -> 1.2981729 | AW35: =[13]byGOVDetalhado!E35 -> 98.094683 | AX35: =[14]byGOVDetalhado!B35 -> 22.362688 | AY35: =[14]byGOVDetalhado!C35 -> 0.46446111 | AZ35: =[14]byGOVDetalhado!D35 -> 1.3651508 | BA35: =[14]byGOVDetalhado!E35 -> 112.23856 | BB35: =[15]byGOVDetalhado!B35 -> 23.317189 | BC35: =[15]byGOVDetalhado!C35 -> 0.43733788 | BD35: =[15]byGOVDetalhado!D35 -> 1.3010038 | BE35: =[15]byGOVDetalhado!E35 -> 115.98704 | BF35: =[16]byGOVDetalhado!B35 -> 26.566038 | BG35: =[16]byGOVDetalhado!C35 -> 0.45970331 | BH35: =[16]byGOVDetalhado!D35 -> 1.3983735 | BI35: =[16]byGOVDetalhado!E35 -> 131.01655 | BJ35: =[17]byGOVDetalhado!B35 -> 28.451411 | BK35: =[17]byGOVDetalhado!C35 -> 0.47452338 | BL35: =[17]byGOVDetalhado!D35 -> 1.4449448 | BM35: =[17]byGOVDetalhado!E35 -> 139.16029 | BN35: =[18]byGOVDetalhado!B35 -> 31.774143 | BO35: =[18]byGOVDetalhado!C35 -> 0.50699065 | BP35: =[18]byGOVDetalhado!D35 -> 1.5230949 | BQ35: =[18]byGOVDetalhado!E35 -> 154.18247 | BR35: =[19]byGOVDetalhado!B35 -> 32.842181 | BS35: =[19]byGOVDetalhado!C35 -> 0.50111335 | BT35: =[19]byGOVDetalhado!D35 -> 1.4905199 | BU35: =[19]byGOVDetalhado!E35 -> 158.15291 | BV35: =[20]byGOVDetalhado!B35 -> 34.886256 | BW35: =[20]byGOVDetalhado!C35 -> 0.50639228 | BX35: =[20]byGOVDetalhado!D35 -> 1.4702572 | BY35: =[20]byGOVDetalhado!E35 -> 167.32427 | BZ35: =[21]byGOVDetalhado!B35 -> 35.719832 | CA35: =[21]byGOVDetalhado!C35 -> 0.48341046 | CB35: =[21]byGOVDetalhado!D35 -> 1.4305533 | CC35: =[21]byGOVDetalhado!E35 -> 169.97535 | CD35: =[22]byGOVDetalhado!B35 -> 39.087141 | CE35: =[22]byGOVDetalhado!C35 -> 0.51365586 | CF35: =[22]byGOVDetalhado!D35 -> 1.59438 | CG35: =[22]byGOVDetalhado!E35 -> 184.58602 | CH35: =[23]byGOVDetalhado!B35 -> 45.566981 | CI35: =[23]byGOVDetalhado!C35 -> 0.5120618 | CJ35: =[23]byGOVDetalhado!D35 -> 1.4886473 | CK35: =[23]byGOVDetalhado!E35 -> 213.61094 | CL35: =[24]byGOVDetalhado!B35 -> 51.23082 | CM35: =[24]byGOVDetalhado!C35 -> 0.5082586 | CN35: =[24]byGOVDetalhado!D35 -> 1.4560429 | CO35: =[24]byGOVDetalhado!E35 -> 252.26822 | CP35: =[25]byGOVDetalhado!B35 -> 51.947869 | CQ35: =[25]byGOVDetalhado!C35 -> 0.47469831 | CR35: =[25]byGOVDetalhado!D35 -> 1.372834 | CS35: =[25]byGOVDetalhado!E35 -> 249.95095 | CT35: =[26]byGOVDetalhado!B35 -> 55.32654 | CU35: =[26]byGOVDetalhado!C35 -> 0.4710763 | CV35: =[26]byGOVDetalhado!D35 -> 1.3103655 | CW35: =[26]byGOVDetalhado!E35 -> 260.25762
A36: Contribuições de Melhoria e Econômicas | B36: =[2]byGOVDetalhado!B36 -> 3.144652 | C36: =[2]byGOVDetalhado!C36 -> 0.26153623 | D36: =[2]byGOVDetalhado!D36 -> 0.85581536 | E36: =[2]byGOVDetalhado!E36 -> 18.130193 | F36: =[3]byGOVDetalhado!B36 -> 3.6572112 | G36: =[3]byGOVDetalhado!C36 -> 0.27795534 | H36: =[3]byGOVDetalhado!D36 -> 0.86736403 | I36: =[3]byGOVDetalhado!E36 -> 21.085305 | J36: =[4]byGOVDetalhado!B36 -> 0.62893244 | K36: =[4]byGOVDetalhado!C36 -> 0.042244622 | L36: =[4]byGOVDetalhado!D36 -> 0.12694811 | M36: =[4]byGOVDetalhado!E36 -> 3.5278556 | N36: =[5]byGOVDetalhado!B36 -> 0.71515255 | O36: =[5]byGOVDetalhado!C36 -> 0.041628252 | P36: =[5]byGOVDetalhado!D36 -> 0.12770242 | Q36: =[5]byGOVDetalhado!E36 -> 3.9594512 | R36: =[6]byGOVDetalhado!B36 -> 0.75314871 | S36: =[6]byGOVDetalhado!C36 -> 0.038470097 | T36: =[6]byGOVDetalhado!D36 -> 0.1144163 | U36: =[6]byGOVDetalhado!E36 -> 4.1175583 | V36: =[7]byGOVDetalhado!B36 -> 0.68541389 | W36: =[7]byGOVDetalhado!C36 -> 0.031577381 | X36: =[7]byGOVDetalhado!D36 -> 0.090881485 | Y36: =[7]byGOVDetalhado!E36 -> 3.7019222 | Z36: =[8]byGOVDetalhado!B36 -> 0.41328211 | AA36: =[8]byGOVDetalhado!C36 -> 0.01715255 | AB36: =[8]byGOVDetalhado!D36 -> 0.049820891 | AC36: =[8]byGOVDetalhado!E36 -> 2.206111 | AD36: =[9]byGOVDetalhado!B36 -> 0.4435337 | AE36: =[9]byGOVDetalhado!C36 -> 0.01630481 | AF36: =[9]byGOVDetalhado!D36 -> 0.047143338 | AG36: =[9]byGOVDetalhado!E36 -> 2.3410074 | AH36: =[10]byGOVDetalhado!B36 -> 0.51816196 | AI36: =[10]byGOVDetalhado!C36 -> 0.016662212 | AJ36: =[10]byGOVDetalhado!D36 -> 0.047938637 | AK36: =[10]byGOVDetalhado!E36 -> 2.7053483 | AL36: =[11]byGOVDetalhado!B36 -> 0.66908343 | AM36: =[11]byGOVDetalhado!C36 -> 0.020074275 | AN36: =[11]byGOVDetalhado!D36 -> 0.060530045 | AO36: =[11]byGOVDetalhado!E36 -> 3.45701 | AP36: =[12]byGOVDetalhado!B36 -> 0.68646706 | AQ36: =[12]byGOVDetalhado!C36 -> 0.017665828 | AR36: =[12]byGOVDetalhado!D36 -> 0.053158372 | AS36: =[12]byGOVDetalhado!E36 -> 3.51138 | AT36: =[13]byGOVDetalhado!B36 -> 0.68648114 | AU36: =[13]byGOVDetalhado!C36 -> 0.015686042 | AV36: =[13]byGOVDetalhado!D36 -> 0.046023017 | AW36: =[13]byGOVDetalhado!E36 -> 3.4776672 | AX36: =[14]byGOVDetalhado!B36 -> 0.98555357 | AY36: =[14]byGOVDetalhado!C36 -> 0.020469423 | AZ36: =[14]byGOVDetalhado!D36 -> 0.060164023 | BA36: =[14]byGOVDetalhado!E36 -> 4.9465037 | BB36: =[15]byGOVDetalhado!B36 -> 0.92818633 | BC36: =[15]byGOVDetalhado!C36 -> 0.01740909 | BD36: =[15]byGOVDetalhado!D36 -> 0.051789001 | BE36: =[15]byGOVDetalhado!E36 -> 4.617091 | BF36: =[16]byGOVDetalhado!B36 -> 1.0049558 | BG36: =[16]byGOVDetalhado!C36 -> 0.017389929 | BH36: =[16]byGOVDetalhado!D36 -> 0.052898502 | BI36: =[16]byGOVDetalhado!E36 -> 4.9561719 | BJ36: =[17]byGOVDetalhado!B36 -> 1.0705587 | BK36: =[17]byGOVDetalhado!C36 -> 0.017855182 | BL36: =[17]byGOVDetalhado!D36 -> 0.054369824 | BM36: =[17]byGOVDetalhado!E36 -> 5.2362695 | BN36: =[18]byGOVDetalhado!B36 -> 1.0451031 | BO36: =[18]byGOVDetalhado!C36 -> 0.016675745 | BP36: =[18]byGOVDetalhado!D36 -> 0.050097062 | BQ36: =[18]byGOVDetalhado!E36 -> 5.0713113 | BR36: =[19]byGOVDetalhado!B36 -> 1.7578072 | BS36: =[19]byGOVDetalhado!C36 -> 0.026821016 | BT36: =[19]byGOVDetalhado!D36 -> 0.079776874 | BU36: =[19]byGOVDetalhado!E36 -> 8.464795 | BV36: =[20]byGOVDetalhado!B36 -> 3.3395058 | BW36: =[20]byGOVDetalhado!C36 -> 0.048474676 | BX36: =[20]byGOVDetalhado!D36 -> 0.14074117 | BY36: =[20]byGOVDetalhado!E36 -> 16.017206 | BZ36: =[21]byGOVDetalhado!B36 -> 4.0692327 | CA36: =[21]byGOVDetalhado!C36 -> 0.055070518 | CB36: =[21]byGOVDetalhado!D36 -> 0.16296981 | CC36: =[21]byGOVDetalhado!E36 -> 19.363732 | CD36: =[22]byGOVDetalhado!B36 -> 0 | CE36: =[22]byGOVDetalhado!C36 -> 0 | CF36: =[22]byGOVDetalhado!D36 -> 0 | CG36: =[22]byGOVDetalhado!E36 -> 0 | CH36: =[23]byGOVDetalhado!B36 -> 5.8917652 | CI36: =[23]byGOVDetalhado!C36 -> 0.066209079 | CJ36: =[23]byGOVDetalhado!D36 -> 0.19248061 | CK36: =[23]byGOVDetalhado!E36 -> 27.619681 | CL36: =[24]byGOVDetalhado!B36 -> 6.4620511 | CM36: =[24]byGOVDetalhado!C36 -> 0.06410971 | CN36: =[24]byGOVDetalhado!D36 -> 0.18365944 | CO36: =[24]byGOVDetalhado!E36 -> 31.820105 | CP36: =[25]byGOVDetalhado!B36 -> 6.8995218 | CQ36: =[25]byGOVDetalhado!C36 -> 0.063047655 | CR36: =[25]byGOVDetalhado!D36 -> 0.18233469 | CS36: =[25]byGOVDetalhado!E36 -> 33.197551 | CT36: =[26]byGOVDetalhado!B36 -> 7.7713305 | CU36: =[26]byGOVDetalhado!C36 -> 0.066168779 | CV36: =[26]byGOVDetalhado!D36 -> 0.18405784 | CW36: =[26]byGOVDetalhado!E36 -> 36.55656
A37: Demais (multas, juros e dívida ativa) | B37: =[2]byGOVDetalhado!B37 -> 2.2214229 | C37: =[2]byGOVDetalhado!C37 -> 0.18475258 | D37: =[2]byGOVDetalhado!D37 -> 0.60455907 | E37: =[2]byGOVDetalhado!E37 -> 12.807403 | F37: =[3]byGOVDetalhado!B37 -> 0.76980937 | G37: =[3]byGOVDetalhado!C37 -> 0.058507045 | H37: =[3]byGOVDetalhado!D37 -> 0.18257216 | I37: =[3]byGOVDetalhado!E37 -> 4.438263 | J37: =[4]byGOVDetalhado!B37 -> 2.9684746 | K37: =[4]byGOVDetalhado!C37 -> 0.1993888 | L37: =[4]byGOVDetalhado!D37 -> 0.59917762 | M37: =[4]byGOVDetalhado!E37 -> 16.650993 | N37: =[5]byGOVDetalhado!B37 -> 3.3196599 | O37: =[5]byGOVDetalhado!C37 -> 0.19323379 | P37: =[5]byGOVDetalhado!D37 -> 0.59278068 | Q37: =[5]byGOVDetalhado!E37 -> 18.37934 | R37: =[6]byGOVDetalhado!B37 -> 3.6220456 | S37: =[6]byGOVDetalhado!C37 -> 0.18501054 | T37: =[6]byGOVDetalhado!D37 -> 0.55025133 | U37: =[6]byGOVDetalhado!E37 -> 19.802177 | V37: =[7]byGOVDetalhado!B37 -> 4.3604982 | W37: =[7]byGOVDetalhado!C37 -> 0.20089046 | X37: =[7]byGOVDetalhado!D37 -> 0.5781741 | Y37: =[7]byGOVDetalhado!E37 -> 23.551063 | Z37: =[8]byGOVDetalhado!B37 -> 6.0895492 | AA37: =[8]byGOVDetalhado!C37 -> 0.25273607 | AB37: =[8]byGOVDetalhado!D37 -> 0.73409122 | AC37: =[8]byGOVDetalhado!E37 -> 32.506178 | AD37: =[9]byGOVDetalhado!B37 -> 4.5147407 | AE37: =[9]byGOVDetalhado!C37 -> 0.16596707 | AF37: =[9]byGOVDetalhado!D37 -> 0.47987322 | AG37: =[9]byGOVDetalhado!E37 -> 23.829173 | AH37: =[10]byGOVDetalhado!B37 -> 5.6778153 | AI37: =[10]byGOVDetalhado!C37 -> 0.18257798 | AJ37: =[10]byGOVDetalhado!D37 -> 0.52529276 | AK37: =[10]byGOVDetalhado!E37 -> 29.644145 | AL37: =[11]byGOVDetalhado!B37 -> 6.1047671 | AM37: =[11]byGOVDetalhado!C37 -> 0.18315919 | AN37: =[11]byGOVDetalhado!D37 -> 0.55228065 | AO37: =[11]byGOVDetalhado!E37 -> 31.542017 | AP37: =[12]byGOVDetalhado!B37 -> 8.57503 | AQ37: =[12]byGOVDetalhado!C37 -> 0.22067338 | AR37: =[12]byGOVDetalhado!D37 -> 0.66402987 | AS37: =[12]byGOVDetalhado!E37 -> 43.862541 | AT37: =[13]byGOVDetalhado!B37 -> 8.8579055 | AU37: =[13]byGOVDetalhado!C37 -> 0.20240247 | AV37: =[13]byGOVDetalhado!D37 -> 0.59385104 | AW37: =[13]byGOVDetalhado!E37 -> 44.873553 | AX37: =[14]byGOVDetalhado!B37 -> 10.673318 | AY37: =[14]byGOVDetalhado!C37 -> 0.22167913 | AZ37: =[14]byGOVDetalhado!D37 -> 0.65156251 | BA37: =[14]byGOVDetalhado!E37 -> 53.569495 | BB37: =[15]byGOVDetalhado!B37 -> 13.454941 | BC37: =[15]byGOVDetalhado!C37 -> 0.25236126 | BD37: =[15]byGOVDetalhado!D37 -> 0.75073067 | BE37: =[15]byGOVDetalhado!E37 -> 66.929112 | BF37: =[16]byGOVDetalhado!B37 -> 12.160555 | BG37: =[16]byGOVDetalhado!C37 -> 0.21042835 | BH37: =[16]byGOVDetalhado!D37 -> 0.64010291 | BI37: =[16]byGOVDetalhado!E37 -> 59.972587 | BJ37: =[17]byGOVDetalhado!B37 -> 13.227217 | BK37: =[17]byGOVDetalhado!C37 -> 0.22060852 | BL37: =[17]byGOVDetalhado!D37 -> 0.67176275 | BM37: =[17]byGOVDetalhado!E37 -> 64.696379 | BN37: =[18]byGOVDetalhado!B37 -> 13.697792 | BO37: =[18]byGOVDetalhado!C37 -> 0.21856302 | BP37: =[18]byGOVDetalhado!D37 -> 0.65660426 | BQ37: =[18]byGOVDetalhado!E37 -> 66.467863 | BR37: =[19]byGOVDetalhado!B37 -> 11.456293 | BS37: =[19]byGOVDetalhado!C37 -> 0.17480268 | BT37: =[19]byGOVDetalhado!D37 -> 0.519936 | BU37: =[19]byGOVDetalhado!E37 -> 55.168264 | BV37: =[20]byGOVDetalhado!B37 -> 0 | BW37: =[20]byGOVDetalhado!C37 -> 0 | BX37: =[20]byGOVDetalhado!D37 -> 0 | BY37: =[20]byGOVDetalhado!E37 -> 0 | BZ37: =[21]byGOVDetalhado!B37 -> 0 | CA37: =[21]byGOVDetalhado!C37 -> 0 | CB37: =[21]byGOVDetalhado!D37 -> 0 | CC37: =[21]byGOVDetalhado!E37 -> 0 | CD37: =[22]byGOVDetalhado!B37 -> 0 | CE37: =[22]byGOVDetalhado!C37 -> 0 | CF37: =[22]byGOVDetalhado!D37 -> 0 | CG37: =[22]byGOVDetalhado!E37 -> 0 | CH37: =[23]byGOVDetalhado!B37 -> 0 | CI37: =[23]byGOVDetalhado!C37 -> 0 | CJ37: =[23]byGOVDetalhado!D37 -> 0 | CK37: =[23]byGOVDetalhado!E37 -> 0 | CL37: =[24]byGOVDetalhado!B37 -> 0 | CM37: =[24]byGOVDetalhado!C37 -> 0 | CN37: =[24]byGOVDetalhado!D37 -> 0 | CO37: =[24]byGOVDetalhado!E37 -> 0 | CP37: =[25]byGOVDetalhado!B37 -> 0 | CQ37: =[25]byGOVDetalhado!C37 -> 0 | CR37: =[25]byGOVDetalhado!D37 -> 0 | CS37: =[25]byGOVDetalhado!E37 -> 0 | CT37: =[26]byGOVDetalhado!B37 -> 0 | CU37: =[26]byGOVDetalhado!C37 -> 0 | CV37: =[26]byGOVDetalhado!D37 -> 0 | CW37: =[26]byGOVDetalhado!E37 -> 0
B38: =[2]byGOVDetalhado!B38 -> 0 | C38: =[2]byGOVDetalhado!C38 -> 0 | D38: =[2]byGOVDetalhado!D38 -> 0 | E38: =[2]byGOVDetalhado!E38 -> 0 | F38: =[3]byGOVDetalhado!B38 -> 0 | G38: =[3]byGOVDetalhado!C38 -> 0 | H38: =[3]byGOVDetalhado!D38 -> 0 | I38: =[3]byGOVDetalhado!E38 -> 0 | J38: =[4]byGOVDetalhado!B38 -> 0 | K38: =[4]byGOVDetalhado!C38 -> 0 | L38: =[4]byGOVDetalhado!D38 -> 0 | M38: =[4]byGOVDetalhado!E38 -> 0 | N38: =[5]byGOVDetalhado!B38 -> 0 | O38: =[5]byGOVDetalhado!C38 -> 0 | P38: =[5]byGOVDetalhado!D38 -> 0 | Q38: =[5]byGOVDetalhado!E38 -> 0 | R38: =[6]byGOVDetalhado!B38 -> 0 | S38: =[6]byGOVDetalhado!C38 -> 0 | T38: =[6]byGOVDetalhado!D38 -> 0 | U38: =[6]byGOVDetalhado!E38 -> 0 | V38: =[7]byGOVDetalhado!B38 -> 0 | W38: =[7]byGOVDetalhado!C38 -> 0 | X38: =[7]byGOVDetalhado!D38 -> 0 | Y38: =[7]byGOVDetalhado!E38 -> 0 | Z38: =[8]byGOVDetalhado!B38 -> 0 | AA38: =[8]byGOVDetalhado!C38 -> 0 | AB38: =[8]byGOVDetalhado!D38 -> 0 | AC38: =[8]byGOVDetalhado!E38 -> 0 | AD38: =[9]byGOVDetalhado!B38 -> 0 | AE38: =[9]byGOVDetalhado!C38 -> 0 | AF38: =[9]byGOVDetalhado!D38 -> 0 | AG38: =[9]byGOVDetalhado!E38 -> 0 | AH38: =[10]byGOVDetalhado!B38 -> 0 | AI38: =[10]byGOVDetalhado!C38 -> 0 | AJ38: =[10]byGOVDetalhado!D38 -> 0 | AK38: =[10]byGOVDetalhado!E38 -> 0 | AL38: =[11]byGOVDetalhado!B38 -> 0 | AM38: =[11]byGOVDetalhado!C38 -> 0 | AN38: =[11]byGOVDetalhado!D38 -> 0 | AO38: =[11]byGOVDetalhado!E38 -> 0 | AP38: =[12]byGOVDetalhado!B38 -> 0 | AQ38: =[12]byGOVDetalhado!C38 -> 0 | AR38: =[12]byGOVDetalhado!D38 -> 0 | AS38: =[12]byGOVDetalhado!E38 -> 0 | AT38: =[13]byGOVDetalhado!B38 -> 0 | AU38: =[13]byGOVDetalhado!C38 -> 0 | AV38: =[13]byGOVDetalhado!D38 -> 0 | AW38: =[13]byGOVDetalhado!E38 -> 0 | AX38: =[14]byGOVDetalhado!B38 -> 0 | AY38: =[14]byGOVDetalhado!C38 -> 0 | AZ38: =[14]byGOVDetalhado!D38 -> 0 | BA38: =[14]byGOVDetalhado!E38 -> 0 | BB38: =[15]byGOVDetalhado!B38 -> 0 | BC38: =[15]byGOVDetalhado!C38 -> 0 | BD38: =[15]byGOVDetalhado!D38 -> 0 | BE38: =[15]byGOVDetalhado!E38 -> 0 | BF38: =[16]byGOVDetalhado!B38 -> 0 | BG38: =[16]byGOVDetalhado!C38 -> 0 | BH38: =[16]byGOVDetalhado!D38 -> 0 | BI38: =[16]byGOVDetalhado!E38 -> 0 | BJ38: =[17]byGOVDetalhado!B38 -> 0 | BK38: =[17]byGOVDetalhado!C38 -> 0 | BL38: =[17]byGOVDetalhado!D38 -> 0 | BM38: =[17]byGOVDetalhado!E38 -> 0 | BN38: =[18]byGOVDetalhado!B38 -> 0 | BO38: =[18]byGOVDetalhado!C38 -> 0 | BP38: =[18]byGOVDetalhado!D38 -> 0 | BQ38: =[18]byGOVDetalhado!E38 -> 0 | BR38: =[19]byGOVDetalhado!B38 -> 0 | BS38: =[19]byGOVDetalhado!C38 -> 0 | BT38: =[19]byGOVDetalhado!D38 -> 0 | BU38: =[19]byGOVDetalhado!E38 -> 0 | BV38: =[20]byGOVDetalhado!B38 -> 0 | BW38: =[20]byGOVDetalhado!C38 -> 0 | BX38: =[20]byGOVDetalhado!D38 -> 0 | BY38: =[20]byGOVDetalhado!E38 -> 0 | BZ38: =[21]byGOVDetalhado!B38 -> 0 | CA38: =[21]byGOVDetalhado!C38 -> 0 | CB38: =[21]byGOVDetalhado!D38 -> 0 | CC38: =[21]byGOVDetalhado!E38 -> 0 | CD38: =[22]byGOVDetalhado!B38 -> 0 | CE38: =[22]byGOVDetalhado!C38 -> 0 | CF38: =[22]byGOVDetalhado!D38 -> 0 | CG38: =[22]byGOVDetalhado!E38 -> 0 | CH38: =[23]byGOVDetalhado!B38 -> 0 | CI38: =[23]byGOVDetalhado!C38 -> 0 | CJ38: =[23]byGOVDetalhado!D38 -> 0 | CK38: =[23]byGOVDetalhado!E38 -> 0 | CL38: =[24]byGOVDetalhado!B38 -> 0 | CM38: =[24]byGOVDetalhado!C38 -> 0 | CN38: =[24]byGOVDetalhado!D38 -> 0 | CO38: =[24]byGOVDetalhado!E38 -> 0 | CP38: =[25]byGOVDetalhado!B38 -> 0 | CQ38: =[25]byGOVDetalhado!C38 -> 0 | CR38: =[25]byGOVDetalhado!D38 -> 0 | CS38: =[25]byGOVDetalhado!E38 -> 0 | CT38: =[26]byGOVDetalhado!B38 -> 0 | CU38: =[26]byGOVDetalhado!C38 -> 0 | CV38: =[26]byGOVDetalhado!D38 -> 0 | CW38: =[26]byGOVDetalhado!E38 -> 0
A39: MUNICÍPIOS (6) | B39: =[2]byGOVDetalhado!B39 -> 20.860392 | C39: =[2]byGOVDetalhado!C39 -> 1.7349291 | D39: =[2]byGOVDetalhado!D39 -> 5.6771446 | E39: =[2]byGOVDetalhado!E39 -> 120.26861 | F39: =[3]byGOVDetalhado!B39 -> 23.063749 | G39: =[3]byGOVDetalhado!C39 -> 1.7528908 | H39: =[3]byGOVDetalhado!D39 -> 5.4699236 | I39: =[3]byGOVDetalhado!E39 -> 132.97186 | J39: =[4]byGOVDetalhado!B39 -> 27.088906 | K39: =[4]byGOVDetalhado!C39 -> 1.8195286 | L39: =[4]byGOVDetalhado!D39 -> 5.4678138 | M39: =[4]byGOVDetalhado!E39 -> 151.94915 | N39: =[5]byGOVDetalhado!B39 -> 32.428329 | O39: =[5]byGOVDetalhado!C39 -> 1.8876178 | P39: =[5]byGOVDetalhado!D39 -> 5.7906193 | Q39: =[5]byGOVDetalhado!E39 -> 179.53986 | R39: =[6]byGOVDetalhado!B39 -> 38.53364 | S39: =[6]byGOVDetalhado!C39 -> 1.9682605 | T39: =[6]byGOVDetalhado!D39 -> 5.8539259 | U39: =[6]byGOVDetalhado!E39 -> 210.66824 | V39: =[7]byGOVDetalhado!B39 -> 41.602176 | W39: =[7]byGOVDetalhado!C39 -> 1.9166343 | X39: =[7]byGOVDetalhado!D39 -> 5.5161817 | Y39: =[7]byGOVDetalhado!E39 -> 224.69346 | Z39: =[8]byGOVDetalhado!B39 -> 47.884981 | AA39: =[8]byGOVDetalhado!C39 -> 1.9873822 | AB39: =[8]byGOVDetalhado!D39 -> 5.7725035 | AC39: =[8]byGOVDetalhado!E39 -> 255.61132 | AD39: =[9]byGOVDetalhado!B39 -> 55.345339 | AE39: =[9]byGOVDetalhado!C39 -> 2.0345584 | AF39: =[9]byGOVDetalhado!D39 -> 5.8826736 | AG39: =[9]byGOVDetalhado!E39 -> 292.11725 | AH39: =[10]byGOVDetalhado!B39 -> 63.168046 | AI39: =[10]byGOVDetalhado!C39 -> 2.0312556 | AJ39: =[10]byGOVDetalhado!D39 -> 5.8440995 | AK39: =[10]byGOVDetalhado!E39 -> 329.80338 | AL39: =[11]byGOVDetalhado!B39 -> 68.1575 | AM39: =[11]byGOVDetalhado!C39 -> 2.0449056 | AN39: =[11]byGOVDetalhado!D39 -> 6.1660121 | AO39: =[11]byGOVDetalhado!E39 -> 352.15512 | AP39: =[12]byGOVDetalhado!B39 -> 80.331811 | AQ39: =[12]byGOVDetalhado!C39 -> 2.0672922 | AR39: =[12]byGOVDetalhado!D39 -> 6.2207039 | AS39: =[12]byGOVDetalhado!E39 -> 410.90904 | AT39: =[13]byGOVDetalhado!B39 -> 93.388072 | AU39: =[13]byGOVDetalhado!C39 -> 2.1339104 | AV39: =[13]byGOVDetalhado!D39 -> 6.2609162 | AW39: =[13]byGOVDetalhado!E39 -> 473.09768 | AX39: =[14]byGOVDetalhado!B39 -> 105.20005 | AY39: =[14]byGOVDetalhado!C39 -> 2.184949 | AZ39: =[14]byGOVDetalhado!D39 -> 6.4220336 | BA39: =[14]byGOVDetalhado!E39 -> 528.00014 | BB39: =[15]byGOVDetalhado!B39 -> 116.72588 | BC39: =[15]byGOVDetalhado!C39 -> 2.1893139 | BD39: =[15]byGOVDetalhado!D39 -> 6.5128266 | BE39: =[15]byGOVDetalhado!E39 -> 580.63126 | BF39: =[16]byGOVDetalhado!B39 -> 129.70966 | BG39: =[16]byGOVDetalhado!C39 -> 2.2445184 | BH39: =[16]byGOVDetalhado!D39 -> 6.8276104 | BI39: =[16]byGOVDetalhado!E39 -> 639.69317 | BJ39: =[17]byGOVDetalhado!B39 -> 142.04254 | BK39: =[17]byGOVDetalhado!C39 -> 2.3690391 | BL39: =[17]byGOVDetalhado!D39 -> 7.2138294 | BM39: =[17]byGOVDetalhado!E39 -> 694.7522 | BN39: =[18]byGOVDetalhado!B39 -> 150.79234 | BO39: =[18]byGOVDetalhado!C39 -> 2.4060541 | BP39: =[18]byGOVDetalhado!D39 -> 7.2282373 | BQ39: =[18]byGOVDetalhado!E39 -> 731.71242 | BR39: =[19]byGOVDetalhado!B39 -> 163.75807 | BS39: =[19]byGOVDetalhado!C39 -> 2.4986573 | BT39: =[19]byGOVDetalhado!D39 -> 7.4320476 | BU39: =[19]byGOVDetalhado!E39 -> 788.58392 | BV39: =[20]byGOVDetalhado!B39 -> 172.03457 | BW39: =[20]byGOVDetalhado!C39 -> 2.4971719 | BX39: =[20]byGOVDetalhado!D39 -> 7.2502783 | BY39: =[20]byGOVDetalhado!E39 -> 825.12603 | BZ39: =[21]byGOVDetalhado!B39 -> 191.52298 | CA39: =[21]byGOVDetalhado!C39 -> 2.5919554 | CB39: =[21]byGOVDetalhado!D39 -> 7.6703561 | CC39: =[21]byGOVDetalhado!E39 -> 911.3757 | CD39: =[22]byGOVDetalhado!B39 -> 197.6834 | CE39: =[22]byGOVDetalhado!C39 -> 2.5978169 | CF39: =[22]byGOVDetalhado!D39 -> 8.0635844 | CG39: =[22]byGOVDetalhado!E39 -> 933.54466 | CH39: =[23]byGOVDetalhado!B39 -> 240.57754 | CI39: =[23]byGOVDetalhado!C39 -> 2.7035052 | CJ39: =[23]byGOVDetalhado!D39 -> 7.8595311 | CK39: =[23]byGOVDetalhado!E39 -> 1127.7902 | CL39: =[24]byGOVDetalhado!B39 -> 275.58647 | CM39: =[24]byGOVDetalhado!C39 -> 2.7340807 | CN39: =[24]byGOVDetalhado!D39 -> 7.8325064 | CO39: =[24]byGOVDetalhado!E39 -> 1357.029 | CP39: =[25]byGOVDetalhado!B39 -> 318.12355 | CQ39: =[25]byGOVDetalhado!C39 -> 2.907005 | CR39: =[25]byGOVDetalhado!D39 -> 8.4070984 | CS39: =[25]byGOVDetalhado!E39 -> 1530.6746 | CT39: =[26]byGOVDetalhado!B39 -> 359.79669 | CU39: =[26]byGOVDetalhado!C39 -> 3.0634789 | CV39: =[26]byGOVDetalhado!D39 -> 8.521501 | CW39: =[26]byGOVDetalhado!E39 -> 1692.4938
A40: ISS | B40: =[2]byGOVDetalhado!B40 -> 6.7093919 | C40: =[2]byGOVDetalhado!C40 -> 0.55801057 | D40: =[2]byGOVDetalhado!D40 -> 1.8259574 | E40: =[2]byGOVDetalhado!E40 -> 38.682363 | F40: =[3]byGOVDetalhado!B40 -> 7.4459304 | G40: =[3]byGOVDetalhado!C40 -> 0.56590554 | H40: =[3]byGOVDetalhado!D40 -> 1.7659172 | I40: =[3]byGOVDetalhado!E40 -> 42.928806 | J40: =[4]byGOVDetalhado!B40 -> 8.4952964 | K40: =[4]byGOVDetalhado!C40 -> 0.57061866 | L40: =[4]byGOVDetalhado!D40 -> 1.7147499 | M40: =[4]byGOVDetalhado!E40 -> 47.652462 | N40: =[5]byGOVDetalhado!B40 -> 9.6740003 | O40: =[5]byGOVDetalhado!C40 -> 0.56311303 | P40: =[5]byGOVDetalhado!D40 -> 1.7274542 | Q40: =[5]byGOVDetalhado!E40 -> 53.560226 | R40: =[6]byGOVDetalhado!B40 -> 11.681605 | S40: =[6]byGOVDetalhado!C40 -> 0.59668493 | T40: =[6]byGOVDetalhado!D40 -> 1.7746377 | U40: =[6]byGOVDetalhado!E40 -> 63.864799 | V40: =[7]byGOVDetalhado!B40 -> 14.049918 | W40: =[7]byGOVDetalhado!C40 -> 0.64728718 | X40: =[7]byGOVDetalhado!D40 -> 1.8629291 | Y40: =[7]byGOVDetalhado!E40 -> 75.883647 | Z40: =[8]byGOVDetalhado!B40 -> 16.916469 | AA40: =[8]byGOVDetalhado!C40 -> 0.70208839 | AB40: =[8]byGOVDetalhado!D40 -> 2.0392694 | AC40: =[8]byGOVDetalhado!E40 -> 90.300565 | AD40: =[9]byGOVDetalhado!B40 -> 19.740563 | AE40: =[9]byGOVDetalhado!C40 -> 0.72568582 | AF40: =[9]byGOVDetalhado!D40 -> 2.0982307 | AG40: =[9]byGOVDetalhado!E40 -> 104.19231 | AH40: =[10]byGOVDetalhado!B40 -> 23.821352 | AI40: =[10]byGOVDetalhado!C40 -> 0.76600839 | AJ40: =[10]byGOVDetalhado!D40 -> 2.203873 | AK40: =[10]byGOVDetalhado!E40 -> 124.37242 | AL40: =[11]byGOVDetalhado!B40 -> 26.190433 | AM40: =[11]byGOVDetalhado!C40 -> 0.78578238 | AN40: =[11]byGOVDetalhado!D40 -> 2.3693729 | AO40: =[11]byGOVDetalhado!E40 -> 135.32033 | AP40: =[12]byGOVDetalhado!B40 -> 31.40724 | AQ40: =[12]byGOVDetalhado!C40 -> 0.80824697 | AR40: =[12]byGOVDetalhado!D40 -> 2.4321018 | AS40: =[12]byGOVDetalhado!E40 -> 160.65266 | AT40: =[13]byGOVDetalhado!B40 -> 36.656297 | AU40: =[13]byGOVDetalhado!C40 -> 0.83759363 | AV40: =[13]byGOVDetalhado!D40 -> 2.4575087 | AW40: =[13]byGOVDetalhado!E40 -> 185.69833 | AX40: =[14]byGOVDetalhado!B40 -> 42.31651 | AY40: =[14]byGOVDetalhado!C40 -> 0.87889136 | AZ40: =[14]byGOVDetalhado!D40 -> 2.5832502 | BA40: =[14]byGOVDetalhado!E40 -> 212.387 | BB40: =[15]byGOVDetalhado!B40 -> 45.783505 | BC40: =[15]byGOVDetalhado!C40 -> 0.85871674 | BD40: =[15]byGOVDetalhado!D40 -> 2.5545323 | BE40: =[15]byGOVDetalhado!E40 -> 227.74156 | BF40: =[16]byGOVDetalhado!B40 -> 50.493152 | BG40: =[16]byGOVDetalhado!C40 -> 0.87374221 | BH40: =[16]byGOVDetalhado!D40 -> 2.6578403 | BI40: =[16]byGOVDetalhado!E40 -> 249.01864 | BJ40: =[17]byGOVDetalhado!B40 -> 54.074215 | BK40: =[17]byGOVDetalhado!C40 -> 0.90187019 | BL40: =[17]byGOVDetalhado!D40 -> 2.7462348 | BM40: =[17]byGOVDetalhado!E40 -> 264.48542 | BN40: =[18]byGOVDetalhado!B40 -> 53.986154 | BO40: =[18]byGOVDetalhado!C40 -> 0.86140717 | BP40: =[18]byGOVDetalhado!D40 -> 2.5878286 | BQ40: =[18]byGOVDetalhado!E40 -> 261.96515 | BR40: =[19]byGOVDetalhado!B40 -> 56.27956 | BS40: =[19]byGOVDetalhado!C40 -> 0.85872614 | BT40: =[19]byGOVDetalhado!D40 -> 2.5542092 | BU40: =[19]byGOVDetalhado!E40 -> 271.01661 | BV40: =[20]byGOVDetalhado!B40 -> 63.776391 | BW40: =[20]byGOVDetalhado!C40 -> 0.92574773 | BX40: =[20]byGOVDetalhado!D40 -> 2.687812 | BY40: =[20]byGOVDetalhado!E40 -> 305.88946 | BZ40: =[21]byGOVDetalhado!B40 -> 71.314854 | CA40: =[21]byGOVDetalhado!C40 -> 0.96513181 | CB40: =[21]byGOVDetalhado!D40 -> 2.856108 | CC40: =[21]byGOVDetalhado!E40 -> 339.35679 | CD40: =[22]byGOVDetalhado!B40 -> 71.841188 | CE40: =[22]byGOVDetalhado!C40 -> 0.94408663 | CF40: =[22]byGOVDetalhado!D40 -> 2.9304307 | CG40: =[22]byGOVDetalhado!E40 -> 339.2645 | CH40: =[23]byGOVDetalhado!B40 -> 90.520456 | CI40: =[23]byGOVDetalhado!C40 -> 1.0172293 | CJ40: =[23]byGOVDetalhado!D40 -> 2.9572516 | CK40: =[23]byGOVDetalhado!E40 -> 424.34585 | CL40: =[24]byGOVDetalhado!B40 -> 109.34862 | CM40: =[24]byGOVDetalhado!C40 -> 1.0848426 | CN40: =[24]byGOVDetalhado!D40 -> 3.1078222 | CO40: =[24]byGOVDetalhado!E40 -> 538.44895 | CP40: =[25]byGOVDetalhado!B40 -> 123.44516 | CQ40: =[25]byGOVDetalhado!C40 -> 1.1280388 | CR40: =[25]byGOVDetalhado!D40 -> 3.2623036 | CS40: =[25]byGOVDetalhado!E40 -> 593.96538 | CT40: =[26]byGOVDetalhado!B40 -> 142.63379 | CU40: =[26]byGOVDetalhado!C40 -> 1.2144515 | CV40: =[26]byGOVDetalhado!D40 -> 3.378169 | CW40: =[26]byGOVDetalhado!E40 -> 670.95341 | CX40: =CU40-CQ40 -> 0.086412725
A41: IPTU | B41: =[2]byGOVDetalhado!B41 -> 5.5586584 | C41: =[2]byGOVDetalhado!C41 -> 0.4623057 | D41: =[2]byGOVDetalhado!D41 -> 1.5127859 | E41: =[2]byGOVDetalhado!E41 -> 32.047918 | F41: =[3]byGOVDetalhado!B41 -> 5.9793953 | G41: =[3]byGOVDetalhado!C41 -> 0.45444595 | H41: =[3]byGOVDetalhado!D41 -> 1.4181058 | I41: =[3]byGOVDetalhado!E41 -> 34.473637 | J41: =[4]byGOVDetalhado!B41 -> 6.9639612 | K41: =[4]byGOVDetalhado!C41 -> 0.46776075 | L41: =[4]byGOVDetalhado!D41 -> 1.4056545 | M41: =[4]byGOVDetalhado!E41 -> 39.06278 | N41: =[5]byGOVDetalhado!B41 -> 8.0917336 | O41: =[5]byGOVDetalhado!C41 -> 0.471011 | P41: =[5]byGOVDetalhado!D41 -> 1.4449141 | Q41: =[5]byGOVDetalhado!E41 -> 44.799986 | R41: =[6]byGOVDetalhado!B41 -> 9.5086535 | S41: =[6]byGOVDetalhado!C41 -> 0.48569269 | T41: =[6]byGOVDetalhado!D41 -> 1.4445288 | U41: =[6]byGOVDetalhado!E41 -> 51.984999 | V41: =[7]byGOVDetalhado!B41 -> 9.9101775 | W41: =[7]byGOVDetalhado!C41 -> 0.45656712 | X41: =[7]byGOVDetalhado!D41 -> 1.314026 | Y41: =[7]byGOVDetalhado!E41 -> 53.524895 | Z41: =[8]byGOVDetalhado!B41 -> 10.870441 | AA41: =[8]byGOVDetalhado!C41 -> 0.45115859 | AB41: =[8]byGOVDetalhado!D41 -> 1.3104246 | AC41: =[8]byGOVDetalhado!E41 -> 58.026705 | AD41: =[9]byGOVDetalhado!B41 -> 11.879157 | AE41: =[9]byGOVDetalhado!C41 -> 0.43669148 | AF41: =[9]byGOVDetalhado!D41 -> 1.2626393 | AG41: =[9]byGOVDetalhado!E41 -> 62.699166 | AH41: =[10]byGOVDetalhado!B41 -> 12.857911 | AI41: =[10]byGOVDetalhado!C41 -> 0.41346384 | AJ41: =[10]byGOVDetalhado!D41 -> 1.1895716 | AK41: =[10]byGOVDetalhado!E41 -> 67.131767 | AL41: =[11]byGOVDetalhado!B41 -> 14.18485 | AM41: =[11]byGOVDetalhado!C41 -> 0.42558307 | AN41: =[11]byGOVDetalhado!D41 -> 1.2832624 | AO41: =[11]byGOVDetalhado!E41 -> 73.290063 | AP41: =[12]byGOVDetalhado!B41 -> 16.364694 | AQ41: =[12]byGOVDetalhado!C41 -> 0.42113582 | AR41: =[12]byGOVDetalhado!D41 -> 1.2672428 | AS41: =[12]byGOVDetalhado!E41 -> 83.707816 | AT41: =[13]byGOVDetalhado!B41 -> 18.378709 | AU41: =[13]byGOVDetalhado!C41 -> 0.41995212 | AV41: =[13]byGOVDetalhado!D41 -> 1.232144 | AW41: =[13]byGOVDetalhado!E41 -> 93.105303 | AX41: =[14]byGOVDetalhado!B41 -> 20.246648 | AY41: =[14]byGOVDetalhado!C41 -> 0.42051208 | AZ41: =[14]byGOVDetalhado!D41 -> 1.2359752 | BA41: =[14]byGOVDetalhado!E41 -> 101.61814 | BB41: =[15]byGOVDetalhado!B41 -> 22.580858 | BC41: =[15]byGOVDetalhado!C41 -> 0.42352722 | BD41: =[15]byGOVDetalhado!D41 -> 1.2599195 | BE41: =[15]byGOVDetalhado!E41 -> 112.32429 | BF41: =[16]byGOVDetalhado!B41 -> 25.042157 | BG41: =[16]byGOVDetalhado!C41 -> 0.4333338 | BH41: =[16]byGOVDetalhado!D41 -> 1.31816 | BI41: =[16]byGOVDetalhado!E41 -> 123.50118 | BJ41: =[17]byGOVDetalhado!B41 -> 28.085178 | BK41: =[17]byGOVDetalhado!C41 -> 0.46841521 | BL41: =[17]byGOVDetalhado!D41 -> 1.4263451 | BM41: =[17]byGOVDetalhado!E41 -> 137.36898 | BN41: =[18]byGOVDetalhado!B41 -> 31.86679 | BO41: =[18]byGOVDetalhado!C41 -> 0.50846893 | BP41: =[18]byGOVDetalhado!D41 -> 1.5275359 | BQ41: =[18]byGOVDetalhado!E41 -> 154.63203 | BR41: =[19]byGOVDetalhado!B41 -> 35.284887 | BS41: =[19]byGOVDetalhado!C41 -> 0.5383847 | BT41: =[19]byGOVDetalhado!D41 -> 1.6013804 | BU41: =[19]byGOVDetalhado!E41 -> 169.91587 | BV41: =[20]byGOVDetalhado!B41 -> 45.062243 | BW41: =[20]byGOVDetalhado!C41 -> 0.65410206 | BX41: =[20]byGOVDetalhado!D41 -> 1.8991171 | BY41: =[20]byGOVDetalhado!E41 -> 216.13115 | BZ41: =[21]byGOVDetalhado!B41 -> 50.587826 | CA41: =[21]byGOVDetalhado!C41 -> 0.68462483 | CB41: =[21]byGOVDetalhado!D41 -> 2.0260056 | CC41: =[21]byGOVDetalhado!E41 -> 240.72576 | CD41: =[22]byGOVDetalhado!B41 -> 50.81946 | CE41: =[22]byGOVDetalhado!C41 -> 0.66783379 | CF41: =[22]byGOVDetalhado!D41 -> 2.072946 | CG41: =[22]byGOVDetalhado!E41 -> 239.991 | CH41: =[23]byGOVDetalhado!B41 -> 60.043901 | CI41: =[23]byGOVDetalhado!C41 -> 0.67474708 | CJ41: =[23]byGOVDetalhado!D41 -> 1.9616 | CK41: =[23]byGOVDetalhado!E41 -> 281.47649 | CL41: =[24]byGOVDetalhado!B41 -> 65.580775 | CM41: =[24]byGOVDetalhado!C41 -> 0.65062384 | CN41: =[24]byGOVDetalhado!D41 -> 1.8638863 | CO41: =[24]byGOVDetalhado!E41 -> 322.92954 | CP41: =[25]byGOVDetalhado!B41 -> 72.900986 | CQ41: =[25]byGOVDetalhado!C41 -> 0.66616736 | CR41: =[25]byGOVDetalhado!D41 -> 1.9265652 | CS41: =[25]byGOVDetalhado!E41 -> 350.7684 | CT41: =[26]byGOVDetalhado!B41 -> 77.634384 | CU41: =[26]byGOVDetalhado!C41 -> 0.66101581 | CV41: =[26]byGOVDetalhado!D41 -> 1.8387092 | CW41: =[26]byGOVDetalhado!E41 -> 365.19435
A42: ITBI | B42: =[2]byGOVDetalhado!B42 -> 1.1359224 | C42: =[2]byGOVDetalhado!C42 -> 0.094473052 | D42: =[2]byGOVDetalhado!D42 -> 0.30914069 | E42: =[2]byGOVDetalhado!E42 -> 6.5490532 | F42: =[3]byGOVDetalhado!B42 -> 1.2718676 | G42: =[3]byGOVDetalhado!C42 -> 0.096664471 | H42: =[3]byGOVDetalhado!D42 -> 0.30164301 | I42: =[3]byGOVDetalhado!E42 -> 7.3328322 | J42: =[4]byGOVDetalhado!B42 -> 1.5283993 | K42: =[4]byGOVDetalhado!C42 -> 0.10266071 | L42: =[4]byGOVDetalhado!D42 -> 0.30850278 | M42: =[4]byGOVDetalhado!E42 -> 8.5732134 | N42: =[5]byGOVDetalhado!B42 -> 1.6147847 | O42: =[5]byGOVDetalhado!C42 -> 0.093994857 | P42: =[5]byGOVDetalhado!D42 -> 0.28834675 | Q42: =[5]byGOVDetalhado!E42 -> 8.9402759 | R42: =[6]byGOVDetalhado!B42 -> 1.7407976 | S42: =[6]byGOVDetalhado!C42 -> 0.088918232 | T42: =[6]byGOVDetalhado!D42 -> 0.26445724 | U42: =[6]byGOVDetalhado!E42 -> 9.5171583 | V42: =[7]byGOVDetalhado!B42 -> 2.0356648 | W42: =[7]byGOVDetalhado!C42 -> 0.093784156 | X42: =[7]byGOVDetalhado!D42 -> 0.2699161 | Y42: =[7]byGOVDetalhado!E42 -> 10.994631 | Z42: =[8]byGOVDetalhado!B42 -> 2.4614849 | AA42: =[8]byGOVDetalhado!C42 -> 0.10215962 | AB42: =[8]byGOVDetalhado!D42 -> 0.29673041 | AC42: =[8]byGOVDetalhado!E42 -> 13.139473 | AD42: =[9]byGOVDetalhado!B42 -> 3.1984923 | AE42: =[9]byGOVDetalhado!C42 -> 0.11758026 | AF42: =[9]byGOVDetalhado!D42 -> 0.33996876 | AG42: =[9]byGOVDetalhado!E42 -> 16.881905 | AH42: =[10]byGOVDetalhado!B42 -> 4.0237766 | AI42: =[10]byGOVDetalhado!C42 -> 0.12939008 | AJ42: =[10]byGOVDetalhado!D42 -> 0.37226655 | AK42: =[10]byGOVDetalhado!E42 -> 21.008329 | AL42: =[11]byGOVDetalhado!B42 -> 4.1835575 | AM42: =[11]byGOVDetalhado!C42 -> 0.12551781 | AN42: =[11]byGOVDetalhado!D42 -> 0.37847437 | AO42: =[11]byGOVDetalhado!E42 -> 21.615541 | AP42: =[12]byGOVDetalhado!B42 -> 5.572766 | AQ42: =[12]byGOVDetalhado!C42 -> 0.14341187 | AR42: =[12]byGOVDetalhado!D42 -> 0.43154171 | AS42: =[12]byGOVDetalhado!E42 -> 28.505518 | AT42: =[13]byGOVDetalhado!B42 -> 6.8709687 | AU42: =[13]byGOVDetalhado!C42 -> 0.15700112 | AV42: =[13]byGOVDetalhado!D42 -> 0.46064297 | AW42: =[13]byGOVDetalhado!E42 -> 34.807865 | AX42: =[14]byGOVDetalhado!B42 -> 7.9039374 | AY42: =[14]byGOVDetalhado!C42 -> 0.16416057 | AZ42: =[14]byGOVDetalhado!D42 -> 0.48250312 | BA42: =[14]byGOVDetalhado!E42 -> 39.669944 | BB42: =[15]byGOVDetalhado!B42 -> 9.3046846 | BC42: =[15]byGOVDetalhado!C42 -> 0.17451893 | BD42: =[15]byGOVDetalhado!D42 -> 0.51916334 | BE42: =[15]byGOVDetalhado!E42 -> 46.28443 | BF42: =[16]byGOVDetalhado!B42 -> 9.9345403 | BG42: =[16]byGOVDetalhado!C42 -> 0.171909 | BH42: =[16]byGOVDetalhado!D42 -> 0.52293074 | BI42: =[16]byGOVDetalhado!E42 -> 48.99448 | BJ42: =[17]byGOVDetalhado!B42 -> 10.160812 | BK42: =[17]byGOVDetalhado!C42 -> 0.16946586 | BL42: =[17]byGOVDetalhado!D42 -> 0.51603109 | BM42: =[17]byGOVDetalhado!E42 -> 49.698116 | BN42: =[18]byGOVDetalhado!B42 -> 9.7763206 | BO42: =[18]byGOVDetalhado!C42 -> 0.15599171 | BP42: =[18]byGOVDetalhado!D42 -> 0.46862834 | BQ42: =[18]byGOVDetalhado!E42 -> 47.439114 | BR42: =[19]byGOVDetalhado!B42 -> 10.293095 | BS42: =[19]byGOVDetalhado!C42 -> 0.15705435 | BT42: =[19]byGOVDetalhado!D42 -> 0.46714506 | BU42: =[19]byGOVDetalhado!E42 -> 49.566836 | BV42: =[20]byGOVDetalhado!B42 -> 11.493558 | BW42: =[20]byGOVDetalhado!C42 -> 0.16683502 | BX42: =[20]byGOVDetalhado!D42 -> 0.48438808 | BY42: =[20]byGOVDetalhado!E42 -> 55.126327 | BZ42: =[21]byGOVDetalhado!B42 -> 12.808551 | CA42: =[21]byGOVDetalhado!C42 -> 0.17334313 | CB42: =[21]byGOVDetalhado!D42 -> 0.51297315 | CC42: =[21]byGOVDetalhado!E42 -> 60.950399 | CD42: =[22]byGOVDetalhado!B42 -> 14.581663 | CE42: =[22]byGOVDetalhado!C42 -> 0.19162202 | CF42: =[22]byGOVDetalhado!D42 -> 0.59479185 | CG42: =[22]byGOVDetalhado!E42 -> 68.860785 | CH42: =[23]byGOVDetalhado!B42 -> 21.087291 | CI42: =[23]byGOVDetalhado!C42 -> 0.23696975 | CJ42: =[23]byGOVDetalhado!D42 -> 0.68890975 | CK42: =[23]byGOVDetalhado!E42 -> 98.853947 | CL42: =[24]byGOVDetalhado!B42 -> 20.306394 | CM42: =[24]byGOVDetalhado!C42 -> 0.2014588 | CN42: =[24]byGOVDetalhado!D42 -> 0.57713268 | CO42: =[24]byGOVDetalhado!E42 -> 99.99172 | CP42: =[25]byGOVDetalhado!B42 -> 21.64862 | CQ42: =[25]byGOVDetalhado!C42 -> 0.19782454 | CR42: =[25]byGOVDetalhado!D42 -> 0.57211129 | CS42: =[25]byGOVDetalhado!E42 -> 104.16391 | CT42: =[26]byGOVDetalhado!B42 -> 25.102512 | CU42: =[26]byGOVDetalhado!C42 -> 0.21373464 | CV42: =[26]byGOVDetalhado!D42 -> 0.5945332 | CW42: =[26]byGOVDetalhado!E42 -> 118.08293
A43: IRRF | B43: =[2]byGOVDetalhado!B43 -> 1.3827698 | C43: =[2]byGOVDetalhado!C43 -> 0.11500299 | D43: =[2]byGOVDetalhado!D43 -> 0.37632006 | E43: =[2]byGOVDetalhado!E43 -> 7.9722283 | F43: =[3]byGOVDetalhado!B43 -> 1.6681816 | G43: =[3]byGOVDetalhado!C43 -> 0.12678512 | H43: =[3]byGOVDetalhado!D43 -> 0.39563499 | I43: =[3]byGOVDetalhado!E43 -> 9.6177429 | J43: =[4]byGOVDetalhado!B43 -> 1.7921628 | K43: =[4]byGOVDetalhado!C43 -> 0.12037738 | L43: =[4]byGOVDetalhado!D43 -> 0.36174265 | M43: =[4]byGOVDetalhado!E43 -> 10.052736 | N43: =[5]byGOVDetalhado!B43 -> 2.1897554 | O43: =[5]byGOVDetalhado!C43 -> 0.12746328 | P43: =[5]byGOVDetalhado!D43 -> 0.39101737 | Q43: =[5]byGOVDetalhado!E43 -> 12.123609 | R43: =[6]byGOVDetalhado!B43 -> 2.4195038 | S43: =[6]byGOVDetalhado!C43 -> 0.12358588 | T43: =[6]byGOVDetalhado!D43 -> 0.36756443 | U43: =[6]byGOVDetalhado!E43 -> 13.22773 | V43: =[7]byGOVDetalhado!B43 -> 2.8000979 | W43: =[7]byGOVDetalhado!C43 -> 0.12900199 | X43: =[7]byGOVDetalhado!D43 -> 0.37127502 | Y43: =[7]byGOVDetalhado!E43 -> 15.123336 | Z43: =[8]byGOVDetalhado!B43 -> 3.2860689 | AA43: =[8]byGOVDetalhado!C43 -> 0.13638253 | AB43: =[8]byGOVDetalhado!D43 -> 0.39613349 | AC43: =[8]byGOVDetalhado!E43 -> 17.541124 | AD43: =[9]byGOVDetalhado!B43 -> 4.0324565 | AE43: =[9]byGOVDetalhado!C43 -> 0.14823775 | AF43: =[9]byGOVDetalhado!D43 -> 0.42861108 | AG43: =[9]byGOVDetalhado!E43 -> 21.283637 | AH43: =[10]byGOVDetalhado!B43 -> 4.9486813 | AI43: =[10]byGOVDetalhado!C43 -> 0.15913166 | AJ43: =[10]byGOVDetalhado!D43 -> 0.45783568 | AK43: =[10]byGOVDetalhado!E43 -> 25.837301 | AL43: =[11]byGOVDetalhado!B43 -> 4.8844532 | AM43: =[11]byGOVDetalhado!C43 -> 0.14654654 | AN43: =[11]byGOVDetalhado!D43 -> 0.44188237 | AO43: =[11]byGOVDetalhado!E43 -> 25.236918 | AP43: =[12]byGOVDetalhado!B43 -> 5.5871918 | AQ43: =[12]byGOVDetalhado!C43 -> 0.14378311 | AR43: =[12]byGOVDetalhado!D43 -> 0.43265881 | AS43: =[12]byGOVDetalhado!E43 -> 28.579308 | AT43: =[13]byGOVDetalhado!B43 -> 6.776699 | AU43: =[13]byGOVDetalhado!C43 -> 0.15484706 | AV43: =[13]byGOVDetalhado!D43 -> 0.45432295 | AW43: =[13]byGOVDetalhado!E43 -> 34.330301 | AX43: =[14]byGOVDetalhado!B43 -> 8.1085417 | AY43: =[14]byGOVDetalhado!C43 -> 0.16841009 | AZ43: =[14]byGOVDetalhado!D43 -> 0.49499338 | BA43: =[14]byGOVDetalhado!E43 -> 40.696855 | BB43: =[15]byGOVDetalhado!B43 -> 9.2591592 | BC43: =[15]byGOVDetalhado!C43 -> 0.17366506 | BD43: =[15]byGOVDetalhado!D43 -> 0.51662321 | BE43: =[15]byGOVDetalhado!E43 -> 46.057973 | BF43: =[16]byGOVDetalhado!B43 -> 10.718654 | BG43: =[16]byGOVDetalhado!C43 -> 0.18547743 | BH43: =[16]byGOVDetalhado!D43 -> 0.56420462 | BI43: =[16]byGOVDetalhado!E43 -> 52.861516 | BJ43: =[17]byGOVDetalhado!B43 -> 12.454595 | BK43: =[17]byGOVDetalhado!C43 -> 0.20772244 | BL43: =[17]byGOVDetalhado!D43 -> 0.63252406 | BM43: =[17]byGOVDetalhado!E43 -> 60.917365 | BN43: =[18]byGOVDetalhado!B43 -> 14.665266 | BO43: =[18]byGOVDetalhado!C43 -> 0.23400009 | BP43: =[18]byGOVDetalhado!D43 -> 0.70298013 | BQ43: =[18]byGOVDetalhado!E43 -> 71.162479 | BR43: =[19]byGOVDetalhado!B43 -> 16.224766 | BS43: =[19]byGOVDetalhado!C43 -> 0.24756112 | BT43: =[19]byGOVDetalhado!D43 -> 0.73634989 | BU43: =[19]byGOVDetalhado!E43 -> 78.131049 | BV43: =[20]byGOVDetalhado!B43 -> 18.048039 | BW43: =[20]byGOVDetalhado!C43 -> 0.26197673 | BX43: =[20]byGOVDetalhado!D43 -> 0.76062214 | BY43: =[20]byGOVDetalhado!E43 -> 86.563454 | BZ43: =[21]byGOVDetalhado!B43 -> 19.194821 | CA43: =[21]byGOVDetalhado!C43 -> 0.25977101 | CB43: =[21]byGOVDetalhado!D43 -> 0.76873859 | CC43: =[21]byGOVDetalhado!E43 -> 91.339915 | CD43: =[22]byGOVDetalhado!B43 -> 21.739582 | CE43: =[22]byGOVDetalhado!C43 -> 0.28568637 | CF43: =[22]byGOVDetalhado!D43 -> 0.8867662 | CG43: =[22]byGOVDetalhado!E43 -> 102.66351 | CH43: =[23]byGOVDetalhado!B43 -> 23.810982 | CI43: =[23]byGOVDetalhado!C43 -> 0.26757739 | CJ43: =[23]byGOVDetalhado!D43 -> 0.77789118 | CK43: =[23]byGOVDetalhado!E43 -> 111.62219 | CL43: =[24]byGOVDetalhado!B43 -> 30.249823 | CM43: =[24]byGOVDetalhado!C43 -> 0.30010709 | CN43: =[24]byGOVDetalhado!D43 -> 0.85973715 | CO43: =[24]byGOVDetalhado!E43 -> 148.95465 | CP43: =[25]byGOVDetalhado!B43 -> 40.212346 | CQ43: =[25]byGOVDetalhado!C43 -> 0.3674594 | CR43: =[25]byGOVDetalhado!D43 -> 1.0626976 | CS43: =[25]byGOVDetalhado!E43 -> 193.48463 | CT43: =[26]byGOVDetalhado!B43 -> 48.838753 | CU43: =[26]byGOVDetalhado!C43 -> 0.41583622 | CV43: =[26]byGOVDetalhado!D43 -> 1.1567074 | CW43: =[26]byGOVDetalhado!E43 -> 229.73888 | CX43: =CU43-CQ43 -> 0.048376817
A44: TAXAS | B44: =[2]byGOVDetalhado!B44 -> 2.2263568 | C44: =[2]byGOVDetalhado!C44 -> 0.18516293 | D44: =[2]byGOVDetalhado!D44 -> 0.60590182 | E44: =[2]byGOVDetalhado!E44 -> 12.835849 | F44: =[3]byGOVDetalhado!B44 -> 2.3350684 | G44: =[3]byGOVDetalhado!C44 -> 0.17746985 | H44: =[3]byGOVDetalhado!D44 -> 0.55379747 | I44: =[3]byGOVDetalhado!E44 -> 13.462616 | J44: =[4]byGOVDetalhado!B44 -> 2.4964933 | K44: =[4]byGOVDetalhado!C44 -> 0.1676864 | L44: =[4]byGOVDetalhado!D44 -> 0.50390963 | M44: =[4]byGOVDetalhado!E44 -> 14.00352 | N44: =[5]byGOVDetalhado!B44 -> 2.7502886 | O44: =[5]byGOVDetalhado!C44 -> 0.16009131 | P44: =[5]byGOVDetalhado!D44 -> 0.49110993 | Q44: =[5]byGOVDetalhado!E44 -> 15.227008 | R44: =[6]byGOVDetalhado!B44 -> 2.7295109 | S44: =[6]byGOVDetalhado!C44 -> 0.13942074 | T44: =[6]byGOVDetalhado!D44 -> 0.41465988 | U44: =[6]byGOVDetalhado!E44 -> 14.922578 | V44: =[7]byGOVDetalhado!B44 -> 2.8951366 | W44: =[7]byGOVDetalhado!C44 -> 0.13338048 | X44: =[7]byGOVDetalhado!D44 -> 0.38387655 | Y44: =[7]byGOVDetalhado!E44 -> 15.636641 | Z44: =[8]byGOVDetalhado!B44 -> 3.0078594 | AA44: =[8]byGOVDetalhado!C44 -> 0.12483593 | AB44: =[8]byGOVDetalhado!D44 -> 0.3625955 | AC44: =[8]byGOVDetalhado!E44 -> 16.056034 | AD44: =[9]byGOVDetalhado!B44 -> 3.1969889 | AE44: =[9]byGOVDetalhado!C44 -> 0.11752499 | AF44: =[9]byGOVDetalhado!D44 -> 0.33980896 | AG44: =[9]byGOVDetalhado!E44 -> 16.87397 | AH44: =[10]byGOVDetalhado!B44 -> 3.4916127 | AI44: =[10]byGOVDetalhado!C44 -> 0.11227762 | AJ44: =[10]byGOVDetalhado!D44 -> 0.3230325 | AK44: =[10]byGOVDetalhado!E44 -> 18.229877 | AL44: =[11]byGOVDetalhado!B44 -> 3.8626013 | AM44: =[11]byGOVDetalhado!C44 -> 0.11588827 | AN44: =[11]byGOVDetalhado!D44 -> 0.34943838 | AO44: =[11]byGOVDetalhado!E44 -> 19.957229 | AP44: =[12]byGOVDetalhado!B44 -> 4.3375584 | AQ44: =[12]byGOVDetalhado!C44 -> 0.11162453 | AR44: =[12]byGOVDetalhado!D44 -> 0.33589017 | AS44: =[12]byGOVDetalhado!E44 -> 22.187249 | AT44: =[13]byGOVDetalhado!B44 -> 4.8306379 | AU44: =[13]byGOVDetalhado!C44 -> 0.11037971 | AV44: =[13]byGOVDetalhado!D44 -> 0.32385527 | AW44: =[13]byGOVDetalhado!E44 -> 24.471687 | AX44: =[14]byGOVDetalhado!B44 -> 5.3201198 | AY44: =[14]byGOVDetalhado!C44 -> 0.11049605 | AZ44: =[14]byGOVDetalhado!D44 -> 0.3247716 | BA44: =[14]byGOVDetalhado!E44 -> 26.701737 | BB44: =[15]byGOVDetalhado!B44 -> 5.8986247 | BC44: =[15]byGOVDetalhado!C44 -> 0.11063477 | BD44: =[15]byGOVDetalhado!D44 -> 0.32911913 | BE44: =[15]byGOVDetalhado!E44 -> 29.341616 | BF44: =[16]byGOVDetalhado!B44 -> 6.4613561 | BG44: =[16]byGOVDetalhado!C44 -> 0.11180842 | BH44: =[16]byGOVDetalhado!D44 -> 0.34011053 | BI44: =[16]byGOVDetalhado!E44 -> 31.86567 | BJ44: =[17]byGOVDetalhado!B44 -> 7.1878028 | BK44: =[17]byGOVDetalhado!C44 -> 0.11988089 | BL44: =[17]byGOVDetalhado!D44 -> 0.36504264 | BM44: =[17]byGOVDetalhado!E44 -> 35.156664 | BN44: =[18]byGOVDetalhado!B44 -> 7.7504554 | BO44: =[18]byGOVDetalhado!C44 -> 0.12366686 | BP44: =[18]byGOVDetalhado!D44 -> 0.37151841 | BQ44: =[18]byGOVDetalhado!E44 -> 37.608703 | BR44: =[19]byGOVDetalhado!B44 -> 8.6444444 | BS44: =[19]byGOVDetalhado!C44 -> 0.13189887 | BT44: =[19]byGOVDetalhado!D44 -> 0.39232218 | BU44: =[19]byGOVDetalhado!E44 -> 41.627688 | BV44: =[20]byGOVDetalhado!B44 -> 10.919362 | BW44: =[20]byGOVDetalhado!C44 -> 0.15850026 | BX44: =[20]byGOVDetalhado!D44 -> 0.46018897 | BY44: =[20]byGOVDetalhado!E44 -> 52.372321 | BZ44: =[21]byGOVDetalhado!B44 -> 12.058536 | CA44: =[21]byGOVDetalhado!C44 -> 0.16319289 | CB44: =[21]byGOVDetalhado!D44 -> 0.48293559 | CC44: =[21]byGOVDetalhado!E44 -> 57.3814 | CD44: =[22]byGOVDetalhado!B44 -> 11.504252 | CE44: =[22]byGOVDetalhado!C44 -> 0.15118082 | CF44: =[22]byGOVDetalhado!D44 -> 0.469263 | CG44: =[22]byGOVDetalhado!E44 -> 54.327945 | CH44: =[23]byGOVDetalhado!B44 -> 13.741151 | CI44: =[23]byGOVDetalhado!C44 -> 0.15441704 | CJ44: =[23]byGOVDetalhado!D44 -> 0.44891555 | CK44: =[23]byGOVDetalhado!E44 -> 64.416383 | CL44: =[24]byGOVDetalhado!B44 -> 15.700357 | CM44: =[24]byGOVDetalhado!C44 -> 0.15576252 | CN44: =[24]byGOVDetalhado!D44 -> 0.44622346 | CO44: =[24]byGOVDetalhado!E44 -> 77.310907 | CP44: =[25]byGOVDetalhado!B44 -> 18.046451 | CQ44: =[25]byGOVDetalhado!C44 -> 0.16490801 | CR44: =[25]byGOVDetalhado!D44 -> 0.47691625 | CS44: =[25]byGOVDetalhado!E44 -> 86.831813 | CT44: =[26]byGOVDetalhado!B44 -> 20.125118 | CU44: =[26]byGOVDetalhado!C44 -> 0.17135476 | CV44: =[26]byGOVDetalhado!D44 -> 0.47664755 | CW44: =[26]byGOVDetalhado!E44 -> 94.669126
A45: Previd. Municipal | B45: =[2]byGOVDetalhado!B45 -> 0.82276427 | C45: =[2]byGOVDetalhado!C45 -> 0.068428132 | D45: =[2]byGOVDetalhado!D45 -> 0.22391486 | E45: =[2]byGOVDetalhado!E45 -> 4.7435694 | F45: =[3]byGOVDetalhado!B45 -> 1.035901 | G45: =[3]byGOVDetalhado!C45 -> 0.078730536 | H45: =[3]byGOVDetalhado!D45 -> 0.24567988 | I45: =[3]byGOVDetalhado!E45 -> 5.9723888 | J45: =[4]byGOVDetalhado!B45 -> 2.0863509 | K45: =[4]byGOVDetalhado!C45 -> 0.14013764 | L45: =[4]byGOVDetalhado!D45 -> 0.42112363 | M45: =[4]byGOVDetalhado!E45 -> 11.702918 | N45: =[5]byGOVDetalhado!B45 -> 2.6998817 | O45: =[5]byGOVDetalhado!C45 -> 0.15715718 | P45: =[5]byGOVDetalhado!D45 -> 0.48210894 | Q45: =[5]byGOVDetalhado!E45 -> 14.94793 | R45: =[6]byGOVDetalhado!B45 -> 3.3940958 | S45: =[6]byGOVDetalhado!C45 -> 0.17336708 | T45: =[6]byGOVDetalhado!D45 -> 0.51562181 | U45: =[6]byGOVDetalhado!E45 -> 18.555947 | V45: =[7]byGOVDetalhado!B45 -> 3.1856205 | W45: =[7]byGOVDetalhado!C45 -> 0.14676322 | X45: =[7]byGOVDetalhado!D45 -> 0.42239285 | Y45: =[7]byGOVDetalhado!E45 -> 17.205545 | Z45: =[8]byGOVDetalhado!B45 -> 3.4779493 | AA45: =[8]byGOVDetalhado!C45 -> 0.14434619 | AB45: =[8]byGOVDetalhado!D45 -> 0.41926454 | AC45: =[8]byGOVDetalhado!E45 -> 18.565387 | AD45: =[9]byGOVDetalhado!B45 -> 4.4498505 | AE45: =[9]byGOVDetalhado!C45 -> 0.16358163 | AF45: =[9]byGOVDetalhado!D45 -> 0.47297602 | AG45: =[9]byGOVDetalhado!E45 -> 23.486677 | AH45: =[10]byGOVDetalhado!B45 -> 4.5661628 | AI45: =[10]byGOVDetalhado!C45 -> 0.14683126 | AJ45: =[10]byGOVDetalhado!D45 -> 0.42244633 | AK45: =[10]byGOVDetalhado!E45 -> 23.840154 | AL45: =[11]byGOVDetalhado!B45 -> 5.1621578 | AM45: =[11]byGOVDetalhado!C45 -> 0.15487841 | AN45: =[11]byGOVDetalhado!D45 -> 0.4670055 | AO45: =[11]byGOVDetalhado!E45 -> 26.671757 | AP45: =[12]byGOVDetalhado!B45 -> 6.0358281 | AQ45: =[12]byGOVDetalhado!C45 -> 0.15532851 | AR45: =[12]byGOVDetalhado!D45 -> 0.46740013 | AS45: =[12]byGOVDetalhado!E45 -> 30.874149 | AT45: =[13]byGOVDetalhado!B45 -> 7.2115784 | AU45: =[13]byGOVDetalhado!C45 -> 0.16478402 | AV45: =[13]byGOVDetalhado!D45 -> 0.4834781 | AW45: =[13]byGOVDetalhado!E45 -> 36.53337 | AX45: =[14]byGOVDetalhado!B45 -> 7.8656269 | AY45: =[14]byGOVDetalhado!C45 -> 0.16336488 | AZ45: =[14]byGOVDetalhado!D45 -> 0.48016442 | BA45: =[14]byGOVDetalhado!E45 -> 39.477664 | BB45: =[15]byGOVDetalhado!B45 -> 8.5071647 | BC45: =[15]byGOVDetalhado!C45 -> 0.15956063 | BD45: =[15]byGOVDetalhado!D45 -> 0.474665 | BE45: =[15]byGOVDetalhado!E45 -> 42.317315 | BF45: =[16]byGOVDetalhado!B45 -> 9.2741001 | BG45: =[16]byGOVDetalhado!C45 -> 0.16048063 | BH45: =[16]byGOVDetalhado!D45 -> 0.48816673 | BI45: =[16]byGOVDetalhado!E45 -> 45.737367 | BJ45: =[17]byGOVDetalhado!B45 -> 10.698587 | BK45: =[17]byGOVDetalhado!C45 -> 0.17843507 | BL45: =[17]byGOVDetalhado!D45 -> 0.54334273 | BM45: =[17]byGOVDetalhado!E45 -> 52.328456 | BN45: =[18]byGOVDetalhado!B45 -> 12.048673 | BO45: =[18]byGOVDetalhado!C45 -> 0.19224955 | BP45: =[18]byGOVDetalhado!D45 -> 0.57755366 | BQ45: =[18]byGOVDetalhado!E45 -> 58.465593 | BR45: =[19]byGOVDetalhado!B45 -> 12.823354 | BS45: =[19]byGOVDetalhado!C45 -> 0.19566161 | BT45: =[19]byGOVDetalhado!D45 -> 0.58197914 | BU45: =[19]byGOVDetalhado!E45 -> 61.751406 | BV45: =[20]byGOVDetalhado!B45 -> 13.547791 | BW45: =[20]byGOVDetalhado!C45 -> 0.19665328 | BX45: =[20]byGOVDetalhado!D45 -> 0.5709623 | BY45: =[20]byGOVDetalhado!E45 -> 64.979003 | BZ45: =[21]byGOVDetalhado!B45 -> 14.835992 | CA45: =[21]byGOVDetalhado!C45 -> 0.20078128 | CB45: =[21]byGOVDetalhado!D45 -> 0.59417067 | CC45: =[21]byGOVDetalhado!E45 -> 70.59812 | CD45: =[22]byGOVDetalhado!B45 -> 16.744059 | CE45: =[22]byGOVDetalhado!C45 -> 0.2200387 | CF45: =[22]byGOVDetalhado!D45 -> 0.68299682 | CG45: =[22]byGOVDetalhado!E45 -> 79.072531 | CH45: =[23]byGOVDetalhado!B45 -> 19.329653 | CI45: =[23]byGOVDetalhado!C45 -> 0.21721818 | CJ45: =[23]byGOVDetalhado!D45 -> 0.63148873 | CK45: =[23]byGOVDetalhado!E45 -> 90.614414 | CL45: =[24]byGOVDetalhado!B45 -> 21.431529 | CM45: =[24]byGOVDetalhado!C45 -> 0.21262121 | CN45: =[24]byGOVDetalhado!D45 -> 0.6091104 | CO45: =[24]byGOVDetalhado!E45 -> 105.53205 | CP45: =[25]byGOVDetalhado!B45 -> 26.984806 | CQ45: =[25]byGOVDetalhado!C45 -> 0.24658648 | CR45: =[25]byGOVDetalhado!D45 -> 0.71313149 | CS45: =[25]byGOVDetalhado!E45 -> 129.83936 | CT45: =[26]byGOVDetalhado!B45 -> 29.224977 | CU45: =[26]byGOVDetalhado!C45 -> 0.24883526 | CV45: =[26]byGOVDetalhado!D45 -> 0.69217055 | CW45: =[26]byGOVDetalhado!E45 -> 137.47512
A46: Contribuições de Melhoria e Econômicas | B46: =[2]byGOVDetalhado!B46 -> 0.44854758 | C46: =[2]byGOVDetalhado!C46 -> 0.037305063 | D46: =[2]byGOVDetalhado!D46 -> 0.12207198 | E46: =[2]byGOVDetalhado!E46 -> 2.5860585 | F46: =[3]byGOVDetalhado!B46 -> 0.54834376 | G46: =[3]byGOVDetalhado!C46 -> 0.041675218 | H46: =[3]byGOVDetalhado!D46 -> 0.13004818 | I46: =[3]byGOVDetalhado!E46 -> 3.161424 | J46: =[4]byGOVDetalhado!B46 -> 0.40326716 | K46: =[4]byGOVDetalhado!C46 -> 0.027086962 | L46: =[4]byGOVDetalhado!D46 -> 0.081398258 | M46: =[4]byGOVDetalhado!E46 -> 2.2620368 | N46: =[5]byGOVDetalhado!B46 -> 1.5829323 | O46: =[5]byGOVDetalhado!C46 -> 0.092140766 | P46: =[5]byGOVDetalhado!D46 -> 0.28265898 | Q46: =[5]byGOVDetalhado!E46 -> 8.7639249 | R46: =[6]byGOVDetalhado!B46 -> 2.6249195 | S46: =[6]byGOVDetalhado!C46 -> 0.13407831 | T46: =[6]byGOVDetalhado!D46 -> 0.39877064 | U46: =[6]byGOVDetalhado!E46 -> 14.350764 | V46: =[7]byGOVDetalhado!B46 -> 1.9565987 | W46: =[7]byGOVDetalhado!C46 -> 0.090141538 | X46: =[7]byGOVDetalhado!D46 -> 0.25943244 | Y46: =[7]byGOVDetalhado!E46 -> 10.567595 | Z46: =[8]byGOVDetalhado!B46 -> 2.2682382 | AA46: =[8]byGOVDetalhado!C46 -> 0.094139251 | AB46: =[8]byGOVDetalhado!D46 -> 0.27343465 | AC46: =[8]byGOVDetalhado!E46 -> 12.107916 | AD46: =[9]byGOVDetalhado!B46 -> 2.5498988 | AE46: =[9]byGOVDetalhado!C46 -> 0.093737217 | AF46: =[9]byGOVDetalhado!D46 -> 0.27102955 | AG46: =[9]byGOVDetalhado!E46 -> 13.458576 | AH46: =[10]byGOVDetalhado!B46 -> 2.6587321 | AI46: =[10]byGOVDetalhado!C46 -> 0.085495195 | AJ46: =[10]byGOVDetalhado!D46 -> 0.24597713 | AK46: =[10]byGOVDetalhado!E46 -> 13.881367 | AL46: =[11]byGOVDetalhado!B46 -> 2.8897082 | AM46: =[11]byGOVDetalhado!C46 -> 0.086698902 | AN46: =[11]byGOVDetalhado!D46 -> 0.26142355 | AO46: =[11]byGOVDetalhado!E46 -> 14.9305 | AP46: =[12]byGOVDetalhado!B46 -> 3.2742683 | AQ46: =[12]byGOVDetalhado!C46 -> 0.084261381 | AR46: =[12]byGOVDetalhado!D46 -> 0.25355153 | AS46: =[12]byGOVDetalhado!E46 -> 16.748364 | AT46: =[13]byGOVDetalhado!B46 -> 3.3899537 | AU46: =[13]byGOVDetalhado!C46 -> 0.077460189 | AV46: =[13]byGOVDetalhado!D46 -> 0.22726903 | AW46: =[13]byGOVDetalhado!E46 -> 17.173277 | AX46: =[14]byGOVDetalhado!B46 -> 3.62109 | AY46: =[14]byGOVDetalhado!C46 -> 0.075208109 | AZ46: =[14]byGOVDetalhado!D46 -> 0.22105276 | BA46: =[14]byGOVDetalhado!E46 -> 18.174288 | BB46: =[15]byGOVDetalhado!B46 -> 4.2616137 | BC46: =[15]byGOVDetalhado!C46 -> 0.07993095 | BD46: =[15]byGOVDetalhado!D46 -> 0.23778061 | BE46: =[15]byGOVDetalhado!E46 -> 21.198608 | BF46: =[16]byGOVDetalhado!B46 -> 4.7278201 | BG46: =[16]byGOVDetalhado!C46 -> 0.081811014 | BH46: =[16]byGOVDetalhado!D46 -> 0.24886128 | BI46: =[16]byGOVDetalhado!E46 -> 23.316337 | BJ46: =[17]byGOVDetalhado!B46 -> 6.3462093 | BK46: =[17]byGOVDetalhado!C46 -> 0.10584448 | BL46: =[17]byGOVDetalhado!D46 -> 0.32230114 | BM46: =[17]byGOVDetalhado!E46 -> 31.040299 | BN46: =[18]byGOVDetalhado!B46 -> 7.6690952 | BO46: =[18]byGOVDetalhado!C46 -> 0.12236867 | BP46: =[18]byGOVDetalhado!D46 -> 0.3676184 | BQ46: =[18]byGOVDetalhado!E46 -> 37.213907 | BR46: =[19]byGOVDetalhado!B46 -> 7.9531407 | BS46: =[19]byGOVDetalhado!C46 -> 0.1213508 | BT46: =[19]byGOVDetalhado!D46 -> 0.36094783 | BU46: =[19]byGOVDetalhado!E46 -> 38.298686 | BV46: =[20]byGOVDetalhado!B46 -> 9.1871864 | BW46: =[20]byGOVDetalhado!C46 -> 0.13335682 | BX46: =[20]byGOVDetalhado!D46 -> 0.38718763 | BY46: =[20]byGOVDetalhado!E46 -> 44.064322 | BZ46: =[21]byGOVDetalhado!B46 -> 10.722405 | CA46: =[21]byGOVDetalhado!C46 -> 0.14511049 | CB46: =[21]byGOVDetalhado!D46 -> 0.4294245 | CC46: =[21]byGOVDetalhado!E46 -> 51.023323 | CD46: =[22]byGOVDetalhado!B46 -> 10.453193 | CE46: =[22]byGOVDetalhado!C46 -> 0.13736855 | CF46: =[22]byGOVDetalhado!D46 -> 0.42638991 | CG46: =[22]byGOVDetalhado!E46 -> 49.364402 | CH46: =[23]byGOVDetalhado!B46 -> 12.044112 | CI46: =[23]byGOVDetalhado!C46 -> 0.13534646 | CJ46: =[23]byGOVDetalhado!D46 -> 0.39347428 | CK46: =[23]byGOVDetalhado!E46 -> 56.46093 | CL46: =[24]byGOVDetalhado!B46 -> 12.968975 | CM46: =[24]byGOVDetalhado!C46 -> 0.1286646 | CN46: =[24]byGOVDetalhado!D46 -> 0.36859421 | CO46: =[24]byGOVDetalhado!E46 -> 63.861171 | CP46: =[25]byGOVDetalhado!B46 -> 14.885181 | CQ46: =[25]byGOVDetalhado!C46 -> 0.13602041 | CR46: =[25]byGOVDetalhado!D46 -> 0.3933729 | CS46: =[25]byGOVDetalhado!E46 -> 71.621133 | CT46: =[26]byGOVDetalhado!B46 -> 16.237151 | CU46: =[26]byGOVDetalhado!C46 -> 0.13825077 | CV46: =[26]byGOVDetalhado!D46 -> 0.38456411 | CW46: =[26]byGOVDetalhado!E46 -> 76.380018
A47: Demais (multas, juros e dívida ativa) | B47: =[2]byGOVDetalhado!B47 -> 2.575981 | C47: =[2]byGOVDetalhado!C47 -> 0.21424067 | D47: =[2]byGOVDetalhado!D47 -> 0.70105185 | E47: =[2]byGOVDetalhado!E47 -> 14.851574 | F47: =[3]byGOVDetalhado!B47 -> 2.7790609 | G47: =[3]byGOVDetalhado!C47 -> 0.21121416 | H47: =[3]byGOVDetalhado!D47 -> 0.65909714 | I47: =[3]byGOVDetalhado!E47 -> 16.022412 | J47: =[4]byGOVDetalhado!B47 -> 3.3229748 | K47: =[4]byGOVDetalhado!C47 -> 0.22320015 | L47: =[4]byGOVDetalhado!D47 -> 0.67073241 | M47: =[4]byGOVDetalhado!E47 -> 18.639483 | N47: =[5]byGOVDetalhado!B47 -> 3.8249527 | O47: =[5]byGOVDetalhado!C47 -> 0.22264634 | P47: =[5]byGOVDetalhado!D47 -> 0.68300914 | Q47: =[5]byGOVDetalhado!E47 -> 21.1769 | R47: =[6]byGOVDetalhado!B47 -> 4.4345539 | S47: =[6]byGOVDetalhado!C47 -> 0.22651266 | T47: =[6]byGOVDetalhado!D47 -> 0.67368538 | U47: =[6]byGOVDetalhado!E47 -> 24.244262 | V47: =[7]byGOVDetalhado!B47 -> 4.7689614 | W47: =[7]byGOVDetalhado!C47 -> 0.21970858 | X47: =[7]byGOVDetalhado!D47 -> 0.6323337 | Y47: =[7]byGOVDetalhado!E47 -> 25.757173 | Z47: =[8]byGOVDetalhado!B47 -> 5.5964709 | AA47: =[8]byGOVDetalhado!C47 -> 0.23227172 | AB47: =[8]byGOVDetalhado!D47 -> 0.67465095 | AC47: =[8]byGOVDetalhado!E47 -> 29.874112 | AD47: =[9]byGOVDetalhado!B47 -> 6.2979323 | AE47: =[9]byGOVDetalhado!C47 -> 0.23151924 | AF47: =[9]byGOVDetalhado!D47 -> 0.66940922 | AG47: =[9]byGOVDetalhado!E47 -> 33.241005 | AH47: =[10]byGOVDetalhado!B47 -> 6.7998178 | AI47: =[10]byGOVDetalhado!C47 -> 0.21865751 | AJ47: =[10]byGOVDetalhado!D47 -> 0.62909673 | AK47: =[10]byGOVDetalhado!E47 -> 35.502173 | AL47: =[11]byGOVDetalhado!B47 -> 6.7997387 | AM47: =[11]byGOVDetalhado!C47 -> 0.20401017 | AN47: =[11]byGOVDetalhado!D47 -> 0.61515272 | AO47: =[11]byGOVDetalhado!E47 -> 35.132785 | AP47: =[12]byGOVDetalhado!B47 -> 7.7522648 | AQ47: =[12]byGOVDetalhado!C47 -> 0.1995 | AR47: =[12]byGOVDetalhado!D47 -> 0.6003169 | AS47: =[12]byGOVDetalhado!E47 -> 39.653975 | AT47: =[13]byGOVDetalhado!B47 -> 9.2732283 | AU47: =[13]byGOVDetalhado!C47 -> 0.21189257 | AV47: =[13]byGOVDetalhado!D47 -> 0.62169508 | AW47: =[13]byGOVDetalhado!E47 -> 46.97755 | AX47: =[14]byGOVDetalhado!B47 -> 9.8175753 | AY47: =[14]byGOVDetalhado!C47 -> 0.20390581 | AZ47: =[14]byGOVDetalhado!D47 -> 0.5993229 | BA47: =[14]byGOVDetalhado!E47 -> 49.274513 | BB47: =[15]byGOVDetalhado!B47 -> 11.130269 | BC47: =[15]byGOVDetalhado!C47 -> 0.20875965 | BD47: =[15]byGOVDetalhado!D47 -> 0.6210235 | BE47: =[15]byGOVDetalhado!E47 -> 55.365463 | BF47: =[16]byGOVDetalhado!B47 -> 13.057885 | BG47: =[16]byGOVDetalhado!C47 -> 0.22595589 | BH47: =[16]byGOVDetalhado!D47 -> 0.68733621 | BI47: =[16]byGOVDetalhado!E47 -> 64.397974 | BJ47: =[17]byGOVDetalhado!B47 -> 13.035138 | BK47: =[17]byGOVDetalhado!C47 -> 0.21740496 | BL47: =[17]byGOVDetalhado!D47 -> 0.66200776 | BM47: =[17]byGOVDetalhado!E47 -> 63.756893 | BN47: =[18]byGOVDetalhado!B47 -> 13.029589 | BO47: =[18]byGOVDetalhado!C47 -> 0.20790112 | BP47: =[18]byGOVDetalhado!D47 -> 0.62457391 | BQ47: =[18]byGOVDetalhado!E47 -> 63.22544 | BR47: =[19]byGOVDetalhado!B47 -> 16.254821 | BS47: =[19]byGOVDetalhado!C47 -> 0.2480197 | BT47: =[19]byGOVDetalhado!D47 -> 0.7377139 | BU47: =[19]byGOVDetalhado!E47 -> 78.275779 | BV47: =[20]byGOVDetalhado!B47 -> 0 | BW47: =[20]byGOVDetalhado!C47 -> 0 | BX47: =[20]byGOVDetalhado!D47 -> 0 | BY47: =[20]byGOVDetalhado!E47 -> 0 | BZ47: =[21]byGOVDetalhado!B47 -> 0 | CA47: =[21]byGOVDetalhado!C47 -> 0 | CB47: =[21]byGOVDetalhado!D47 -> 0 | CC47: =[21]byGOVDetalhado!E47 -> 0 | CD47: =[22]byGOVDetalhado!B47 -> 0 | CE47: =[22]byGOVDetalhado!C47 -> 0 | CF47: =[22]byGOVDetalhado!D47 -> 0 | CG47: =[22]byGOVDetalhado!E47 -> 0 | CH47: =[23]byGOVDetalhado!B47 -> 0 | CI47: =[23]byGOVDetalhado!C47 -> 0 | CJ47: =[23]byGOVDetalhado!D47 -> 0 | CK47: =[23]byGOVDetalhado!E47 -> 0 | CL47: =[24]byGOVDetalhado!B47 -> 0 | CM47: =[24]byGOVDetalhado!C47 -> 0 | CN47: =[24]byGOVDetalhado!D47 -> 0 | CO47: =[24]byGOVDetalhado!E47 -> 0 | CP47: =[25]byGOVDetalhado!B47 -> 0 | CQ47: =[25]byGOVDetalhado!C47 -> 0 | CR47: =[25]byGOVDetalhado!D47 -> 0 | CS47: =[25]byGOVDetalhado!E47 -> 0 | CT47: =[26]byGOVDetalhado!B47 -> 0 | CU47: =[26]byGOVDetalhado!C47 -> 0 | CV47: =[26]byGOVDetalhado!D47 -> 0 | CW47: =[26]byGOVDetalhado!E47 -> 0
A48: (1) Dados extraídos da Execução Orçamentária da União. Inclui SIMPLES/Previdência | Z48: =[8]byGOVDetalhado!B48 -> 0 | AA48: =[8]byGOVDetalhado!C48 -> 0 | AB48: =[8]byGOVDetalhado!D48 -> 0 | AC48: =[8]byGOVDetalhado!E48 -> 0
A49: (2) Em 2003 e 2004, inclui "Cota-Parte do Serv. No Fundo de Saúde Militar", classificada como "Outras Receitas" no Balanço da STN.
A50: (3) Inclui "Receita Part. Seguro-Dpvat-Sist. Nac. de Trânsito", classifacada como "Outras Receitas" no Balanço da STN.
A51: (4) A fonte dos dados é o cálculo de carga tributária efetuado pela SRF.
A52: (5) Inclui "Util.Recurso Hidricos-Trat. Itaipu", classificada como "Outras Receitas" no Balanço da STN
A53: (6) Em 2004 e 2005, como o Finbra cobre somente 77% dos municípios, aplicou-se uma receita 5% adicional sobre o IPTU, o ISS e as Taxas. Nos anos de 2003, 2002, 2001, a cobertura é de 90%, 93% e 96% dos municípios, respectivamente. IPTU, ISS e ITBI dos anos de 2005, 2004, 2003 e 2002 incluem a arrecadação de Brasília.
A54: As demais rubricas de Brasília estão classificadas nas receitas estaduais.

Sheet AD ESFERA
A1: Arrecadação Direta por Esfera de Governo
A3: Esfera de Governo | B3: 2000 | F3: 2001 | J3: 2002 | N3: 2003 | R3: 2004 | V3: 2005 | Z3: 2006 | AD3: 2007 | AH3: 2008 | AL3: 2009 | AP3: 2010 | AT3: 2011 | AX3: 2012 | BB3: 2013 | BF3: 2014 | BJ3: 2015 | BN3: 2016 | BR3: 2017 | BV3: 2018 | BZ3: 2019 | CD3: 2020 | CH3: 2021 | CL3: 2022 | CP3: 2023 | CT3: 2024
B4: R$ Bilhões | C4: % PIB | D4: % Total | E4: Per capita (R$) | F4: R$ Bilhões | G4: % PIB | H4: % Total | I4: Per capita (R$) | J4: R$ Bilhões | K4: % PIB | L4: % Total | M4: Per capita (R$) | N4: R$ Bilhões | O4: % PIB | P4: % Total | Q4: Per capita (R$) | R4: R$ Bilhões | S4: % PIB | T4: % Total | U4: Per capita (R$) | V4: R$ Bilhões | W4: % PIB | X4: % Total | Y4: Per capita (R$) | Z4: R$ Bilhões | AA4: % PIB | AB4: % Total | AC4: Per capita (R$) | AD4: R$ Bilhões | AE4: % PIB | AF4: % Total | AG4: Per capita (R$) | AH4: R$ Bilhões | AI4: % PIB | AJ4: % Total | AK4: Per capita (R$) | AL4: R$ Bilhões | AM4: % PIB | AN4: % Total | AO4: Per capita (R$) | AP4: R$ Bilhões | AQ4: % PIB | AR4: % Total | AS4: Per capita (R$) | AT4: R$ Bilhões | AU4: % PIB | AV4: % Total | AW4: Per capita (R$) | AX4: R$ Bilhões | AY4: % PIB | AZ4: % Total | BA4: Per capita (R$) | BB4: R$ Bilhões | BC4: % PIB | BD4: % Total | BE4: Per capita (R$) | BF4: R$ Bilhões | BG4: % PIB | BH4: % Total | BI4: Per capita (R$) | BJ4: R$ Bilhões | BK4: % PIB | BL4: % Total | BM4: Per capita (R$) | BN4: R$ Bilhões | BO4: % PIB | BP4: % Total | BQ4: Per capita (R$) | BR4: R$ Bilhões | BS4: % PIB | BT4: % Total | BU4: Per capita (R$) | BV4: R$ Bilhões | BW4: % PIB | BX4: % Total | BY4: Per capita (R$) | BZ4: R$ Bilhões | CA4: % PIB | CB4: % Total | CC4: Per capita (R$) | CD4: R$ Bilhões | CE4: % PIB | CF4: % Total | CG4: Per capita (R$) | CH4: R$ Bilhões | CI4: % PIB | CJ4: % Total | CK4: Per capita (R$) | CL4: R$ Bilhões | CM4: % PIB | CN4: % Total | CO4: Per capita (R$) | CP4: R$ Bilhões | CQ4: % PIB | CR4: % Total | CS4: Per capita (R$) | CT4: R$ Bilhões | CU4: % PIB | CV4: % Total | CW4: Per capita (R$)
A5: PIB | B5: ='[2]AD ESFERA'!B5 -> 1202.3772 | C5: ='[2]AD ESFERA'!C5 -> 0 | D5: ='[2]AD ESFERA'!D5 -> 0 | E5: ='[2]AD ESFERA'!E5 -> 0 | F5: ='[3]AD ESFERA'!B5 -> 1315.755 | G5: ='[3]AD ESFERA'!C5 -> 0 | H5: ='[3]AD ESFERA'!D5 -> 0 | I5: ='[3]AD ESFERA'!E5 -> 0 | J5: ='[4]AD ESFERA'!B5 -> 1488.787 | K5: ='[4]AD ESFERA'!C5 -> 0 | L5: ='[4]AD ESFERA'!D5 -> 0 | M5: ='[4]AD ESFERA'!E5 -> 0 | N5: ='[5]AD ESFERA'!B5 -> 1717.95 | O5: ='[5]AD ESFERA'!C5 -> 0 | P5: ='[5]AD ESFERA'!D5 -> 0 | Q5: ='[5]AD ESFERA'!E5 -> 0 | R5: ='[6]AD ESFERA'!B5 -> 1957.751 | S5: ='[6]AD ESFERA'!C5 -> 0 | T5: ='[6]AD ESFERA'!D5 -> 0 | U5: ='[6]AD ESFERA'!E5 -> 0 | V5: ='[7]AD ESFERA'!B5 -> 2170.585 | W5: ='[7]AD ESFERA'!C5 -> 0 | X5: ='[7]AD ESFERA'!D5 -> 0 | Y5: ='[7]AD ESFERA'!E5 -> 0 | Z5: ='[8]AD ESFERA'!B5 -> 2409.45 | AA5: ='[8]AD ESFERA'!C5 -> 0 | AB5: ='[8]AD ESFERA'!D5 -> 0 | AC5: ='[8]AD ESFERA'!E5 -> 0 | AD5: ='[9]AD ESFERA'!B5 -> 2720.263 | AE5: ='[9]AD ESFERA'!C5 -> 0 | AF5: ='[9]AD ESFERA'!D5 -> 0 | AG5: ='[9]AD ESFERA'!E5 -> 0 | AH5: ='[10]AD ESFERA'!B5 -> 3109.803 | AI5: ='[10]AD ESFERA'!C5 -> 0 | AJ5: ='[10]AD ESFERA'!D5 -> 0 | AK5: ='[10]AD ESFERA'!E5 -> 0 | AL5: ='[11]AD ESFERA'!B5 -> 3333.039 | AM5: ='[11]AD ESFERA'!C5 -> 0 | AN5: ='[11]AD ESFERA'!D5 -> 0 | AO5: ='[11]AD ESFERA'!E5 -> 0 | AP5: ='[12]AD ESFERA'!B5 -> 3885.847 | AQ5: ='[12]AD ESFERA'!C5 -> 0 | AR5: ='[12]AD ESFERA'!D5 -> 0 | AS5: ='[12]AD ESFERA'!E5 -> 0 | AT5: ='[13]AD ESFERA'!B5 -> 4376.382 | AU5: ='[13]AD ESFERA'!C5 -> 0 | AV5: ='[13]AD ESFERA'!D5 -> 0 | AW5: ='[13]AD ESFERA'!E5 -> 0 | AX5: ='[14]AD ESFERA'!B5 -> 4814.76 | AY5: ='[14]AD ESFERA'!C5 -> 0 | AZ5: ='[14]AD ESFERA'!D5 -> 0 | BA5: ='[14]AD ESFERA'!E5 -> 0 | BB5: ='[15]AD ESFERA'!B5 -> 5331.619 | BC5: ='[15]AD ESFERA'!C5 -> 0 | BD5: ='[15]AD ESFERA'!D5 -> 0 | BE5: ='[15]AD ESFERA'!E5 -> 0 | BF5: ='[16]AD ESFERA'!B5 -> 5778.953 | BG5: ='[16]AD ESFERA'!C5 -> 0 | BH5: ='[16]AD ESFERA'!D5 -> 0 | BI5: ='[16]AD ESFERA'!E5 -> 0 | BJ5: ='[17]AD ESFERA'!B5 -> 5995.787 | BK5: ='[17]AD ESFERA'!C5 -> 0 | BL5: ='[17]AD ESFERA'!D5 -> 0 | BM5: ='[17]AD ESFERA'!E5 -> 0 | BN5: ='[18]AD ESFERA'!B5 -> 6267.205 | BO5: ='[18]AD ESFERA'!C5 -> 0 | BP5: ='[18]AD ESFERA'!D5 -> 0 | BQ5: ='[18]AD ESFERA'!E5 -> 0 | BR5: ='[19]AD ESFERA'!B5 -> 6553.8427 | BS5: ='[19]AD ESFERA'!C5 -> 0 | BT5: ='[19]AD ESFERA'!D5 -> 0 | BU5: ='[19]AD ESFERA'!E5 -> 0 | BV5: ='[20]AD ESFERA'!B5 -> 6889.1761 | BW5: ='[20]AD ESFERA'!C5 -> 0 | BX5: ='[20]AD ESFERA'!D5 -> 0 | BY5: ='[20]AD ESFERA'!E5 -> 0 | BZ5: ='[21]AD ESFERA'!B5 -> 7389.131 | CA5: ='[21]AD ESFERA'!C5 -> 0 | CB5: ='[21]AD ESFERA'!D5 -> 0 | CC5: ='[21]AD ESFERA'!E5 -> 0 | CD5: ='[22]AD ESFERA'!B5 -> 7609.597 | CE5: ='[22]AD ESFERA'!C5 -> 0 | CF5: ='[22]AD ESFERA'!D5 -> 0 | CG5: ='[22]AD ESFERA'!E5 -> 0 | CH5: ='[23]AD ESFERA'!B5 -> 8898.727 | CI5: ='[23]AD ESFERA'!C5 -> 0 | CJ5: ='[23]AD ESFERA'!D5 -> 0 | CK5: ='[23]AD ESFERA'!E5 -> 0 | CL5: ='[24]AD ESFERA'!B5 -> 10079.676 | CM5: ='[24]AD ESFERA'!C5 -> 0 | CN5: ='[24]AD ESFERA'!D5 -> 0 | CO5: ='[24]AD ESFERA'!E5 -> 0 | CP5: ='[25]AD ESFERA'!B5 -> 10943.344 | CQ5: ='[25]AD ESFERA'!C5 -> 0 | CR5: ='[25]AD ESFERA'!D5 -> 0 | CS5: ='[25]AD ESFERA'!E5 -> 0 | CT5: ='[26]AD ESFERA'!B5 -> 11744.709 | CU5: ='[26]AD ESFERA'!C5 -> 0 | CV5: ='[26]AD ESFERA'!D5 -> 0 | CW5: ='[26]AD ESFERA'!E5 -> 0
A6: População | B6: ='[2]AD ESFERA'!B6 -> 173448346 | C6: ='[2]AD ESFERA'!C6 -> 0 | D6: ='[2]AD ESFERA'!D6 -> 0 | E6: ='[2]AD ESFERA'!E6 -> 0 | F6: ='[3]AD ESFERA'!B6 -> 173448346 | G6: ='[3]AD ESFERA'!C6 -> 0 | H6: ='[3]AD ESFERA'!D6 -> 0 | I6: ='[3]AD ESFERA'!E6 -> 0 | J6: ='[4]AD ESFERA'!B6 -> 178276128 | K6: ='[4]AD ESFERA'!C6 -> 0 | L6: ='[4]AD ESFERA'!D6 -> 0 | M6: ='[4]AD ESFERA'!E6 -> 0 | N6: ='[5]AD ESFERA'!B6 -> 180619108 | O6: ='[5]AD ESFERA'!C6 -> 0 | P6: ='[5]AD ESFERA'!D6 -> 0 | Q6: ='[5]AD ESFERA'!E6 -> 0 | R6: ='[6]AD ESFERA'!B6 -> 182911487 | S6: ='[6]AD ESFERA'!C6 -> 0 | T6: ='[6]AD ESFERA'!D6 -> 0 | U6: ='[6]AD ESFERA'!E6 -> 0 | V6: ='[7]AD ESFERA'!B6 -> 185150806 | W6: ='[7]AD ESFERA'!C6 -> 0 | X6: ='[7]AD ESFERA'!D6 -> 0 | Y6: ='[7]AD ESFERA'!E6 -> 0 | Z6: ='[8]AD ESFERA'!B6 -> 187335137 | AA6: ='[8]AD ESFERA'!C6 -> 0 | AB6: ='[8]AD ESFERA'!D6 -> 0 | AC6: ='[8]AD ESFERA'!E6 -> 0 | AD6: ='[9]AD ESFERA'!B6 -> 189462755 | AE6: ='[9]AD ESFERA'!C6 -> 0 | AF6: ='[9]AD ESFERA'!D6 -> 0 | AG6: ='[9]AD ESFERA'!E6 -> 0 | AH6: ='[10]AD ESFERA'!B6 -> 191532439 | AI6: ='[10]AD ESFERA'!C6 -> 0 | AJ6: ='[10]AD ESFERA'!D6 -> 0 | AK6: ='[10]AD ESFERA'!E6 -> 0 | AL6: ='[11]AD ESFERA'!B6 -> 193543969 | AM6: ='[11]AD ESFERA'!C6 -> 0 | AN6: ='[11]AD ESFERA'!D6 -> 0 | AO6: ='[11]AD ESFERA'!E6 -> 0 | AP6: ='[12]AD ESFERA'!B6 -> 195497797 | AQ6: ='[12]AD ESFERA'!C6 -> 0 | AR6: ='[12]AD ESFERA'!D6 -> 0 | AS6: ='[12]AD ESFERA'!E6 -> 0 | AT6: ='[13]AD ESFERA'!B6 -> 197397018 | AU6: ='[13]AD ESFERA'!C6 -> 0 | AV6: ='[13]AD ESFERA'!D6 -> 0 | AW6: ='[13]AD ESFERA'!E6 -> 0 | AX6: ='[14]AD ESFERA'!B6 -> 199242462 | AY6: ='[14]AD ESFERA'!C6 -> 0 | AZ6: ='[14]AD ESFERA'!D6 -> 0 | BA6: ='[14]AD ESFERA'!E6 -> 0 | BB6: ='[15]AD ESFERA'!B6 -> 201032714 | BC6: ='[15]AD ESFERA'!C6 -> 0 | BD6: ='[15]AD ESFERA'!D6 -> 0 | BE6: ='[15]AD ESFERA'!E6 -> 0 | BF6: ='[16]AD ESFERA'!B6 -> 202768562 | BG6: ='[16]AD ESFERA'!C6 -> 0 | BH6: ='[16]AD ESFERA'!D6 -> 0 | BI6: ='[16]AD ESFERA'!E6 -> 0 | BJ6: ='[17]AD ESFERA'!B6 -> 204450649 | BK6: ='[17]AD ESFERA'!C6 -> 0 | BL6: ='[17]AD ESFERA'!D6 -> 0 | BM6: ='[17]AD ESFERA'!E6 -> 0 | BN6: ='[18]AD ESFERA'!B6 -> 206081432 | BO6: ='[18]AD ESFERA'!C6 -> 0 | BP6: ='[18]AD ESFERA'!D6 -> 0 | BQ6: ='[18]AD ESFERA'!E6 -> 0 | BR6: ='[19]AD ESFERA'!B6 -> 207660929 | BS6: ='[19]AD ESFERA'!C6 -> 0 | BT6: ='[19]AD ESFERA'!D6 -> 0 | BU6: ='[19]AD ESFERA'!E6 -> 0 | BV6: ='[20]AD ESFERA'!B6 -> 208494900 | BW6: ='[20]AD ESFERA'!C6 -> 0 | BX6: ='[20]AD ESFERA'!D6 -> 0 | BY6: ='[20]AD ESFERA'!E6 -> 0 | BZ6: ='[21]AD ESFERA'!B6 -> 210147125 | CA6: ='[21]AD ESFERA'!C6 -> 0 | CB6: ='[21]AD ESFERA'!D6 -> 0 | CC6: ='[21]AD ESFERA'!E6 -> 0 | CD6: ='[22]AD ESFERA'!B6 -> 211755692 | CE6: ='[22]AD ESFERA'!C6 -> 0 | CF6: ='[22]AD ESFERA'!D6 -> 0 | CG6: ='[22]AD ESFERA'!E6 -> 0 | CH6: ='[23]AD ESFERA'!B6 -> 213317639 | CI6: ='[23]AD ESFERA'!C6 -> 0 | CJ6: ='[23]AD ESFERA'!D6 -> 0 | CK6: ='[23]AD ESFERA'!E6 -> 0 | CL6: ='[24]AD ESFERA'!B6 -> 203080756 | CM6: ='[24]AD ESFERA'!C6 -> 0 | CN6: ='[24]AD ESFERA'!D6 -> 0 | CO6: ='[24]AD ESFERA'!E6 -> 0 | CP6: ='[25]AD ESFERA'!B6 -> 207832253 | CQ6: ='[25]AD ESFERA'!C6 -> 0 | CR6: ='[25]AD ESFERA'!D6 -> 0 | CS6: ='[25]AD ESFERA'!E6 -> 0 | CT6: ='[26]AD ESFERA'!B6 -> 212583750 | CU6: ='[26]AD ESFERA'!C6 -> 0 | CV6: ='[26]AD ESFERA'!D6 -> 0 | CW6: ='[26]AD ESFERA'!E6 -> 0
A7: TOTAL | B7: ='[2]AD ESFERA'!B7 -> 367.44515 | C7: ='[2]AD ESFERA'!C7 -> 30.559889 | D7: ='[2]AD ESFERA'!D7 -> 100 | E7: ='[2]AD ESFERA'!E7 -> 2118.4702 | F7: ='[3]AD ESFERA'!B7 -> 421.64663 | G7: ='[3]AD ESFERA'!C7 -> 32.045984 | H7: ='[3]AD ESFERA'!D7 -> 100 | I7: ='[3]AD ESFERA'!E7 -> 2430.9637 | J7: ='[4]AD ESFERA'!B7 -> 495.42481 | K7: ='[4]AD ESFERA'!C7 -> 33.277078 | L7: ='[4]AD ESFERA'!D7 -> 100 | M7: ='[4]AD ESFERA'!E7 -> 2778.9745 | N7: ='[5]AD ESFERA'!B7 -> 560.01487 | O7: ='[5]AD ESFERA'!C7 -> 32.597856 | P7: ='[5]AD ESFERA'!D7 -> 100 | Q7: ='[5]AD ESFERA'!E7 -> 3100.5295 | R7: ='[6]AD ESFERA'!B7 -> 658.25296 | S7: ='[6]AD ESFERA'!C7 -> 33.622915 | T7: ='[6]AD ESFERA'!D7 -> 100 | U7: ='[6]AD ESFERA'!E7 -> 3598.7513 | V7: ='[7]AD ESFERA'!B7 -> 754.18429 | W7: ='[7]AD ESFERA'!C7 -> 34.74567 | X7: ='[7]AD ESFERA'!D7 -> 100 | Y7: ='[7]AD ESFERA'!E7 -> 4073.3514 | Z7: ='[8]AD ESFERA'!B7 -> 829.53577 | AA7: ='[8]AD ESFERA'!C7 -> 34.428428 | AB7: ='[8]AD ESFERA'!D7 -> 100 | AC7: ='[8]AD ESFERA'!E7 -> 4428.0842 | AD7: ='[9]AD ESFERA'!B7 -> 940.81948 | AE7: ='[9]AD ESFERA'!C7 -> 34.585607 | AF7: ='[9]AD ESFERA'!D7 -> 100 | AG7: ='[9]AD ESFERA'!E7 -> 4965.7226 | AH7: ='[10]AD ESFERA'!B7 -> 1080.8859 | AI7: ='[10]AD ESFERA'!C7 -> 34.757375 | AJ7: ='[10]AD ESFERA'!D7 -> 100 | AK7: ='[10]AD ESFERA'!E7 -> 5643.3568 | AL7: ='[11]AD ESFERA'!B7 -> 1105.3741 | AM7: ='[11]AD ESFERA'!C7 -> 33.164151 | AN7: ='[11]AD ESFERA'!D7 -> 100 | AO7: ='[11]AD ESFERA'!E7 -> 5711.2298 | AP7: ='[12]AD ESFERA'!B7 -> 1291.3621 | AQ7: ='[12]AD ESFERA'!C7 -> 33.232448 | AR7: ='[12]AD ESFERA'!D7 -> 100 | AS7: ='[12]AD ESFERA'!E7 -> 6605.5071 | AT7: ='[13]AD ESFERA'!B7 -> 1491.6039 | AU7: ='[13]AD ESFERA'!C7 -> 34.083038 | AV7: ='[13]AD ESFERA'!D7 -> 100 | AW7: ='[13]AD ESFERA'!E7 -> 7556.3651 | AX7: ='[14]AD ESFERA'!B7 -> 1638.1111 | AY7: ='[14]AD ESFERA'!C7 -> 34.022696 | AZ7: ='[14]AD ESFERA'!D7 -> 100 | BA7: ='[14]AD ESFERA'!E7 -> 8221.6969 | BB7: ='[15]AD ESFERA'!B7 -> 1792.2461 | BC7: ='[15]AD ESFERA'!C7 -> 33.615419 | BD7: ='[15]AD ESFERA'!D7 -> 100 | BE7: ='[15]AD ESFERA'!E7 -> 8915.1961 | BF7: ='[16]AD ESFERA'!B7 -> 1899.7813 | BG7: ='[16]AD ESFERA'!C7 -> 32.874143 | BH7: ='[16]AD ESFERA'!D7 -> 100 | BI7: ='[16]AD ESFERA'!E7 -> 9369.2102 | BJ7: ='[17]AD ESFERA'!B7 -> 1969.031 | BK7: ='[17]AD ESFERA'!C7 -> 32.840243 | BL7: ='[17]AD ESFERA'!D7 -> 100 | BM7: ='[17]AD ESFERA'!E7 -> 9630.8376 | BN7: ='[18]AD ESFERA'!B7 -> 2086.1565 | BO7: ='[18]AD ESFERA'!C7 -> 33.286872 | BP7: ='[18]AD ESFERA'!D7 -> 100 | BQ7: ='[18]AD ESFERA'!E7 -> 10122.972 | BR7: ='[19]AD ESFERA'!B7 -> 2203.4045 | BS7: ='[19]AD ESFERA'!C7 -> 33.620039 | BT7: ='[19]AD ESFERA'!D7 -> 100 | BU7: ='[19]AD ESFERA'!E7 -> 10610.588 | BV7: ='[20]AD ESFERA'!B7 -> 2372.7995 | BW7: ='[20]AD ESFERA'!C7 -> 34.442428 | BX7: ='[20]AD ESFERA'!D7 -> 100 | BY7: ='[20]AD ESFERA'!E7 -> 11380.612 | BZ7: ='[21]AD ESFERA'!B7 -> 2496.9243 | CA7: ='[21]AD ESFERA'!C7 -> 33.791853 | CB7: ='[21]AD ESFERA'!D7 -> 100 | CC7: ='[21]AD ESFERA'!E7 -> 11881.791 | CD7: ='[22]AD ESFERA'!B7 -> 2451.5573 | CE7: ='[22]AD ESFERA'!C7 -> 32.216651 | CF7: ='[22]AD ESFERA'!D7 -> 100 | CG7: ='[22]AD ESFERA'!E7 -> 11577.291 | CH7: ='[23]AD ESFERA'!B7 -> 3060.9656 | CI7: ='[23]AD ESFERA'!C7 -> 34.397792 | CJ7: ='[23]AD ESFERA'!D7 -> 100 | CK7: ='[23]AD ESFERA'!E7 -> 14349.332 | CL7: ='[24]AD ESFERA'!B7 -> 3518.4966 | CM7: ='[24]AD ESFERA'!C7 -> 34.906843 | CN7: ='[24]AD ESFERA'!D7 -> 100 | CO7: ='[24]AD ESFERA'!E7 -> 17325.603 | CP7: ='[25]AD ESFERA'!B7 -> 3783.9875 | CQ7: ='[25]AD ESFERA'!C7 -> 34.577982 | CR7: ='[25]AD ESFERA'!D7 -> 100 | CS7: ='[25]AD ESFERA'!E7 -> 18206.931 | CT7: ='[26]AD ESFERA'!B7 -> 4222.222 | CU7: ='[26]AD ESFERA'!C7 -> 35.949992 | CV7: ='[26]AD ESFERA'!D7 -> 100 | CW7: ='[26]AD ESFERA'!E7 -> 19861.452
B8: ='[2]AD ESFERA'!B8 -> 0 | C8: ='[2]AD ESFERA'!C8 -> 0 | D8: ='[2]AD ESFERA'!D8 -> 0 | E8: ='[2]AD ESFERA'!E8 -> 0 | F8: ='[3]AD ESFERA'!B8 -> 0 | G8: ='[3]AD ESFERA'!C8 -> 0 | H8: ='[3]AD ESFERA'!D8 -> 0 | I8: ='[3]AD ESFERA'!E8 -> 0 | J8: ='[4]AD ESFERA'!B8 -> 0 | K8: ='[4]AD ESFERA'!C8 -> 0 | L8: ='[4]AD ESFERA'!D8 -> 0 | M8: ='[4]AD ESFERA'!E8 -> 0 | N8: ='[5]AD ESFERA'!B8 -> 0 | O8: ='[5]AD ESFERA'!C8 -> 0 | P8: ='[5]AD ESFERA'!D8 -> 0 | Q8: ='[5]AD ESFERA'!E8 -> 0 | R8: ='[6]AD ESFERA'!B8 -> 0 | S8: ='[6]AD ESFERA'!C8 -> 0 | T8: ='[6]AD ESFERA'!D8 -> 0 | U8: ='[6]AD ESFERA'!E8 -> 0 | V8: ='[7]AD ESFERA'!B8 -> 0 | W8: ='[7]AD ESFERA'!C8 -> 0 | X8: ='[7]AD ESFERA'!D8 -> 0 | Y8: ='[7]AD ESFERA'!E8 -> 0 | Z8: ='[8]AD ESFERA'!B8 -> 0 | AA8: ='[8]AD ESFERA'!C8 -> 0 | AB8: ='[8]AD ESFERA'!D8 -> 0 | AC8: ='[8]AD ESFERA'!E8 -> 0 | AD8: ='[9]AD ESFERA'!B8 -> 0 | AE8: ='[9]AD ESFERA'!C8 -> 0 | AF8: ='[9]AD ESFERA'!D8 -> 0 | AG8: ='[9]AD ESFERA'!E8 -> 0 | AH8: ='[10]AD ESFERA'!B8 -> 0 | AI8: ='[10]AD ESFERA'!C8 -> 0 | AJ8: ='[10]AD ESFERA'!D8 -> 0 | AK8: ='[10]AD ESFERA'!E8 -> 0 | AL8: ='[11]AD ESFERA'!B8 -> 0 | AM8: ='[11]AD ESFERA'!C8 -> 0 | AN8: ='[11]AD ESFERA'!D8 -> 0 | AO8: ='[11]AD ESFERA'!E8 -> 0 | AP8: ='[12]AD ESFERA'!B8 -> 0 | AQ8: ='[12]AD ESFERA'!C8 -> 0 | AR8: ='[12]AD ESFERA'!D8 -> 0 | AS8: ='[12]AD ESFERA'!E8 -> 0 | AT8: ='[13]AD ESFERA'!B8 -> 0 | AU8: ='[13]AD ESFERA'!C8 -> 0 | AV8: ='[13]AD ESFERA'!D8 -> 0 | AW8: ='[13]AD ESFERA'!E8 -> 0 | AX8: ='[14]AD ESFERA'!B8 -> 0 | AY8: ='[14]AD ESFERA'!C8 -> 0 | AZ8: ='[14]AD ESFERA'!D8 -> 0 | BA8: ='[14]AD ESFERA'!E8 -> 0 | BB8: ='[15]AD ESFERA'!B8 -> 0 | BC8: ='[15]AD ESFERA'!C8 -> 0 | BD8: ='[15]AD ESFERA'!D8 -> 0 | BE8: ='[15]AD ESFERA'!E8 -> 0 | BF8: ='[16]AD ESFERA'!B8 -> 0 | BG8: ='[16]AD ESFERA'!C8 -> 0 | BH8: ='[16]AD ESFERA'!D8 -> 0 | BI8: ='[16]AD ESFERA'!E8 -> 0 | BJ8: ='[17]AD ESFERA'!B8 -> 0 | BK8: ='[17]AD ESFERA'!C8 -> 0 | BL8: ='[17]AD ESFERA'!D8 -> 0 | BM8: ='[17]AD ESFERA'!E8 -> 0 | BN8: ='[18]AD ESFERA'!B8 -> 0 | BO8: ='[18]AD ESFERA'!C8 -> 0 | BP8: ='[18]AD ESFERA'!D8 -> 0 | BQ8: ='[18]AD ESFERA'!E8 -> 0 | BR8: ='[19]AD ESFERA'!B8 -> 0 | BS8: ='[19]AD ESFERA'!C8 -> 0 | BT8: ='[19]AD ESFERA'!D8 -> 0 | BU8: ='[19]AD ESFERA'!E8 -> 0 | BV8: ='[20]AD ESFERA'!B8 -> 0 | BW8: ='[20]AD ESFERA'!C8 -> 0 | BX8: ='[20]AD ESFERA'!D8 -> 0 | BY8: ='[20]AD ESFERA'!E8 -> 0 | BZ8: ='[21]AD ESFERA'!B8 -> 0 | CA8: ='[21]AD ESFERA'!C8 -> 0 | CB8: ='[21]AD ESFERA'!D8 -> 0 | CC8: ='[21]AD ESFERA'!E8 -> 0 | CD8: ='[22]AD ESFERA'!B8 -> 0 | CE8: ='[22]AD ESFERA'!C8 -> 0 | CF8: ='[22]AD ESFERA'!D8 -> 0 | CG8: ='[22]AD ESFERA'!E8 -> 0 | CH8: ='[23]AD ESFERA'!B8 -> 0 | CI8: ='[23]AD ESFERA'!C8 -> 0 | CJ8: ='[23]AD ESFERA'!D8 -> 0 | CK8: ='[23]AD ESFERA'!E8 -> 0 | CL8: ='[24]AD ESFERA'!B8 -> 0 | CM8: ='[24]AD ESFERA'!C8 -> 0 | CN8: ='[24]AD ESFERA'!D8 -> 0 | CO8: ='[24]AD ESFERA'!E8 -> 0 | CP8: ='[25]AD ESFERA'!B8 -> 0 | CQ8: ='[25]AD ESFERA'!C8 -> 0 | CR8: ='[25]AD ESFERA'!D8 -> 0 | CS8: ='[25]AD ESFERA'!E8 -> 0 | CT8: ='[26]AD ESFERA'!B8 -> 0 | CU8: ='[26]AD ESFERA'!C8 -> 0 | CV8: ='[26]AD ESFERA'!D8 -> 0 | CW8: ='[26]AD ESFERA'!E8 -> 0
A9: UNIÃO | B9: ='[2]AD ESFERA'!B9 -> 245.03204 | C9: ='[2]AD ESFERA'!C9 -> 20.378966 | D9: ='[2]AD ESFERA'!D9 -> 66.685339 | E9: ='[2]AD ESFERA'!E9 -> 1412.709 | F9: ='[3]AD ESFERA'!B9 -> 281.98373 | G9: ='[3]AD ESFERA'!C9 -> 21.431325 | H9: ='[3]AD ESFERA'!D9 -> 66.876788 | I9: ='[3]AD ESFERA'!E9 -> 1625.7505 | J9: ='[4]AD ESFERA'!B9 -> 337.12695 | K9: ='[4]AD ESFERA'!C9 -> 22.644404 | L9: ='[4]AD ESFERA'!D9 -> 68.048055 | M9: ='[4]AD ESFERA'!E9 -> 1891.0381 | N9: ='[5]AD ESFERA'!B9 -> 377.00184 | O9: ='[5]AD ESFERA'!C9 -> 21.944867 | P9: ='[5]AD ESFERA'!D9 -> 67.319971 | Q9: ='[5]AD ESFERA'!E9 -> 2087.2755 | R9: ='[6]AD ESFERA'!B9 -> 443.44386 | S9: ='[6]AD ESFERA'!C9 -> 22.650677 | T9: ='[6]AD ESFERA'!D9 -> 67.366786 | U9: ='[6]AD ESFERA'!E9 -> 2424.3631 | V9: ='[7]AD ESFERA'!B9 -> 515.78386 | W9: ='[7]AD ESFERA'!C9 -> 23.762435 | X9: ='[7]AD ESFERA'!D9 -> 68.389631 | Y9: ='[7]AD ESFERA'!E9 -> 2785.75 | Z9: ='[8]AD ESFERA'!B9 -> 564.59653 | AA9: ='[8]AD ESFERA'!C9 -> 23.43259 | AB9: ='[8]AD ESFERA'!D9 -> 68.061747 | AC9: ='[8]AD ESFERA'!E9 -> 3013.8315 | AD9: ='[9]AD ESFERA'!B9 -> 646.5957 | AE9: ='[9]AD ESFERA'!C9 -> 23.769602 | AF9: ='[9]AD ESFERA'!D9 -> 68.726862 | AG9: ='[9]AD ESFERA'!E9 -> 3412.7853 | AH9: ='[10]AD ESFERA'!B9 -> 738.74107 | AI9: ='[10]AD ESFERA'!C9 -> 23.755237 | AJ9: ='[10]AD ESFERA'!D9 -> 68.345889 | AK9: ='[10]AD ESFERA'!E9 -> 3857.0024 | AL9: ='[11]AD ESFERA'!B9 -> 745.83668 | AM9: ='[11]AD ESFERA'!C9 -> 22.377076 | AN9: ='[11]AD ESFERA'!D9 -> 67.47369 | AO9: ='[11]AD ESFERA'!E9 -> 3853.5775 | AP9: ='[12]AD ESFERA'!B9 -> 868.73679 | AQ9: ='[12]AD ESFERA'!C9 -> 22.356433 | AR9: ='[12]AD ESFERA'!D9 -> 67.272905 | AS9: ='[12]AD ESFERA'!E9 -> 4443.7165 | AT9: ='[13]AD ESFERA'!B9 -> 1017.0071 | AU9: ='[13]AD ESFERA'!C9 -> 23.238536 | AV9: ='[13]AD ESFERA'!D9 -> 68.182114 | AW9: ='[13]AD ESFERA'!E9 -> 5152.0895 | AX9: ='[14]AD ESFERA'!B9 -> 1111.1552 | AY9: ='[14]AD ESFERA'!C9 -> 23.078101 | AZ9: ='[14]AD ESFERA'!D9 -> 67.831488 | BA9: ='[14]AD ESFERA'!E9 -> 5576.8994 | BB9: ='[15]AD ESFERA'!B9 -> 1208.3874 | BC9: ='[15]AD ESFERA'!C9 -> 22.66455 | BD9: ='[15]AD ESFERA'!D9 -> 67.423076 | BE9: ='[15]AD ESFERA'!E9 -> 6010.8995 | BF9: ='[16]AD ESFERA'!B9 -> 1266.193 | BG9: ='[16]AD ESFERA'!C9 -> 21.910422 | BH9: ='[16]AD ESFERA'!D9 -> 66.649409 | BI9: ='[16]AD ESFERA'!E9 -> 6244.5232 | BJ9: ='[17]AD ESFERA'!B9 -> 1299.1238 | BK9: ='[17]AD ESFERA'!C9 -> 21.667278 | BL9: ='[17]AD ESFERA'!D9 -> 65.977824 | BM9: ='[17]AD ESFERA'!E9 -> 6354.2171 | BN9: ='[18]AD ESFERA'!B9 -> 1374.5454 | BO9: ='[18]AD ESFERA'!C9 -> 21.932351 | BP9: ='[18]AD ESFERA'!D9 -> 65.888892 | BQ9: ='[18]AD ESFERA'!E9 -> 6669.9138 | BR9: ='[19]AD ESFERA'!B9 -> 1439.7472 | BS9: ='[19]AD ESFERA'!C9 -> 21.967986 | BT9: ='[19]AD ESFERA'!D9 -> 65.341941 | BU9: ='[19]AD ESFERA'!E9 -> 6933.1638 | BV9: ='[20]AD ESFERA'!B9 -> 1550.492 | BW9: ='[20]AD ESFERA'!C9 -> 22.506204 | BX9: ='[20]AD ESFERA'!D9 -> 65.344418 | BY9: ='[20]AD ESFERA'!E9 -> 7436.5946 | BZ9: ='[21]AD ESFERA'!B9 -> 1610.6225 | CA9: ='[21]AD ESFERA'!C9 -> 21.797184 | CB9: ='[21]AD ESFERA'!D9 -> 64.504259 | CC9: ='[21]AD ESFERA'!E9 -> 7664.2615 | CD9: ='[22]AD ESFERA'!B9 -> 1541.6976 | CE9: ='[22]AD ESFERA'!C9 -> 20.259911 | CF9: ='[22]AD ESFERA'!D9 -> 62.886457 | CG9: ='[22]AD ESFERA'!E9 -> 7280.5484 | CH9: ='[23]AD ESFERA'!B9 -> 1962.2415 | CI9: ='[23]AD ESFERA'!C9 -> 22.050811 | CJ9: ='[23]AD ESFERA'!D9 -> 64.105309 | CK9: ='[23]AD ESFERA'!E9 -> 9198.6836 | CL9: ='[24]AD ESFERA'!B9 -> 2292.7229 | CM9: ='[24]AD ESFERA'!C9 -> 22.745998 | CN9: ='[24]AD ESFERA'!D9 -> 65.162002 | CO9: ='[24]AD ESFERA'!E9 -> 11289.71 | CP9: ='[25]AD ESFERA'!B9 -> 2470.2827 | CQ9: ='[25]AD ESFERA'!C9 -> 22.573381 | CR9: ='[25]AD ESFERA'!D9 -> 65.282528 | CS9: ='[25]AD ESFERA'!E9 -> 11885.945 | CT9: ='[26]AD ESFERA'!B9 -> 2735.2139 | CU9: ='[26]AD ESFERA'!C9 -> 23.288903 | CV9: ='[26]AD ESFERA'!D9 -> 64.781386 | CW9: ='[26]AD ESFERA'!E9 -> 12866.524
A10: Impostos | B10: ='[2]AD ESFERA'!B10 -> 77.35753 | C10: ='[2]AD ESFERA'!C10 -> 6.4337155 | D10: ='[2]AD ESFERA'!D10 -> 21.05281 | E10: ='[2]AD ESFERA'!E10 -> 445.99751 | F10: ='[3]AD ESFERA'!B10 -> 90.128571 | G10: ='[3]AD ESFERA'!C10 -> 6.8499509 | H10: ='[3]AD ESFERA'!D10 -> 21.37538 | I10: ='[3]AD ESFERA'!E10 -> 519.62773 | J10: ='[4]AD ESFERA'!B10 -> 106.15866 | K10: ='[4]AD ESFERA'!C10 -> 7.130547 | L10: ='[4]AD ESFERA'!D10 -> 21.427804 | M10: ='[4]AD ESFERA'!E10 -> 595.47321 | N10: ='[5]AD ESFERA'!B10 -> 113.1202 | O10: ='[5]AD ESFERA'!C10 -> 6.5846036 | P10: ='[5]AD ESFERA'!D10 -> 20.199499 | Q10: ='[5]AD ESFERA'!E10 -> 626.29142 | R10: ='[6]AD ESFERA'!B10 -> 126.10838 | S10: ='[6]AD ESFERA'!C10 -> 6.4414924 | T10: ='[6]AD ESFERA'!D10 -> 19.158043 | U10: ='[6]AD ESFERA'!E10 -> 689.45031 | V10: ='[7]AD ESFERA'!B10 -> 151.80948 | W10: ='[7]AD ESFERA'!C10 -> 6.9939432 | X10: ='[7]AD ESFERA'!D10 -> 20.128964 | Y10: ='[7]AD ESFERA'!E10 -> 819.92342 | Z10: ='[8]AD ESFERA'!B10 -> 165.84367 | AA10: ='[8]AD ESFERA'!C10 -> 6.883051 | AB10: ='[8]AD ESFERA'!D10 -> 19.992347 | AC10: ='[8]AD ESFERA'!E10 -> 885.27799 | AD10: ='[9]AD ESFERA'!B10 -> 195.54627 | AE10: ='[9]AD ESFERA'!C10 -> 7.1885061 | AF10: ='[9]AD ESFERA'!D10 -> 20.784675 | AG10: ='[9]AD ESFERA'!E10 -> 1032.1093 | AH10: ='[10]AD ESFERA'!B10 -> 248.65945 | AI10: ='[10]AD ESFERA'!C10 -> 7.9959871 | AJ10: ='[10]AD ESFERA'!D10 -> 23.005153 | AK10: ='[10]AD ESFERA'!E10 -> 1298.2628 | AL10: ='[11]AD ESFERA'!B10 -> 235.60912 | AM10: ='[11]AD ESFERA'!C10 -> 7.0688978 | AN10: ='[11]AD ESFERA'!D10 -> 21.314877 | AO10: ='[11]AD ESFERA'!E10 -> 1217.3416 | AP10: ='[12]AD ESFERA'!B10 -> 275.8912 | AQ10: ='[12]AD ESFERA'!C10 -> 7.0998986 | AR10: ='[12]AD ESFERA'!D10 -> 21.364356 | AS10: ='[12]AD ESFERA'!E10 -> 1411.2241 | AT10: ='[13]AD ESFERA'!B10 -> 331.50074 | AU10: ='[13]AD ESFERA'!C10 -> 7.5747669 | AV10: ='[13]AD ESFERA'!D10 -> 22.224448 | AW10: ='[13]AD ESFERA'!E10 -> 1679.3604 | AX10: ='[14]AD ESFERA'!B10 -> 340.90148 | AY10: ='[14]AD ESFERA'!C10 -> 7.0803421 | AZ10: ='[14]AD ESFERA'!D10 -> 20.810644 | BA10: ='[14]AD ESFERA'!E10 -> 1710.9881 | BB10: ='[15]AD ESFERA'!B10 -> 369.1948 | BC10: ='[15]AD ESFERA'!C10 -> 6.9246284 | BD10: ='[15]AD ESFERA'!D10 -> 20.59956 | BE10: ='[15]AD ESFERA'!E10 -> 1836.4912 | BF10: ='[16]AD ESFERA'!B10 -> 393.70669 | BG10: ='[16]AD ESFERA'!C10 -> 6.8127686 | BH10: ='[16]AD ESFERA'!D10 -> 20.723791 | BI10: ='[16]AD ESFERA'!E10 -> 1941.6555 | BJ10: ='[17]AD ESFERA'!B10 -> 417.30468 | BK10: ='[17]AD ESFERA'!C10 -> 6.9599651 | BL10: ='[17]AD ESFERA'!D10 -> 21.193404 | BM10: ='[17]AD ESFERA'!E10 -> 2041.1023 | BN10: ='[18]AD ESFERA'!B10 -> 441.73014 | BO10: ='[18]AD ESFERA'!C10 -> 7.0482797 | BP10: ='[18]AD ESFERA'!D10 -> 21.174353 | BQ10: ='[18]AD ESFERA'!E10 -> 2143.4737 | BR10: ='[19]AD ESFERA'!B10 -> 467.76634 | BS10: ='[19]AD ESFERA'!C10 -> 7.1372836 | BT10: ='[19]AD ESFERA'!D10 -> 21.229255 | BU10: ='[19]AD ESFERA'!E10 -> 2252.5486 | BV10: ='[20]AD ESFERA'!B10 -> 483.28507 | BW10: ='[20]AD ESFERA'!C10 -> 7.015136 | BX10: ='[20]AD ESFERA'!D10 -> 20.367716 | BY10: ='[20]AD ESFERA'!E10 -> 2317.9707 | BZ10: ='[21]AD ESFERA'!B10 -> 525.88096 | CA10: ='[21]AD ESFERA'!C10 -> 7.1169528 | CB10: ='[21]AD ESFERA'!D10 -> 21.06115 | CC10: ='[21]AD ESFERA'!E10 -> 2502.4419 | CD10: ='[22]AD ESFERA'!B10 -> 500.00671 | CE10: ='[22]AD ESFERA'!C10 -> 6.5707384 | CF10: ='[22]AD ESFERA'!D10 -> 20.395473 | CG10: ='[22]AD ESFERA'!E10 -> 2361.2433 | CH10: ='[23]AD ESFERA'!B10 -> 689.60087 | CI10: ='[23]AD ESFERA'!C10 -> 7.7494328 | CJ10: ='[23]AD ESFERA'!D10 -> 22.528867 | CK10: ='[23]AD ESFERA'!E10 -> 3232.7419 | CL10: ='[24]AD ESFERA'!B10 -> 832.28759 | CM10: ='[24]AD ESFERA'!C10 -> 8.2570867 | CN10: ='[24]AD ESFERA'!D10 -> 23.654637 | CO10: ='[24]AD ESFERA'!E10 -> 4098.3085 | CP10: ='[25]AD ESFERA'!B10 -> 913.98154 | CQ10: ='[25]AD ESFERA'!C10 -> 8.3519402 | CR10: ='[25]AD ESFERA'!D10 -> 24.153926 | CS10: ='[25]AD ESFERA'!E10 -> 4397.6887 | CT10: ='[26]AD ESFERA'!B10 -> 994.87939 | CU10: ='[26]AD ESFERA'!C10 -> 8.4708731 | CV10: ='[26]AD ESFERA'!D10 -> 23.562934 | CW10: ='[26]AD ESFERA'!E10 -> 4679.9409
A11: Contribuições Sociais | B11: ='[2]AD ESFERA'!B11 -> 82.011453 | C11: ='[2]AD ESFERA'!C11 -> 6.8207757 | D11: ='[2]AD ESFERA'!D11 -> 22.319373 | E11: ='[2]AD ESFERA'!E11 -> 472.82926 | F11: ='[3]AD ESFERA'!B11 -> 95.601597 | G11: ='[3]AD ESFERA'!C11 -> 7.2659117 | H11: ='[3]AD ESFERA'!D11 -> 22.673393 | I11: ='[3]AD ESFERA'!E11 -> 551.18195 | J11: ='[4]AD ESFERA'!B11 -> 111.83499 | K11: ='[4]AD ESFERA'!C11 -> 7.5118192 | L11: ='[4]AD ESFERA'!D11 -> 22.573554 | M11: ='[4]AD ESFERA'!E11 -> 627.31331 | N11: ='[5]AD ESFERA'!B11 -> 130.34994 | O11: ='[5]AD ESFERA'!C11 -> 7.5875281 | P11: ='[5]AD ESFERA'!D11 -> 23.276157 | Q11: ='[5]AD ESFERA'!E11 -> 721.6841 | R11: ='[6]AD ESFERA'!B11 -> 164.50135 | S11: ='[6]AD ESFERA'!C11 -> 8.4025673 | T11: ='[6]AD ESFERA'!D11 -> 24.990597 | U11: ='[6]AD ESFERA'!E11 -> 899.34945 | V11: ='[7]AD ESFERA'!B11 -> 184.08687 | W11: ='[7]AD ESFERA'!C11 -> 8.4809795 | X11: ='[7]AD ESFERA'!D11 -> 24.408738 | Y11: ='[7]AD ESFERA'!E11 -> 994.25367 | Z11: ='[8]AD ESFERA'!B11 -> 196.42126 | AA11: ='[8]AD ESFERA'!C11 -> 8.1521203 | AB11: ='[8]AD ESFERA'!D11 -> 23.678456 | AC11: ='[8]AD ESFERA'!E11 -> 1048.502 | AD11: ='[9]AD ESFERA'!B11 -> 223.50805 | AE11: ='[9]AD ESFERA'!C11 -> 8.2164134 | AF11: ='[9]AD ESFERA'!D11 -> 23.756742 | AG11: ='[9]AD ESFERA'!E11 -> 1179.6939 | AH11: ='[10]AD ESFERA'!B11 -> 223.52545 | AI11: ='[10]AD ESFERA'!C11 -> 7.1877687 | AJ11: ='[10]AD ESFERA'!D11 -> 20.679838 | AK11: ='[10]AD ESFERA'!E11 -> 1167.037 | AL11: ='[11]AD ESFERA'!B11 -> 224.19242 | AM11: ='[11]AD ESFERA'!C11 -> 6.7263666 | AN11: ='[11]AD ESFERA'!D11 -> 20.282041 | AO11: ='[11]AD ESFERA'!E11 -> 1158.3539 | AP11: ='[12]AD ESFERA'!B11 -> 265.08427 | AQ11: ='[12]AD ESFERA'!C11 -> 6.8217887 | AR11: ='[12]AD ESFERA'!D11 -> 20.527494 | AS11: ='[12]AD ESFERA'!E11 -> 1355.9451 | AT11: ='[13]AD ESFERA'!B11 -> 303.39885 | AU11: ='[13]AD ESFERA'!C11 -> 6.9326409 | AV11: ='[13]AD ESFERA'!D11 -> 20.340443 | AW11: ='[13]AD ESFERA'!E11 -> 1536.9981 | AX11: ='[14]AD ESFERA'!B11 -> 325.12107 | AY11: ='[14]AD ESFERA'!C11 -> 6.7525915 | AZ11: ='[14]AD ESFERA'!D11 -> 19.847315 | BA11: ='[14]AD ESFERA'!E11 -> 1631.7861 | BB11: ='[15]AD ESFERA'!B11 -> 360.11836 | BC11: ='[15]AD ESFERA'!C11 -> 6.7543903 | BD11: ='[15]AD ESFERA'!D11 -> 20.093131 | BE11: ='[15]AD ESFERA'!E11 -> 1791.3421 | BF11: ='[16]AD ESFERA'!B11 -> 369.95556 | BG11: ='[16]AD ESFERA'!C11 -> 6.4017749 | BH11: ='[16]AD ESFERA'!D11 -> 19.473587 | BI11: ='[16]AD ESFERA'!E11 -> 1824.5213 | BJ11: ='[17]AD ESFERA'!B11 -> 380.11726 | BK11: ='[17]AD ESFERA'!C11 -> 6.3397393 | BL11: ='[17]AD ESFERA'!D11 -> 19.304788 | BM11: ='[17]AD ESFERA'!E11 -> 1859.2128 | BN11: ='[18]AD ESFERA'!B11 -> 386.03047 | BO11: ='[18]AD ESFERA'!C11 -> 6.1595315 | BP11: ='[18]AD ESFERA'!D11 -> 18.504387 | BQ11: ='[18]AD ESFERA'!E11 -> 1873.1938 | BR11: ='[19]AD ESFERA'!B11 -> 407.32041 | BS11: ='[19]AD ESFERA'!C11 -> 6.2149861 | BT11: ='[19]AD ESFERA'!D11 -> 18.485957 | BU11: ='[19]AD ESFERA'!E11 -> 1961.4687 | BV11: ='[20]AD ESFERA'!B11 -> 451.00779 | BW11: ='[20]AD ESFERA'!C11 -> 6.5466143 | BX11: ='[20]AD ESFERA'!D11 -> 19.007412 | BY11: ='[20]AD ESFERA'!E11 -> 2163.1598 | BZ11: ='[21]AD ESFERA'!B11 -> 446.5198 | CA11: ='[21]AD ESFERA'!C11 -> 6.0429272 | CB11: ='[21]AD ESFERA'!D11 -> 17.882793 | CC11: ='[21]AD ESFERA'!E11 -> 2124.7962 | CD11: ='[22]AD ESFERA'!B11 -> 419.90937 | CE11: ='[22]AD ESFERA'!C11 -> 5.5181551 | CF11: ='[22]AD ESFERA'!D11 -> 17.12827 | CG11: ='[22]AD ESFERA'!E11 -> 1982.9898 | CH11: ='[23]AD ESFERA'!B11 -> 527.06352 | CI11: ='[23]AD ESFERA'!C11 -> 5.9229092 | CJ11: ='[23]AD ESFERA'!D11 -> 17.218865 | CK11: ='[23]AD ESFERA'!E11 -> 2470.792 | CL11: ='[24]AD ESFERA'!B11 -> 585.32522 | CM11: ='[24]AD ESFERA'!C11 -> 5.8069845 | CN11: ='[24]AD ESFERA'!D11 -> 16.635662 | CO11: ='[24]AD ESFERA'!E11 -> 2882.2289 | CP11: ='[25]AD ESFERA'!B11 -> 656.81182 | CQ11: ='[25]AD ESFERA'!C11 -> 6.0019297 | CR11: ='[25]AD ESFERA'!D11 -> 17.357663 | CS11: ='[25]AD ESFERA'!E11 -> 3160.2978 | CT11: ='[26]AD ESFERA'!B11 -> 710.86421 | CU11: ='[26]AD ESFERA'!C11 -> 6.0526336 | CV11: ='[26]AD ESFERA'!D11 -> 16.836258 | CW11: ='[26]AD ESFERA'!E11 -> 3343.9254
A12: Previdência Social | B12: ='[2]AD ESFERA'!B12 -> 55.712837 | C12: ='[2]AD ESFERA'!C12 -> 4.6335573 | D12: ='[2]AD ESFERA'!D12 -> 15.162219 | E12: ='[2]AD ESFERA'!E12 -> 321.20708 | F12: ='[3]AD ESFERA'!B12 -> 62.433582 | G12: ='[3]AD ESFERA'!C12 -> 4.7450765 | H12: ='[3]AD ESFERA'!D12 -> 14.807087 | I12: ='[3]AD ESFERA'!E12 -> 359.9549 | J12: ='[4]AD ESFERA'!B12 -> 69.251554 | K12: ='[4]AD ESFERA'!C12 -> 4.6515421 | L12: ='[4]AD ESFERA'!D12 -> 13.978217 | M12: ='[4]AD ESFERA'!E12 -> 388.45108 | N12: ='[5]AD ESFERA'!B12 -> 79.375176 | O12: ='[5]AD ESFERA'!C12 -> 4.6203426 | P12: ='[5]AD ESFERA'!D12 -> 14.173762 | Q12: ='[5]AD ESFERA'!E12 -> 439.46168 | R12: ='[6]AD ESFERA'!B12 -> 93.327546 | S12: ='[6]AD ESFERA'!C12 -> 4.7670795 | T12: ='[6]AD ESFERA'!D12 -> 14.178067 | U12: ='[6]AD ESFERA'!E12 -> 510.23338 | V12: ='[7]AD ESFERA'!B12 -> 106.6517 | W12: ='[7]AD ESFERA'!C12 -> 4.9135005 | X12: ='[7]AD ESFERA'!D12 -> 14.141332 | Y12: ='[7]AD ESFERA'!E12 -> 576.02614 | Z12: ='[8]AD ESFERA'!B12 -> 121.05943 | AA12: ='[8]AD ESFERA'!C12 -> 5.0243597 | AB12: ='[8]AD ESFERA'!D12 -> 14.593637 | AC12: ='[8]AD ESFERA'!E12 -> 646.21852 | AD12: ='[9]AD ESFERA'!B12 -> 138.11807 | AE12: ='[9]AD ESFERA'!C12 -> 5.0773794 | AF12: ='[9]AD ESFERA'!D12 -> 14.680614 | AG12: ='[9]AD ESFERA'!E12 -> 728.99855 | AH12: ='[10]AD ESFERA'!B12 -> 158.09568 | AI12: ='[10]AD ESFERA'!C12 -> 5.0837844 | AJ12: ='[10]AD ESFERA'!D12 -> 14.626491 | AK12: ='[10]AD ESFERA'!E12 -> 825.42509 | AL12: ='[11]AD ESFERA'!B12 -> 178.24284 | AM12: ='[11]AD ESFERA'!C12 -> 5.3477574 | AN12: ='[11]AD ESFERA'!D12 -> 16.125115 | AO12: ='[11]AD ESFERA'!E12 -> 920.94237 | AP12: ='[12]AD ESFERA'!B12 -> 210.4037 | AQ12: ='[12]AD ESFERA'!C12 -> 5.4146161 | AR12: ='[12]AD ESFERA'!D12 -> 16.293161 | AS12: ='[12]AD ESFERA'!E12 -> 1076.2459 | AT12: ='[13]AD ESFERA'!B12 -> 242.23414 | AU12: ='[13]AD ESFERA'!C12 -> 5.5350319 | AV12: ='[13]AD ESFERA'!D12 -> 16.239843 | AW12: ='[13]AD ESFERA'!E12 -> 1227.1418 | AX12: ='[14]AD ESFERA'!B12 -> 269.00561 | AY12: ='[14]AD ESFERA'!C12 -> 5.5871033 | AZ12: ='[14]AD ESFERA'!D12 -> 16.421695 | BA12: ='[14]AD ESFERA'!E12 -> 1350.142 | BB12: ='[15]AD ESFERA'!B12 -> 292.7361 | BC12: ='[15]AD ESFERA'!C12 -> 5.4905668 | BD12: ='[15]AD ESFERA'!D12 -> 16.333477 | BE12: ='[15]AD ESFERA'!E12 -> 1456.1615 | BF12: ='[16]AD ESFERA'!B12 -> 312.81126 | BG12: ='[16]AD ESFERA'!C12 -> 5.4129401 | BH12: ='[16]AD ESFERA'!D12 -> 16.465646 | BI12: ='[16]AD ESFERA'!E12 -> 1542.701 | BJ12: ='[17]AD ESFERA'!B12 -> 315.94696 | BK12: ='[17]AD ESFERA'!C12 -> 5.2694828 | BL12: ='[17]AD ESFERA'!D12 -> 16.04581 | BM12: ='[17]AD ESFERA'!E12 -> 1545.3459 | BN12: ='[18]AD ESFERA'!B12 -> 333.76555 | BO12: ='[18]AD ESFERA'!C12 -> 5.3255886 | BP12: ='[18]AD ESFERA'!D12 -> 15.999066 | BQ12: ='[18]AD ESFERA'!E12 -> 1619.5809 | BR12: ='[19]AD ESFERA'!B12 -> 351.88658 | BS12: ='[19]AD ESFERA'!C12 -> 5.3691643 | BT12: ='[19]AD ESFERA'!D12 -> 15.970131 | BU12: ='[19]AD ESFERA'!E12 -> 1694.5247 | BV12: ='[20]AD ESFERA'!B12 -> 371.2967 | BW12: ='[20]AD ESFERA'!C12 -> 5.3895661 | BX12: ='[20]AD ESFERA'!D12 -> 15.648043 | BY12: ='[20]AD ESFERA'!E12 -> 1780.8431 | BZ12: ='[21]AD ESFERA'!B12 -> 394.94103 | CA12: ='[21]AD ESFERA'!C12 -> 5.3448914 | CB12: ='[21]AD ESFERA'!D12 -> 15.817101 | CC12: ='[21]AD ESFERA'!E12 -> 1879.3549 | CD12: ='[22]AD ESFERA'!B12 -> 386.78782 | CE12: ='[22]AD ESFERA'!C12 -> 5.0828949 | CF12: ='[22]AD ESFERA'!D12 -> 15.777229 | CG12: ='[22]AD ESFERA'!E12 -> 1826.5758 | CH12: ='[23]AD ESFERA'!B12 -> 443.13288 | CI12: ='[23]AD ESFERA'!C12 -> 4.9797333 | CJ12: ='[23]AD ESFERA'!D12 -> 14.476898 | CK12: ='[23]AD ESFERA'!E12 -> 2077.3382 | CL12: ='[24]AD ESFERA'!B12 -> 514.64479 | CM12: ='[24]AD ESFERA'!C12 -> 5.1057672 | CN12: ='[24]AD ESFERA'!D12 -> 14.626838 | CO12: ='[24]AD ESFERA'!E12 -> 2534.1879 | CP12: ='[25]AD ESFERA'!B12 -> 534.84268 | CQ12: ='[25]AD ESFERA'!C12 -> 4.8873788 | CR12: ='[25]AD ESFERA'!D12 -> 14.134367 | CS12: ='[25]AD ESFERA'!E12 -> 2573.4344 | CT12: ='[26]AD ESFERA'!B12 -> 611.64221 | CU12: ='[26]AD ESFERA'!C12 -> 5.2078107 | CV12: ='[26]AD ESFERA'!D12 -> 14.486264 | CW12: ='[26]AD ESFERA'!E12 -> 2877.1823
